Workbook

Sheet TenantGuard unit economics
A1: TenantGuard unit economics
A2: TenantGuard — Business Plan · Main Scenario
A4: Variable / dimension | B4: Value
A5: Cost per completed remediation | B5: ='TenantGuard inputs'!B9*'TenantGuard inputs'!B7+'TenantGuard inputs'!B10 -> 0.0425
A6: Monthly compute cost per customer | B6: ='TenantGuard unit economics'!B5*'TenantGuard inputs'!B8 -> 4.25
A7: Unit compute gross margin | B7: =1-'TenantGuard unit economics'!B6/'TenantGuard inputs'!B6 -> 0.99346154
A8: Break-even customers | B8: =CEILING('TenantGuard inputs'!B12/('TenantGuard inputs'!B6-'TenantGuard unit economics'!B6),1) -> 78
A9: Revenue in first 12 months | B9: =SUM('TenantGuard three-case revenue'!B6,'TenantGuard three-case revenue'!E6,'TenantGuard three-case revenue'!H6,'TenantGuard three-case revenue'!K6,'TenantGuard three-case revenue'!N6,'TenantGuard three-case revenue'!Q6,'TenantGuard three-case revenue'!T6,'TenantGuard three-case revenue'!W6,'TenantGuard three-case revenue'!Z6,'TenantGuard three-case revenue'!AC6,'TenantGuard three-case revenue'!AF6,'TenantGuard three-case revenue'!AI6) -> 507000
A10: Cash at month 12 | B10: =IF('TenantGuard three-case revenue'!AI8="","",'TenantGuard three-case revenue'!AI8) -> 803685
A11: Runway months under plateau | B11: =IF(IF(IF(ISERROR('Model inputs'!O29<0),'Model inputs'!O29<0,IF('Model inputs'!O29="","",'Model inputs'!O29<0))="",FALSE,IF(ISERROR('Model inputs'!O29<0),'Model inputs'!O29<0,IF('Model inputs'!O29="","",'Model inputs'!O29<0))),12+'TenantGuard unit economics'!B10/(-'Model inputs'!O29),"")
A12: No-revenue runway months | B12: ='TenantGuard inputs'!B13/'TenantGuard inputs'!B12 -> 18

Sheet TenantGuard three-case revenue
A1: TenantGuard three-case revenue ramp
A2: TenantGuard — Business Plan · Main Scenario
A4: Variable / dimension | B4: 2026-10 | C4: 2026-10 > TenantGuard — Low | D4: 2026-10 > TenantGuard — High | E4: 2026-11 | F4: 2026-11 > TenantGuard — Low | G4: 2026-11 > TenantGuard — High | H4: 2026-12 | I4: 2026-12 > TenantGuard — Low | J4: 2026-12 > TenantGuard — High | K4: 2027-01 | L4: 2027-01 > TenantGuard — Low | M4: 2027-01 > TenantGuard — High | N4: 2027-02 | O4: 2027-02 > TenantGuard — Low | P4: 2027-02 > TenantGuard — High | Q4: 2027-03 | R4: 2027-03 > TenantGuard — Low | S4: 2027-03 > TenantGuard — High | T4: 2027-04 | U4: 2027-04 > TenantGuard — Low | V4: 2027-04 > TenantGuard — High | W4: 2027-05 | X4: 2027-05 > TenantGuard — Low | Y4: 2027-05 > TenantGuard — High | Z4: 2027-06 | AA4: 2027-06 > TenantGuard — Low | AB4: 2027-06 > TenantGuard — High | AC4: 2027-07 | AD4: 2027-07 > TenantGuard — Low | AE4: 2027-07 > TenantGuard — High | AF4: 2027-08 | AG4: 2027-08 > TenantGuard — Low | AH4: 2027-08 > TenantGuard — High | AI4: 2027-09 | AJ4: 2027-09 > TenantGuard — Low | AK4: 2027-09 > TenantGuard — High
A5: Ending customers | B5: ='Model inputs'!D23+'Model inputs'!D16-'Model inputs'!D13 -> 10 | C5: ='Model inputs'!D25+'Model inputs'!D18-'Model inputs'!D15 -> 3.3333333 | D5: ='Model inputs'!D24+'Model inputs'!D17-'Model inputs'!D14 -> 21.666667 | E5: ='Model inputs'!E23+'Model inputs'!E16-'Model inputs'!E13 -> 20 | F5: ='Model inputs'!E25+'Model inputs'!E18-'Model inputs'!E15 -> 6.6666667 | G5: ='Model inputs'!E24+'Model inputs'!E17-'Model inputs'!E14 -> 43.333333 | H5: ='Model inputs'!F23+'Model inputs'!F16-'Model inputs'!F13 -> 30 | I5: ='Model inputs'!F25+'Model inputs'!F18-'Model inputs'!F15 -> 10 | J5: ='Model inputs'!F24+'Model inputs'!F17-'Model inputs'!F14 -> 65 | K5: ='Model inputs'!G23+'Model inputs'!G16-'Model inputs'!G13 -> 40 | L5: ='Model inputs'!G25+'Model inputs'!G18-'Model inputs'!G15 -> 13.333333 | M5: ='Model inputs'!G24+'Model inputs'!G17-'Model inputs'!G14 -> 86.666667 | N5: ='Model inputs'!H23+'Model inputs'!H16-'Model inputs'!H13 -> 50 | O5: ='Model inputs'!H25+'Model inputs'!H18-'Model inputs'!H15 -> 16.666667 | P5: ='Model inputs'!H24+'Model inputs'!H17-'Model inputs'!H14 -> 108.33333 | Q5: ='Model inputs'!I23+'Model inputs'!I16-'Model inputs'!I13 -> 60 | R5: ='Model inputs'!I25+'Model inputs'!I18-'Model inputs'!I15 -> 20 | S5: ='Model inputs'!I24+'Model inputs'!I17-'Model inputs'!I14 -> 130 | T5: ='Model inputs'!J23+'Model inputs'!J16-'Model inputs'!J13 -> 70 | U5: ='Model inputs'!J25+'Model inputs'!J18-'Model inputs'!J15 -> 23.333333 | V5: ='Model inputs'!J24+'Model inputs'!J17-'Model inputs'!J14 -> 151.66667 | W5: ='Model inputs'!K23+'Model inputs'!K16-'Model inputs'!K13 -> 80 | X5: ='Model inputs'!K25+'Model inputs'!K18-'Model inputs'!K15 -> 26.666667 | Y5: ='Model inputs'!K24+'Model inputs'!K17-'Model inputs'!K14 -> 173.33333 | Z5: ='Model inputs'!L23+'Model inputs'!L16-'Model inputs'!L13 -> 90 | AA5: ='Model inputs'!L25+'Model inputs'!L18-'Model inputs'!L15 -> 30 | AB5: ='Model inputs'!L24+'Model inputs'!L17-'Model inputs'!L14 -> 195 | AC5: ='Model inputs'!M23+'Model inputs'!M16-'Model inputs'!M13 -> 100 | AD5: ='Model inputs'!M25+'Model inputs'!M18-'Model inputs'!M15 -> 33.333333 | AE5: ='Model inputs'!M24+'Model inputs'!M17-'Model inputs'!M14 -> 216.66667 | AF5: ='Model inputs'!N23+'Model inputs'!N16-'Model inputs'!N13 -> 110 | AG5: ='Model inputs'!N25+'Model inputs'!N18-'Model inputs'!N15 -> 36.666667 | AH5: ='Model inputs'!N24+'Model inputs'!N17-'Model inputs'!N14 -> 238.33333 | AI5: ='Model inputs'!O23+'Model inputs'!O16-'Model inputs'!O13 -> 120 | AJ5: ='Model inputs'!O25+'Model inputs'!O18-'Model inputs'!O15 -> 40 | AK5: ='Model inputs'!O24+'Model inputs'!O17-'Model inputs'!O14 -> 260
A6: TenantGuard revenue | B6: ='TenantGuard three-case revenue'!B5*'TenantGuard inputs'!B6 -> 6500 | C6: ='TenantGuard three-case revenue'!C5*'Model inputs'!C9 -> 1500 | D6: ='TenantGuard three-case revenue'!D5*'Model inputs'!C8 -> 18416.667 | E6: ='TenantGuard three-case revenue'!E5*'TenantGuard inputs'!B6 -> 13000 | F6: ='TenantGuard three-case revenue'!F5*'Model inputs'!C9 -> 3000 | G6: ='TenantGuard three-case revenue'!G5*'Model inputs'!C8 -> 36833.333 | H6: ='TenantGuard three-case revenue'!H5*'TenantGuard inputs'!B6 -> 19500 | I6: ='TenantGuard three-case revenue'!I5*'Model inputs'!C9 -> 4500 | J6: ='TenantGuard three-case revenue'!J5*'Model inputs'!C8 -> 55250 | K6: ='TenantGuard three-case revenue'!K5*'TenantGuard inputs'!B6 -> 26000 | L6: ='TenantGuard three-case revenue'!L5*'Model inputs'!C9 -> 6000 | M6: ='TenantGuard three-case revenue'!M5*'Model inputs'!C8 -> 73666.667 | N6: ='TenantGuard three-case revenue'!N5*'TenantGuard inputs'!B6 -> 32500 | O6: ='TenantGuard three-case revenue'!O5*'Model inputs'!C9 -> 7500 | P6: ='TenantGuard three-case revenue'!P5*'Model inputs'!C8 -> 92083.333 | Q6: ='TenantGuard three-case revenue'!Q5*'TenantGuard inputs'!B6 -> 39000 | R6: ='TenantGuard three-case revenue'!R5*'Model inputs'!C9 -> 9000 | S6: ='TenantGuard three-case revenue'!S5*'Model inputs'!C8 -> 110500 | T6: ='TenantGuard three-case revenue'!T5*'TenantGuard inputs'!B6 -> 45500 | U6: ='TenantGuard three-case revenue'!U5*'Model inputs'!C9 -> 10500 | V6: ='TenantGuard three-case revenue'!V5*'Model inputs'!C8 -> 128916.67 | W6: ='TenantGuard three-case revenue'!W5*'TenantGuard inputs'!B6 -> 52000 | X6: ='TenantGuard three-case revenue'!X5*'Model inputs'!C9 -> 12000 | Y6: ='TenantGuard three-case revenue'!Y5*'Model inputs'!C8 -> 147333.33 | Z6: ='TenantGuard three-case revenue'!Z5*'TenantGuard inputs'!B6 -> 58500 | AA6: ='TenantGuard three-case revenue'!AA5*'Model inputs'!C9 -> 13500 | AB6: ='TenantGuard three-case revenue'!AB5*'Model inputs'!C8 -> 165750 | AC6: ='TenantGuard three-case revenue'!AC5*'TenantGuard inputs'!B6 -> 65000 | AD6: ='TenantGuard three-case revenue'!AD5*'Model inputs'!C9 -> 15000 | AE6: ='TenantGuard three-case revenue'!AE5*'Model inputs'!C8 -> 184166.67 | AF6: ='TenantGuard three-case revenue'!AF5*'TenantGuard inputs'!B6 -> 71500 | AG6: ='TenantGuard three-case revenue'!AG5*'Model inputs'!C9 -> 16500 | AH6: ='TenantGuard three-case revenue'!AH5*'Model inputs'!C8 -> 202583.33 | AI6: ='TenantGuard three-case revenue'!AI5*'TenantGuard inputs'!B6 -> 78000 | AJ6: ='TenantGuard three-case revenue'!AJ5*'Model inputs'!C9 -> 18000 | AK6: ='TenantGuard three-case revenue'!AK5*'Model inputs'!C8 -> 221000
A7: Compute gross margin | B7: =IFERROR('Model inputs'!D10/'TenantGuard three-case revenue'!B6,"") -> 0.99346154 | C7: =IFERROR('Model inputs'!D12/'TenantGuard three-case revenue'!C6,"") -> 0.98777778 | D7: =IFERROR('Model inputs'!D11/'TenantGuard three-case revenue'!D6,"") -> 0.99529412 | E7: =IFERROR('Model inputs'!E10/'TenantGuard three-case revenue'!E6,"") -> 0.99346154 | F7: =IFERROR('Model inputs'!E12/'TenantGuard three-case revenue'!F6,"") -> 0.98777778 | G7: =IFERROR('Model inputs'!E11/'TenantGuard three-case revenue'!G6,"") -> 0.99529412 | H7: =IFERROR('Model inputs'!F10/'TenantGuard three-case revenue'!H6,"") -> 0.99346154 | I7: =IFERROR('Model inputs'!F12/'TenantGuard three-case revenue'!I6,"") -> 0.98777778 | J7: =IFERROR('Model inputs'!F11/'TenantGuard three-case revenue'!J6,"") -> 0.99529412 | K7: =IFERROR('Model inputs'!G10/'TenantGuard three-case revenue'!K6,"") -> 0.99346154 | L7: =IFERROR('Model inputs'!G12/'TenantGuard three-case revenue'!L6,"") -> 0.98777778 | M7: =IFERROR('Model inputs'!G11/'TenantGuard three-case revenue'!M6,"") -> 0.99529412 | N7: =IFERROR('Model inputs'!H10/'TenantGuard three-case revenue'!N6,"") -> 0.99346154 | O7: =IFERROR('Model inputs'!H12/'TenantGuard three-case revenue'!O6,"") -> 0.98777778 | P7: =IFERROR('Model inputs'!H11/'TenantGuard three-case revenue'!P6,"") -> 0.99529412 | Q7: =IFERROR('Model inputs'!I10/'TenantGuard three-case revenue'!Q6,"") -> 0.99346154 | R7: =IFERROR('Model inputs'!I12/'TenantGuard three-case revenue'!R6,"") -> 0.98777778 | S7: =IFERROR('Model inputs'!I11/'TenantGuard three-case revenue'!S6,"") -> 0.99529412 | T7: =IFERROR('Model inputs'!J10/'TenantGuard three-case revenue'!T6,"") -> 0.99346154 | U7: =IFERROR('Model inputs'!J12/'TenantGuard three-case revenue'!U6,"") -> 0.98777778 | V7: =IFERROR('Model inputs'!J11/'TenantGuard three-case revenue'!V6,"") -> 0.99529412 | W7: =IFERROR('Model inputs'!K10/'TenantGuard three-case revenue'!W6,"") -> 0.99346154 | X7: =IFERROR('Model inputs'!K12/'TenantGuard three-case revenue'!X6,"") -> 0.98777778 | Y7: =IFERROR('Model inputs'!K11/'TenantGuard three-case revenue'!Y6,"") -> 0.99529412 | Z7: =IFERROR('Model inputs'!L10/'TenantGuard three-case revenue'!Z6,"") -> 0.99346154 | AA7: =IFERROR('Model inputs'!L12/'TenantGuard three-case revenue'!AA6,"") -> 0.98777778 | AB7: =IFERROR('Model inputs'!L11/'TenantGuard three-case revenue'!AB6,"") -> 0.99529412 | AC7: =IFERROR('Model inputs'!M10/'TenantGuard three-case revenue'!AC6,"") -> 0.99346154 | AD7: =IFERROR('Model inputs'!M12/'TenantGuard three-case revenue'!AD6,"") -> 0.98777778 | AE7: =IFERROR('Model inputs'!M11/'TenantGuard three-case revenue'!AE6,"") -> 0.99529412 | AF7: =IFERROR('Model inputs'!N10/'TenantGuard three-case revenue'!AF6,"") -> 0.99346154 | AG7: =IFERROR('Model inputs'!N12/'TenantGuard three-case revenue'!AG6,"") -> 0.98777778 | AH7: =IFERROR('Model inputs'!N11/'TenantGuard three-case revenue'!AH6,"") -> 0.99529412 | AI7: =IFERROR('Model inputs'!O10/'TenantGuard three-case revenue'!AI6,"") -> 0.99346154 | AJ7: =IFERROR('Model inputs'!O12/'TenantGuard three-case revenue'!AJ6,"") -> 0.98777778 | AK7: =IFERROR('Model inputs'!O11/'TenantGuard three-case revenue'!AK6,"") -> 0.99529412
A8: TenantGuard ending cash | B8: =IF(IF(DATE(2026,10,1)=DATE(2026,10,1),IF('TenantGuard inputs'!B13="","",'TenantGuard inputs'!B13),IF('Model inputs'!X26="","",'Model inputs'!X26))="",0,IF(DATE(2026,10,1)=DATE(2026,10,1),IF('TenantGuard inputs'!B13="","",'TenantGuard inputs'!B13),IF('Model inputs'!X26="","",'Model inputs'!X26)))+'Model inputs'!D29 -> 856457.5 | C8: =IF(IF(DATE(2026,10,1)=DATE(2026,10,1),IF('Model inputs'!C22="","",'Model inputs'!C22),IF('Model inputs'!X28="","",'Model inputs'!X28))="",0,IF(DATE(2026,10,1)=DATE(2026,10,1),IF('Model inputs'!C22="","",'Model inputs'!C22),IF('Model inputs'!X28="","",'Model inputs'!X28)))+'Model inputs'!D31 -> 851481.67 | D8: =IF(IF(DATE(2026,10,1)=DATE(2026,10,1),IF('Model inputs'!C21="","",'Model inputs'!C21),IF('Model inputs'!X27="","",'Model inputs'!X27))="",0,IF(DATE(2026,10,1)=DATE(2026,10,1),IF('Model inputs'!C21="","",'Model inputs'!C21),IF('Model inputs'!X27="","",'Model inputs'!X27)))+'Model inputs'!D30 -> 868330 | E8: =IF(IF(DATE(2026,11,1)=DATE(2026,10,1),IF('TenantGuard inputs'!B13="","",'TenantGuard inputs'!B13),IF('TenantGuard three-case revenue'!B8="","",'TenantGuard three-case revenue'!B8))="",0,IF(DATE(2026,11,1)=DATE(2026,10,1),IF('TenantGuard inputs'!B13="","",'TenantGuard inputs'!B13),IF('TenantGuard three-case revenue'!B8="","",'TenantGuard three-case revenue'!B8)))+'Model inputs'!E29 -> 819372.5 | F8: =IF(IF(DATE(2026,11,1)=DATE(2026,10,1),IF('Model inputs'!C22="","",'Model inputs'!C22),IF('TenantGuard three-case revenue'!C8="","",'TenantGuard three-case revenue'!C8))="",0,IF(DATE(2026,11,1)=DATE(2026,10,1),IF('Model inputs'!C22="","",'Model inputs'!C22),IF('TenantGuard three-case revenue'!C8="","",'TenantGuard three-case revenue'!C8)))+'Model inputs'!E31 -> 804445 | G8: =IF(IF(DATE(2026,11,1)=DATE(2026,10,1),IF('Model inputs'!C21="","",'Model inputs'!C21),IF('TenantGuard three-case revenue'!D8="","",'TenantGuard three-case revenue'!D8))="",0,IF(DATE(2026,11,1)=DATE(2026,10,1),IF('Model inputs'!C21="","",'Model inputs'!C21),IF('TenantGuard three-case revenue'!D8="","",'TenantGuard three-case revenue'!D8)))+'Model inputs'!E30 -> 854990 | H8: =IF(IF(DATE(2026,12,1)=DATE(2026,10,1),IF('TenantGuard inputs'!B13="","",'TenantGuard inputs'!B13),IF('TenantGuard three-case revenue'!E8="","",'TenantGuard three-case revenue'!E8))="",0,IF(DATE(2026,12,1)=DATE(2026,10,1),IF('TenantGuard inputs'!B13="","",'TenantGuard inputs'!B13),IF('TenantGuard three-case revenue'!E8="","",'TenantGuard three-case revenue'!E8)))+'Model inputs'!F29 -> 788745 | I8: =IF(IF(DATE(2026,12,1)=DATE(2026,10,1),IF('Model inputs'!C22="","",'Model inputs'!C22),IF('TenantGuard three-case revenue'!F8="","",'TenantGuard three-case revenue'!F8))="",0,IF(DATE(2026,12,1)=DATE(2026,10,1),IF('Model inputs'!C22="","",'Model inputs'!C22),IF('TenantGuard three-case revenue'!F8="","",'TenantGuard three-case revenue'!F8)))+'Model inputs'!F31 -> 758890 | J8: =IF(IF(DATE(2026,12,1)=DATE(2026,10,1),IF('Model inputs'!C21="","",'Model inputs'!C21),IF('TenantGuard three-case revenue'!G8="","",'TenantGuard three-case revenue'!G8))="",0,IF(DATE(2026,12,1)=DATE(2026,10,1),IF('Model inputs'!C21="","",'Model inputs'!C21),IF('TenantGuard three-case revenue'!G8="","",'TenantGuard three-case revenue'!G8)))+'Model inputs'!F30 -> 859980 | K8: =IF(IF(DATE(2027,1,1)=DATE(2026,10,1),IF('TenantGuard inputs'!B13="","",'TenantGuard inputs'!B13),IF('TenantGuard three-case revenue'!H8="","",'TenantGuard three-case revenue'!H8))="",0,IF(DATE(2027,1,1)=DATE(2026,10,1),IF('TenantGuard inputs'!B13="","",'TenantGuard inputs'!B13),IF('TenantGuard three-case revenue'!H8="","",'TenantGuard three-case revenue'!H8)))+'Model inputs'!G29 -> 764575 | L8: =IF(IF(DATE(2027,1,1)=DATE(2026,10,1),IF('Model inputs'!C22="","",'Model inputs'!C22),IF('TenantGuard three-case revenue'!I8="","",'TenantGuard three-case revenue'!I8))="",0,IF(DATE(2027,1,1)=DATE(2026,10,1),IF('Model inputs'!C22="","",'Model inputs'!C22),IF('TenantGuard three-case revenue'!I8="","",'TenantGuard three-case revenue'!I8)))+'Model inputs'!G31 -> 714816.67 | M8: =IF(IF(DATE(2027,1,1)=DATE(2026,10,1),IF('Model inputs'!C21="","",'Model inputs'!C21),IF('TenantGuard three-case revenue'!J8="","",'TenantGuard three-case revenue'!J8))="",0,IF(DATE(2027,1,1)=DATE(2026,10,1),IF('Model inputs'!C21="","",'Model inputs'!C21),IF('TenantGuard three-case revenue'!J8="","",'TenantGuard three-case revenue'!J8)))+'Model inputs'!G30 -> 883300 | N8: =IF(IF(DATE(2027,2,1)=DATE(2026,10,1),IF('TenantGuard inputs'!B13="","",'TenantGuard inputs'!B13),IF('TenantGuard three-case revenue'!K8="","",'TenantGuard three-case revenue'!K8))="",0,IF(DATE(2027,2,1)=DATE(2026,10,1),IF('TenantGuard inputs'!B13="","",'TenantGuard inputs'!B13),IF('TenantGuard three-case revenue'!K8="","",'TenantGuard three-case revenue'!K8)))+'Model inputs'!H29 -> 746862.5 | O8: =IF(IF(DATE(2027,2,1)=DATE(2026,10,1),IF('Model inputs'!C22="","",'Model inputs'!C22),IF('TenantGuard three-case revenue'!L8="","",'TenantGuard three-case revenue'!L8))="",0,IF(DATE(2027,2,1)=DATE(2026,10,1),IF('Model inputs'!C22="","",'Model inputs'!C22),IF('TenantGuard three-case revenue'!L8="","",'TenantGuard three-case revenue'!L8)))+'Model inputs'!H31 -> 672225 | P8: =IF(IF(DATE(2027,2,1)=DATE(2026,10,1),IF('Model inputs'!C21="","",'Model inputs'!C21),IF('TenantGuard three-case revenue'!M8="","",'TenantGuard three-case revenue'!M8))="",0,IF(DATE(2027,2,1)=DATE(2026,10,1),IF('Model inputs'!C21="","",'Model inputs'!C21),IF('TenantGuard three-case revenue'!M8="","",'TenantGuard three-case revenue'!M8)))+'Model inputs'!H30 -> 924950 | Q8: =IF(IF(DATE(2027,3,1)=DATE(2026,10,1),IF('TenantGuard inputs'!B13="","",'TenantGuard inputs'!B13),IF('TenantGuard three-case revenue'!N8="","",'TenantGuard three-case revenue'!N8))="",0,IF(DATE(2027,3,1)=DATE(2026,10,1),IF('TenantGuard inputs'!B13="","",'TenantGuard inputs'!B13),IF('TenantGuard three-case revenue'!N8="","",'TenantGuard three-case revenue'!N8)))+'Model inputs'!I29 -> 735607.5 | R8: =IF(IF(DATE(2027,3,1)=DATE(2026,10,1),IF('Model inputs'!C22="","",'Model inputs'!C22),IF('TenantGuard three-case revenue'!O8="","",'TenantGuard three-case revenue'!O8))="",0,IF(DATE(2027,3,1)=DATE(2026,10,1),IF('Model inputs'!C22="","",'Model inputs'!C22),IF('TenantGuard three-case revenue'!O8="","",'TenantGuard three-case revenue'!O8)))+'Model inputs'!I31 -> 631115 | S8: =IF(IF(DATE(2027,3,1)=DATE(2026,10,1),IF('Model inputs'!C21="","",'Model inputs'!C21),IF('TenantGuard three-case revenue'!P8="","",'TenantGuard three-case revenue'!P8))="",0,IF(DATE(2027,3,1)=DATE(2026,10,1),IF('Model inputs'!C21="","",'Model inputs'!C21),IF('TenantGuard three-case revenue'!P8="","",'TenantGuard three-case revenue'!P8)))+'Model inputs'!I30 -> 984930 | T8: =IF(IF(DATE(2027,4,1)=DATE(2026,10,1),IF('TenantGuard inputs'!B13="","",'TenantGuard inputs'!B13),IF('TenantGuard three-case revenue'!Q8="","",'TenantGuard three-case revenue'!Q8))="",0,IF(DATE(2027,4,1)=DATE(2026,10,1),IF('TenantGuard inputs'!B13="","",'TenantGuard inputs'!B13),IF('TenantGuard three-case revenue'!Q8="","",'TenantGuard three-case revenue'!Q8)))+'Model inputs'!J29 -> 730810 | U8: =IF(IF(DATE(2027,4,1)=DATE(2026,10,1),IF('Model inputs'!C22="","",'Model inputs'!C22),IF('TenantGuard three-case revenue'!R8="","",'TenantGuard three-case revenue'!R8))="",0,IF(DATE(2027,4,1)=DATE(2026,10,1),IF('Model inputs'!C22="","",'Model inputs'!C22),IF('TenantGuard three-case revenue'!R8="","",'TenantGuard three-case revenue'!R8)))+'Model inputs'!J31 -> 591486.67 | V8: =IF(IF(DATE(2027,4,1)=DATE(2026,10,1),IF('Model inputs'!C21="","",'Model inputs'!C21),IF('TenantGuard three-case revenue'!S8="","",'TenantGuard three-case revenue'!S8))="",0,IF(DATE(2027,4,1)=DATE(2026,10,1),IF('Model inputs'!C21="","",'Model inputs'!C21),IF('TenantGuard three-case revenue'!S8="","",'TenantGuard three-case revenue'!S8)))+'Model inputs'!J30 -> 1063240 | W8: =IF(IF(DATE(2027,5,1)=DATE(2026,10,1),IF('TenantGuard inputs'!B13="","",'TenantGuard inputs'!B13),IF('TenantGuard three-case revenue'!T8="","",'TenantGuard three-case revenue'!T8))="",0,IF(DATE(2027,5,1)=DATE(2026,10,1),IF('TenantGuard inputs'!B13="","",'TenantGuard inputs'!B13),IF('TenantGuard three-case revenue'!T8="","",'TenantGuard three-case revenue'!T8)))+'Model inputs'!K29 -> 732470 | X8: =IF(IF(DATE(2027,5,1)=DATE(2026,10,1),IF('Model inputs'!C22="","",'Model inputs'!C22),IF('TenantGuard three-case revenue'!U8="","",'TenantGuard three-case revenue'!U8))="",0,IF(DATE(2027,5,1)=DATE(2026,10,1),IF('Model inputs'!C22="","",'Model inputs'!C22),IF('TenantGuard three-case revenue'!U8="","",'TenantGuard three-case revenue'!U8)))+'Model inputs'!K31 -> 553340 | Y8: =IF(IF(DATE(2027,5,1)=DATE(2026,10,1),IF('Model inputs'!C21="","",'Model inputs'!C21),IF('TenantGuard three-case revenue'!V8="","",'TenantGuard three-case revenue'!V8))="",0,IF(DATE(2027,5,1)=DATE(2026,10,1),IF('Model inputs'!C21="","",'Model inputs'!C21),IF('TenantGuard three-case revenue'!V8="","",'TenantGuard three-case revenue'!V8)))+'Model inputs'!K30 -> 1159880 | Z8: =IF(IF(DATE(2027,6,1)=DATE(2026,10,1),IF('TenantGuard inputs'!B13="","",'TenantGuard inputs'!B13),IF('TenantGuard three-case revenue'!W8="","",'TenantGuard three-case revenue'!W8))="",0,IF(DATE(2027,6,1)=DATE(2026,10,1),IF('TenantGuard inputs'!B13="","",'TenantGuard inputs'!B13),IF('TenantGuard three-case revenue'!W8="","",'TenantGuard three-case revenue'!W8)))+'Model inputs'!L29 -> 740587.5 | AA8: =IF(IF(DATE(2027,6,1)=DATE(2026,10,1),IF('Model inputs'!C22="","",'Model inputs'!C22),IF('TenantGuard three-case revenue'!X8="","",'TenantGuard three-case revenue'!X8))="",0,IF(DATE(2027,6,1)=DATE(2026,10,1),IF('Model inputs'!C22="","",'Model inputs'!C22),IF('TenantGuard three-case revenue'!X8="","",'TenantGuard three-case revenue'!X8)))+'Model inputs'!L31 -> 516675 | AB8: =IF(IF(DATE(2027,6,1)=DATE(2026,10,1),IF('Model inputs'!C21="","",'Model inputs'!C21),IF('TenantGuard three-case revenue'!Y8="","",'TenantGuard three-case revenue'!Y8))="",0,IF(DATE(2027,6,1)=DATE(2026,10,1),IF('Model inputs'!C21="","",'Model inputs'!C21),IF('TenantGuard three-case revenue'!Y8="","",'TenantGuard three-case revenue'!Y8)))+'Model inputs'!L30 -> 1274850 | AC8: =IF(IF(DATE(2027,7,1)=DATE(2026,10,1),IF('TenantGuard inputs'!B13="","",'TenantGuard inputs'!B13),IF('TenantGuard three-case revenue'!Z8="","",'TenantGuard three-case revenue'!Z8))="",0,IF(DATE(2027,7,1)=DATE(2026,10,1),IF('TenantGuard inputs'!B13="","",'TenantGuard inputs'!B13),IF('TenantGuard three-case revenue'!Z8="","",'TenantGuard three-case revenue'!Z8)))+'Model inputs'!M29 -> 755162.5 | AD8: =IF(IF(DATE(2027,7,1)=DATE(2026,10,1),IF('Model inputs'!C22="","",'Model inputs'!C22),IF('TenantGuard three-case revenue'!AA8="","",'TenantGuard three-case revenue'!AA8))="",0,IF(DATE(2027,7,1)=DATE(2026,10,1),IF('Model inputs'!C22="","",'Model inputs'!C22),IF('TenantGuard three-case revenue'!AA8="","",'TenantGuard three-case revenue'!AA8)))+'Model inputs'!M31 -> 481491.67 | AE8: =IF(IF(DATE(2027,7,1)=DATE(2026,10,1),IF('Model inputs'!C21="","",'Model inputs'!C21),IF('TenantGuard three-case revenue'!AB8="","",'TenantGuard three-case revenue'!AB8))="",0,IF(DATE(2027,7,1)=DATE(2026,10,1),IF('Model inputs'!C21="","",'Model inputs'!C21),IF('TenantGuard three-case revenue'!AB8="","",'TenantGuard three-case revenue'!AB8)))+'Model inputs'!M30 -> 1408150 | AF8: =IF(IF(DATE(2027,8,1)=DATE(2026,10,1),IF('TenantGuard inputs'!B13="","",'TenantGuard inputs'!B13),IF('TenantGuard three-case revenue'!AC8="","",'TenantGuard three-case revenue'!AC8))="",0,IF(DATE(2027,8,1)=DATE(2026,10,1),IF('TenantGuard inputs'!B13="","",'TenantGuard inputs'!B13),IF('TenantGuard three-case revenue'!AC8="","",'TenantGuard three-case revenue'!AC8)))+'Model inputs'!N29 -> 776195 | AG8: =IF(IF(DATE(2027,8,1)=DATE(2026,10,1),IF('Model inputs'!C22="","",'Model inputs'!C22),IF('TenantGuard three-case revenue'!AD8="","",'TenantGuard three-case revenue'!AD8))="",0,IF(DATE(2027,8,1)=DATE(2026,10,1),IF('Model inputs'!C22="","",'Model inputs'!C22),IF('TenantGuard three-case revenue'!AD8="","",'TenantGuard three-case revenue'!AD8)))+'Model inputs'!N31 -> 447790 | AH8: =IF(IF(DATE(2027,8,1)=DATE(2026,10,1),IF('Model inputs'!C21="","",'Model inputs'!C21),IF('TenantGuard three-case revenue'!AE8="","",'TenantGuard three-case revenue'!AE8))="",0,IF(DATE(2027,8,1)=DATE(2026,10,1),IF('Model inputs'!C21="","",'Model inputs'!C21),IF('TenantGuard three-case revenue'!AE8="","",'TenantGuard three-case revenue'!AE8)))+'Model inputs'!N30 -> 1559780 | AI8: =IF(IF(DATE(2027,9,1)=DATE(2026,10,1),IF('TenantGuard inputs'!B13="","",'TenantGuard inputs'!B13),IF('TenantGuard three-case revenue'!AF8="","",'TenantGuard three-case revenue'!AF8))="",0,IF(DATE(2027,9,1)=DATE(2026,10,1),IF('TenantGuard inputs'!B13="","",'TenantGuard inputs'!B13),IF('TenantGuard three-case revenue'!AF8="","",'TenantGuard three-case revenue'!AF8)))+'Model inputs'!O29 -> 803685 | AJ8: =IF(IF(DATE(2027,9,1)=DATE(2026,10,1),IF('Model inputs'!C22="","",'Model inputs'!C22),IF('TenantGuard three-case revenue'!AG8="","",'TenantGuard three-case revenue'!AG8))="",0,IF(DATE(2027,9,1)=DATE(2026,10,1),IF('Model inputs'!C22="","",'Model inputs'!C22),IF('TenantGuard three-case revenue'!AG8="","",'TenantGuard three-case revenue'!AG8)))+'Model inputs'!O31 -> 415570 | AK8: =IF(IF(DATE(2027,9,1)=DATE(2026,10,1),IF('Model inputs'!C21="","",'Model inputs'!C21),IF('TenantGuard three-case revenue'!AH8="","",'TenantGuard three-case revenue'!AH8))="",0,IF(DATE(2027,9,1)=DATE(2026,10,1),IF('Model inputs'!C21="","",'Model inputs'!C21),IF('TenantGuard three-case revenue'!AH8="","",'TenantGuard three-case revenue'!AH8)))+'Model inputs'!O30 -> 1729740

Sheet TenantGuard inputs
A1: TenantGuard inputs
A2: TenantGuard — Business Plan · Main Scenario
A4: Variable / dimension | B4: Value
A5: Month 12 customers | B5: =120 -> 120
A6: Blended monthly ARPA | B6: =650 -> 650
A7: Attempts per completed fix | B7: =2.5 -> 2.5
A8: Fixes per customer per month | B8: =100 -> 100
A9: Token cost per attempt | B9: =0.005 -> 0.005
A10: Compute cost per completed fix | B10: =0.03 -> 0.03
A11: Monthly customer churn | B11: =0.01 -> 0.01
A12: Fixed monthly operating spend | B12: =50000 -> 50000
A13: Launch cash | B13: =900000 -> 900000

Sheet TenantGuard launch settings
A1: TenantGuard launch settings
A2: TenantGuard — Business Plan · Main Scenario
A4: Variable / dimension | B4: Value
A5: Launch customers | B5: =0 -> 0
A6: Customer ramp months | B6: =12 -> 12

Sheet Model inputs
A1: Model inputs
A2: Integration values are aggregated snapshots; raw source records are not included.
A4: Variables
A5: Variable / segment | B5: Value | C5: Value | D5: 2026-10 | E5: 2026-11 | F5: 2026-12 | G5: 2027-01 | H5: 2027-02 | I5: 2027-03 | J5: 2027-04 | K5: 2027-05 | L5: 2027-06 | M5: 2027-07 | N5: 2027-08 | O5: 2027-09 | P5: 2026-01 | Q5: 2026-02 | R5: 2026-03 | S5: 2026-04 | T5: 2026-05 | U5: 2026-06 | V5: 2026-07 | W5: 2026-08 | X5: 2026-09 | Y5: 2027-10 | Z5: 2027-11 | AA5: 2027-12 | AB5: 2028-01 | AC5: 2028-02 | AD5: 2028-03 | AE5: 2028-04 | AF5: 2028-05 | AG5: 2028-06 | AH5: 2028-07 | AI5: 2028-08 | AJ5: 2028-09 | AK5: 2028-10 | AL5: 2028-11 | AM5: 2028-12 | AN5: 2029-01 | AO5: 2029-02 | AP5: 2029-03 | AQ5: 2029-04 | AR5: 2029-05 | AS5: 2029-06 | AT5: 2029-07 | AU5: 2029-08 | AV5: 2029-09
A6: Blended monthly ARPA · TenantGuard unit economics · Main Scenario | B6: ='TenantGuard inputs'!B6 -> 650
A7: Blended monthly ARPA · TenantGuard three-case revenue ramp · Main Scenario | C7: ='TenantGuard inputs'!B6 -> 650
A8: Blended monthly ARPA · TenantGuard — High | C8: =850 -> 850
A9: Blended monthly ARPA · TenantGuard — Low | C9: =450 -> 450
A10: Compute gross profit · Main Scenario | D10: ='Model inputs'!D32-'Model inputs'!D56 -> 6457.5 | E10: ='Model inputs'!E32-'Model inputs'!E56 -> 12915 | F10: ='Model inputs'!F32-'Model inputs'!F56 -> 19372.5 | G10: ='Model inputs'!G32-'Model inputs'!G56 -> 25830 | H10: ='Model inputs'!H32-'Model inputs'!H56 -> 32287.5 | I10: ='Model inputs'!I32-'Model inputs'!I56 -> 38745 | J10: ='Model inputs'!J32-'Model inputs'!J56 -> 45202.5 | K10: ='Model inputs'!K32-'Model inputs'!K56 -> 51660 | ... O10: ='Model inputs'!O32-'Model inputs'!O56 -> 77490
A11: Compute gross profit · TenantGuard — High | D11: ='Model inputs'!D62-'Model inputs'!D57 -> 18330 | E11: ='Model inputs'!E62-'Model inputs'!E57 -> 36660 | F11: ='Model inputs'!F62-'Model inputs'!F57 -> 54990 | G11: ='Model inputs'!G62-'Model inputs'!G57 -> 73320 | H11: ='Model inputs'!H62-'Model inputs'!H57 -> 91650 | I11: ='Model inputs'!I62-'Model inputs'!I57 -> 109980 | J11: ='Model inputs'!J62-'Model inputs'!J57 -> 128310 | K11: ='Model inputs'!K62-'Model inputs'!K57 -> 146640 | ... O11: ='Model inputs'!O62-'Model inputs'!O57 -> 219960
A12: Compute gross profit · TenantGuard — Low | D12: ='Model inputs'!D63-'Model inputs'!D58 -> 1481.6667 | E12: ='Model inputs'!E63-'Model inputs'!E58 -> 2963.3333 | F12: ='Model inputs'!F63-'Model inputs'!F58 -> 4445 | G12: ='Model inputs'!G63-'Model inputs'!G58 -> 5926.6667 | H12: ='Model inputs'!H63-'Model inputs'!H58 -> 7408.3333 | I12: ='Model inputs'!I63-'Model inputs'!I58 -> 8890 | J12: ='Model inputs'!J63-'Model inputs'!J58 -> 10371.667 | K12: ='Model inputs'!K63-'Model inputs'!K58 -> 11853.333 | ... O12: ='Model inputs'!O63-'Model inputs'!O58 -> 17780
A13: Customer losses · TenantGuard three-case revenue ramp · Main Scenario | D13: ='Model inputs'!D23*'Model inputs'!C51 -> 0 | E13: ='Model inputs'!E23*'Model inputs'!C51 -> 0.1 | F13: ='Model inputs'!F23*'Model inputs'!C51 -> 0.2 | G13: ='Model inputs'!G23*'Model inputs'!C51 -> 0.3 | H13: ='Model inputs'!H23*'Model inputs'!C51 -> 0.4 | I13: ='Model inputs'!I23*'Model inputs'!C51 -> 0.5 | J13: ='Model inputs'!J23*'Model inputs'!C51 -> 0.6 | K13: ='Model inputs'!K23*'Model inputs'!C51 -> 0.7 | L13: ='Model inputs'!L23*'Model inputs'!C51 -> 0.8 | M13: ='Model inputs'!M23*'Model inputs'!C51 -> 0.9 | N13: ='Model inputs'!N23*'Model inputs'!C51 -> 1 | O13: ='Model inputs'!O23*'Model inputs'!C51 -> 1.1 | P13: 0 | Q13: 0 | R13: 0 | S13: 0 | T13: 0 | U13: 0 | V13: 0 | W13: 0 | X13: 0
A14: Customer losses · TenantGuard — High | D14: ='Model inputs'!D24*'Model inputs'!C52 -> 0 | E14: ='Model inputs'!E24*'Model inputs'!C52 -> 0.21666667 | F14: ='Model inputs'!F24*'Model inputs'!C52 -> 0.43333333 | G14: ='Model inputs'!G24*'Model inputs'!C52 -> 0.65 | H14: ='Model inputs'!H24*'Model inputs'!C52 -> 0.86666667 | I14: ='Model inputs'!I24*'Model inputs'!C52 -> 1.0833333 | J14: ='Model inputs'!J24*'Model inputs'!C52 -> 1.3 | K14: ='Model inputs'!K24*'Model inputs'!C52 -> 1.5166667 | L14: ='Model inputs'!L24*'Model inputs'!C52 -> 1.7333333 | M14: ='Model inputs'!M24*'Model inputs'!C52 -> 1.95 | N14: ='Model inputs'!N24*'Model inputs'!C52 -> 2.1666667 | O14: ='Model inputs'!O24*'Model inputs'!C52 -> 2.3833333 | X14: 0
A15: Customer losses · TenantGuard — Low | D15: ='Model inputs'!D25*'Model inputs'!C53 -> 0 | E15: ='Model inputs'!E25*'Model inputs'!C53 -> 0.033333333 | F15: ='Model inputs'!F25*'Model inputs'!C53 -> 0.066666667 | G15: ='Model inputs'!G25*'Model inputs'!C53 -> 0.1 | H15: ='Model inputs'!H25*'Model inputs'!C53 -> 0.13333333 | I15: ='Model inputs'!I25*'Model inputs'!C53 -> 0.16666667 | J15: ='Model inputs'!J25*'Model inputs'!C53 -> 0.2 | K15: ='Model inputs'!K25*'Model inputs'!C53 -> 0.23333333 | L15: ='Model inputs'!L25*'Model inputs'!C53 -> 0.26666667 | M15: ='Model inputs'!M25*'Model inputs'!C53 -> 0.3 | N15: ='Model inputs'!N25*'Model inputs'!C53 -> 0.33333333 | O15: ='Model inputs'!O25*'Model inputs'!C53 -> 0.36666667 | X15: 0
A16: Gross customer additions · TenantGuard three-case revenue ramp · Main Scenario | D16: =IF(IF(IF(IF(ISERROR('Model inputs'!D42<='Model inputs'!C36),'Model inputs'!D42<='Model inputs'!C36,IF(OR('Model inputs'!D42="",'Model inputs'!C36=""),"",'Model inputs'!D42<='Model inputs'!C36))="",FALSE,IF(ISERROR('Model inputs'!D42<='Model inputs'!C36),'Model inputs'!D42<='Model inputs'!C36,IF(OR('Model inputs'!D42="",'Model inputs'!C36=""),"",'Model inputs'!D42<='Model inputs'!C36))),('Model inputs'!C48-'Model inputs'!C45)/'Model inputs'!C36,0)="",0,IF(IF(IF(ISERROR('Model inputs'!D42<='Model inputs'!C36),'Model inputs'!D42<='Model inputs'!C36,IF(OR('Model inputs'!D42="",'Model inputs'!C36=""),"",'Model inputs'!D42<='Model inputs'!C36))="",FALSE,IF(ISERROR('Model inputs'!D42<='Model inputs'!C36),'Model inputs'!D42<='Model inputs'!C36,IF(OR('Model inputs'!D42="",'Model inputs'!C36=""),"",'Model inputs'!D42<='Model inputs'!C36))),('Model inputs'!C48-'Model inputs'!C45)/'Model inputs'!C36,0))+'Model inputs'!D23*'Model inputs'!C51 -> 10 | E16: =IF(IF(IF(IF(ISERROR('Model inputs'!E42<='Model inputs'!C36),'Model inputs'!E42<='Model inputs'!C36,IF(OR('Model inputs'!E42="",'Model inputs'!C36=""),"",'Model inputs'!E42<='Model inputs'!C36))="",FALSE,IF(ISERROR('Model inputs'!E42<='Model inputs'!C36),'Model inputs'!E42<='Model inputs'!C36,IF(OR('Model inputs'!E42="",'Model inputs'!C36=""),"",'Model inputs'!E42<='Model inputs'!C36))),('Model inputs'!C48-'Model inputs'!C45)/'Model inputs'!C36,0)="",0,IF(IF(IF(ISERROR('Model inputs'!E42<='Model inputs'!C36),'Model inputs'!E42<='Model inputs'!C36,IF(OR('Model inputs'!E42="",'Model inputs'!C36=""),"",'Model inputs'!E42<='Model inputs'!C36))="",FALSE,IF(ISERROR('Model inputs'!E42<='Model inputs'!C36),'Model inputs'!E42<='Model inputs'!C36,IF(OR('Model inputs'!E42="",'Model inputs'!C36=""),"",'Model inputs'!E42<='Model inputs'!C36))),('Model inputs'!C48-'Model inputs'!C45)/'Model inputs'!C36,0))+'Model inputs'!E23*'Model inputs'!C51 -> 10.1 | F16: =IF(IF(IF(IF(ISERROR('Model inputs'!F42<='Model inputs'!C36),'Model inputs'!F42<='Model inputs'!C36,IF(OR('Model inputs'!F42="",'Model inputs'!C36=""),"",'Model inputs'!F42<='Model inputs'!C36))="",FALSE,IF(ISERROR('Model inputs'!F42<='Model inputs'!C36),'Model inputs'!F42<='Model inputs'!C36,IF(OR('Model inputs'!F42="",'Model inputs'!C36=""),"",'Model inputs'!F42<='Model inputs'!C36))),('Model inputs'!C48-'Model inputs'!C45)/'Model inputs'!C36,0)="",0,IF(IF(IF(ISERROR('Model inputs'!F42<='Model inputs'!C36),'Model inputs'!F42<='Model inputs'!C36,IF(OR('Model inputs'!F42="",'Model inputs'!C36=""),"",'Model inputs'!F42<='Model inputs'!C36))="",FALSE,IF(ISERROR('Model inputs'!F42<='Model inputs'!C36),'Model inputs'!F42<='Model inputs'!C36,IF(OR('Model inputs'!F42="",'Model inputs'!C36=""),"",'Model inputs'!F42<='Model inputs'!C36))),('Model inputs'!C48-'Model inputs'!C45)/'Model inputs'!C36,0))+'Model inputs'!F23*'Model inputs'!C51 -> 10.2 | G16: =IF(IF(IF(IF(ISERROR('Model inputs'!G42<='Model inputs'!C36),'Model inputs'!G42<='Model inputs'!C36,IF(OR('Model inputs'!G42="",'Model inputs'!C36=""),"",'Model inputs'!G42<='Model inputs'!C36))="",FALSE,IF(ISERROR('Model inputs'!G42<='Model inputs'!C36),'Model inputs'!G42<='Model inputs'!C36,IF(OR('Model inputs'!G42="",'Model inputs'!C36=""),"",'Model inputs'!G42<='Model inputs'!C36))),('Model inputs'!C48-'Model inputs'!C45)/'Model inputs'!C36,0)="",0,IF(IF(IF(ISERROR('Model inputs'!G42<='Model inputs'!C36),'Model inputs'!G42<='Model inputs'!C36,IF(OR('Model inputs'!G42="",'Model inputs'!C36=""),"",'Model inputs'!G42<='Model inputs'!C36))="",FALSE,IF(ISERROR('Model inputs'!G42<='Model inputs'!C36),'Model inputs'!G42<='Model inputs'!C36,IF(OR('Model inputs'!G42="",'Model inputs'!C36=""),"",'Model inputs'!G42<='Model inputs'!C36))),('Model inputs'!C48-'Model inputs'!C45)/'Model inputs'!C36,0))+'Model inputs'!G23*'Model inputs'!C51 -> 10.3 | H16: =IF(IF(IF(IF(ISERROR('Model inputs'!H42<='Model inputs'!C36),'Model inputs'!H42<='Model inputs'!C36,IF(OR('Model inputs'!H42="",'Model inputs'!C36=""),"",'Model inputs'!H42<='Model inputs'!C36))="",FALSE,IF(ISERROR('Model inputs'!H42<='Model inputs'!C36),'Model inputs'!H42<='Model inputs'!C36,IF(OR('Model inputs'!H42="",'Model inputs'!C36=""),"",'Model inputs'!H42<='Model inputs'!C36))),('Model inputs'!C48-'Model inputs'!C45)/'Model inputs'!C36,0)="",0,IF(IF(IF(ISERROR('Model inputs'!H42<='Model inputs'!C36),'Model inputs'!H42<='Model inputs'!C36,IF(OR('Model inputs'!H42="",'Model inputs'!C36=""),"",'Model inputs'!H42<='Model inputs'!C36))="",FALSE,IF(ISERROR('Model inputs'!H42<='Model inputs'!C36),'Model inputs'!H42<='Model inputs'!C36,IF(OR('Model inputs'!H42="",'Model inputs'!C36=""),"",'Model inputs'!H42<='Model inputs'!C36))),('Model inputs'!C48-'Model inputs'!C45)/'Model inputs'!C36,0))+'Model inputs'!H23*'Model inputs'!C51 -> 10.4 | I16: =IF(IF(IF(IF(ISERROR('Model inputs'!I42<='Model inputs'!C36),'Model inputs'!I42<='Model inputs'!C36,IF(OR('Model inputs'!I42="",'Model inputs'!C36=""),"",'Model inputs'!I42<='Model inputs'!C36))="",FALSE,IF(ISERROR('Model inputs'!I42<='Model inputs'!C36),'Model inputs'!I42<='Model inputs'!C36,IF(OR('Model inputs'!I42="",'Model inputs'!C36=""),"",'Model inputs'!I42<='Model inputs'!C36))),('Model inputs'!C48-'Model inputs'!C45)/'Model inputs'!C36,0)="",0,IF(IF(IF(ISERROR('Model inputs'!I42<='Model inputs'!C36),'Model inputs'!I42<='Model inputs'!C36,IF(OR('Model inputs'!I42="",'Model inputs'!C36=""),"",'Model inputs'!I42<='Model inputs'!C36))="",FALSE,IF(ISERROR('Model inputs'!I42<='Model inputs'!C36),'Model inputs'!I42<='Model inputs'!C36,IF(OR('Model inputs'!I42="",'Model inputs'!C36=""),"",'Model inputs'!I42<='Model inputs'!C36))),('Model inputs'!C48-'Model inputs'!C45)/'Model inputs'!C36,0))+'Model inputs'!I23*'Model inputs'!C51 -> 10.5 | J16: =IF(IF(IF(IF(ISERROR('Model inputs'!J42<='Model inputs'!C36),'Model inputs'!J42<='Model inputs'!C36,IF(OR('Model inputs'!J42="",'Model inputs'!C36=""),"",'Model inputs'!J42<='Model inputs'!C36))="",FALSE,IF(ISERROR('Model inputs'!J42<='Model inputs'!C36),'Model inputs'!J42<='Model inputs'!C36,IF(OR('Model inputs'!J42="",'Model inputs'!C36=""),"",'Model inputs'!J42<='Model inputs'!C36))),('Model inputs'!C48-'Model inputs'!C45)/'Model inputs'!C36,0)="",0,IF(IF(IF(ISERROR('Model inputs'!J42<='Model inputs'!C36),'Model inputs'!J42<='Model inputs'!C36,IF(OR('Model inputs'!J42="",'Model inputs'!C36=""),"",'Model inputs'!J42<='Model inputs'!C36))="",FALSE,IF(ISERROR('Model inputs'!J42<='Model inputs'!C36),'Model inputs'!J42<='Model inputs'!C36,IF(OR('Model inputs'!J42="",'Model inputs'!C36=""),"",'Model inputs'!J42<='Model inputs'!C36))),('Model inputs'!C48-'Model inputs'!C45)/'Model inputs'!C36,0))+'Model inputs'!J23*'Model inputs'!C51 -> 10.6 | K16: =IF(IF(IF(IF(ISERROR('Model inputs'!K42<='Model inputs'!C36),'Model inputs'!K42<='Model inputs'!C36,IF(OR('Model inputs'!K42="",'Model inputs'!C36=""),"",'Model inputs'!K42<='Model inputs'!C36))="",FALSE,IF(ISERROR('Model inputs'!K42<='Model inputs'!C36),'Model inputs'!K42<='Model inputs'!C36,IF(OR('Model inputs'!K42="",'Model inputs'!C36=""),"",'Model inputs'!K42<='Model inputs'!C36))),('Model inputs'!C48-'Model inputs'!C45)/'Model inputs'!C36,0)="",0,IF(IF(IF(ISERROR('Model inputs'!K42<='Model inputs'!C36),'Model inputs'!K42<='Model inputs'!C36,IF(OR('Model inputs'!K42="",'Model inputs'!C36=""),"",'Model inputs'!K42<='Model inputs'!C36))="",FALSE,IF(ISERROR('Model inputs'!K42<='Model inputs'!C36),'Model inputs'!K42<='Model inputs'!C36,IF(OR('Model inputs'!K42="",'Model inputs'!C36=""),"",'Model inputs'!K42<='Model inputs'!C36))),('Model inputs'!C48-'Model inputs'!C45)/'Model inputs'!C36,0))+'Model inputs'!K23*'Model inputs'!C51 -> 10.7 | L16: =IF(IF(IF(IF(ISERROR('Model inputs'!L42<='Model inputs'!C36),'Model inputs'!L42<='Model inputs'!C36,IF(OR('Model inputs'!L42="",'Model inputs'!C36=""),"",'Model inputs'!L42<='Model inputs'!C36))="",FALSE,IF(ISERROR('Model inputs'!L42<='Model inputs'!C36),'Model inputs'!L42<='Model inputs'!C36,IF(OR('Model inputs'!L42="",'Model inputs'!C36=""),"",'Model inputs'!L42<='Model inputs'!C36))),('Model inputs'!C48-'Model inputs'!C45)/'Model inputs'!C36,0)="",0,IF(IF(IF(ISERROR('Model inputs'!L42<='Model inputs'!C36),'Model inputs'!L42<='Model inputs'!C36,IF(OR('Model inputs'!L42="",'Model inputs'!C36=""),"",'Model inputs'!L42<='Model inputs'!C36))="",FALSE,IF(ISERROR('Model inputs'!L42<='Model inputs'!C36),'Model inputs'!L42<='Model inputs'!C36,IF(OR('Model inputs'!L42="",'Model inputs'!C36=""),"",'Model inputs'!L42<='Model inputs'!C36))),('Model inputs'!C48-'Model inputs'!C45)/'Model inputs'!C36,0))+'Model inputs'!L23*'Model inputs'!C51 -> 10.8 | M16: =IF(IF(IF(IF(ISERROR('Model inputs'!M42<='Model inputs'!C36),'Model inputs'!M42<='Model inputs'!C36,IF(OR('Model inputs'!M42="",'Model inputs'!C36=""),"",'Model inputs'!M42<='Model inputs'!C36))="",FALSE,IF(ISERROR('Model inputs'!M42<='Model inputs'!C36),'Model inputs'!M42<='Model inputs'!C36,IF(OR('Model inputs'!M42="",'Model inputs'!C36=""),"",'Model inputs'!M42<='Model inputs'!C36))),('Model inputs'!C48-'Model inputs'!C45)/'Model inputs'!C36,0)="",0,IF(IF(IF(ISERROR('Model inputs'!M42<='Model inputs'!C36),'Model inputs'!M42<='Model inputs'!C36,IF(OR('Model inputs'!M42="",'Model inputs'!C36=""),"",'Model inputs'!M42<='Model inputs'!C36))="",FALSE,IF(ISERROR('Model inputs'!M42<='Model inputs'!C36),'Model inputs'!M42<='Model inputs'!C36,IF(OR('Model inputs'!M42="",'Model inputs'!C36=""),"",'Model inputs'!M42<='Model inputs'!C36))),('Model inputs'!C48-'Model inputs'!C45)/'Model inputs'!C36,0))+'Model inputs'!M23*'Model inputs'!C51 -> 10.9 | N16: =IF(IF(IF(IF(ISERROR('Model inputs'!N42<='Model inputs'!C36),'Model inputs'!N42<='Model inputs'!C36,IF(OR('Model inputs'!N42="",'Model inputs'!C36=""),"",'Model inputs'!N42<='Model inputs'!C36))="",FALSE,IF(ISERROR('Model inputs'!N42<='Model inputs'!C36),'Model inputs'!N42<='Model inputs'!C36,IF(OR('Model inputs'!N42="",'Model inputs'!C36=""),"",'Model inputs'!N42<='Model inputs'!C36))),('Model inputs'!C48-'Model inputs'!C45)/'Model inputs'!C36,0)="",0,IF(IF(IF(ISERROR('Model inputs'!N42<='Model inputs'!C36),'Model inputs'!N42<='Model inputs'!C36,IF(OR('Model inputs'!N42="",'Model inputs'!C36=""),"",'Model inputs'!N42<='Model inputs'!C36))="",FALSE,IF(ISERROR('Model inputs'!N42<='Model inputs'!C36),'Model inputs'!N42<='Model inputs'!C36,IF(OR('Model inputs'!N42="",'Model inputs'!C36=""),"",'Model inputs'!N42<='Model inputs'!C36))),('Model inputs'!C48-'Model inputs'!C45)/'Model inputs'!C36,0))+'Model inputs'!N23*'Model inputs'!C51 -> 11 | O16: =IF(IF(IF(IF(ISERROR('Model inputs'!O42<='Model inputs'!C36),'Model inputs'!O42<='Model inputs'!C36,IF(OR('Model inputs'!O42="",'Model inputs'!C36=""),"",'Model inputs'!O42<='Model inputs'!C36))="",FALSE,IF(ISERROR('Model inputs'!O42<='Model inputs'!C36),'Model inputs'!O42<='Model inputs'!C36,IF(OR('Model inputs'!O42="",'Model inputs'!C36=""),"",'Model inputs'!O42<='Model inputs'!C36))),('Model inputs'!C48-'Model inputs'!C45)/'Model inputs'!C36,0)="",0,IF(IF(IF(ISERROR('Model inputs'!O42<='Model inputs'!C36),'Model inputs'!O42<='Model inputs'!C36,IF(OR('Model inputs'!O42="",'Model inputs'!C36=""),"",'Model inputs'!O42<='Model inputs'!C36))="",FALSE,IF(ISERROR('Model inputs'!O42<='Model inputs'!C36),'Model inputs'!O42<='Model inputs'!C36,IF(OR('Model inputs'!O42="",'Model inputs'!C36=""),"",'Model inputs'!O42<='Model inputs'!C36))),('Model inputs'!C48-'Model inputs'!C45)/'Model inputs'!C36,0))+'Model inputs'!O23*'Model inputs'!C51 -> 11.1 | P16: 0 | Q16: 0 | R16: 0 | S16: 0 | T16: 0 | U16: 0 | V16: 0 | W16: 0 | X16: 0
A17: Gross customer additions · TenantGuard — High | D17: =IF(IF(IF(IF(ISERROR('Model inputs'!D43<='Model inputs'!C37),'Model inputs'!D43<='Model inputs'!C37,IF(OR('Model inputs'!D43="",'Model inputs'!C37=""),"",'Model inputs'!D43<='Model inputs'!C37))="",FALSE,IF(ISERROR('Model inputs'!D43<='Model inputs'!C37),'Model inputs'!D43<='Model inputs'!C37,IF(OR('Model inputs'!D43="",'Model inputs'!C37=""),"",'Model inputs'!D43<='Model inputs'!C37))),('Model inputs'!C49-'Model inputs'!C46)/'Model inputs'!C37,0)="",0,IF(IF(IF(ISERROR('Model inputs'!D43<='Model inputs'!C37),'Model inputs'!D43<='Model inputs'!C37,IF(OR('Model inputs'!D43="",'Model inputs'!C37=""),"",'Model inputs'!D43<='Model inputs'!C37))="",FALSE,IF(ISERROR('Model inputs'!D43<='Model inputs'!C37),'Model inputs'!D43<='Model inputs'!C37,IF(OR('Model inputs'!D43="",'Model inputs'!C37=""),"",'Model inputs'!D43<='Model inputs'!C37))),('Model inputs'!C49-'Model inputs'!C46)/'Model inputs'!C37,0))+'Model inputs'!D24*'Model inputs'!C52 -> 21.666667 | E17: =IF(IF(IF(IF(ISERROR('Model inputs'!E43<='Model inputs'!C37),'Model inputs'!E43<='Model inputs'!C37,IF(OR('Model inputs'!E43="",'Model inputs'!C37=""),"",'Model inputs'!E43<='Model inputs'!C37))="",FALSE,IF(ISERROR('Model inputs'!E43<='Model inputs'!C37),'Model inputs'!E43<='Model inputs'!C37,IF(OR('Model inputs'!E43="",'Model inputs'!C37=""),"",'Model inputs'!E43<='Model inputs'!C37))),('Model inputs'!C49-'Model inputs'!C46)/'Model inputs'!C37,0)="",0,IF(IF(IF(ISERROR('Model inputs'!E43<='Model inputs'!C37),'Model inputs'!E43<='Model inputs'!C37,IF(OR('Model inputs'!E43="",'Model inputs'!C37=""),"",'Model inputs'!E43<='Model inputs'!C37))="",FALSE,IF(ISERROR('Model inputs'!E43<='Model inputs'!C37),'Model inputs'!E43<='Model inputs'!C37,IF(OR('Model inputs'!E43="",'Model inputs'!C37=""),"",'Model inputs'!E43<='Model inputs'!C37))),('Model inputs'!C49-'Model inputs'!C46)/'Model inputs'!C37,0))+'Model inputs'!E24*'Model inputs'!C52 -> 21.883333 | F17: =IF(IF(IF(IF(ISERROR('Model inputs'!F43<='Model inputs'!C37),'Model inputs'!F43<='Model inputs'!C37,IF(OR('Model inputs'!F43="",'Model inputs'!C37=""),"",'Model inputs'!F43<='Model inputs'!C37))="",FALSE,IF(ISERROR('Model inputs'!F43<='Model inputs'!C37),'Model inputs'!F43<='Model inputs'!C37,IF(OR('Model inputs'!F43="",'Model inputs'!C37=""),"",'Model inputs'!F43<='Model inputs'!C37))),('Model inputs'!C49-'Model inputs'!C46)/'Model inputs'!C37,0)="",0,IF(IF(IF(ISERROR('Model inputs'!F43<='Model inputs'!C37),'Model inputs'!F43<='Model inputs'!C37,IF(OR('Model inputs'!F43="",'Model inputs'!C37=""),"",'Model inputs'!F43<='Model inputs'!C37))="",FALSE,IF(ISERROR('Model inputs'!F43<='Model inputs'!C37),'Model inputs'!F43<='Model inputs'!C37,IF(OR('Model inputs'!F43="",'Model inputs'!C37=""),"",'Model inputs'!F43<='Model inputs'!C37))),('Model inputs'!C49-'Model inputs'!C46)/'Model inputs'!C37,0))+'Model inputs'!F24*'Model inputs'!C52 -> 22.1 | G17: =IF(IF(IF(IF(ISERROR('Model inputs'!G43<='Model inputs'!C37),'Model inputs'!G43<='Model inputs'!C37,IF(OR('Model inputs'!G43="",'Model inputs'!C37=""),"",'Model inputs'!G43<='Model inputs'!C37))="",FALSE,IF(ISERROR('Model inputs'!G43<='Model inputs'!C37),'Model inputs'!G43<='Model inputs'!C37,IF(OR('Model inputs'!G43="",'Model inputs'!C37=""),"",'Model inputs'!G43<='Model inputs'!C37))),('Model inputs'!C49-'Model inputs'!C46)/'Model inputs'!C37,0)="",0,IF(IF(IF(ISERROR('Model inputs'!G43<='Model inputs'!C37),'Model inputs'!G43<='Model inputs'!C37,IF(OR('Model inputs'!G43="",'Model inputs'!C37=""),"",'Model inputs'!G43<='Model inputs'!C37))="",FALSE,IF(ISERROR('Model inputs'!G43<='Model inputs'!C37),'Model inputs'!G43<='Model inputs'!C37,IF(OR('Model inputs'!G43="",'Model inputs'!C37=""),"",'Model inputs'!G43<='Model inputs'!C37))),('Model inputs'!C49-'Model inputs'!C46)/'Model inputs'!C37,0))+'Model inputs'!G24*'Model inputs'!C52 -> 22.316667 | H17: =IF(IF(IF(IF(ISERROR('Model inputs'!H43<='Model inputs'!C37),'Model inputs'!H43<='Model inputs'!C37,IF(OR('Model inputs'!H43="",'Model inputs'!C37=""),"",'Model inputs'!H43<='Model inputs'!C37))="",FALSE,IF(ISERROR('Model inputs'!H43<='Model inputs'!C37),'Model inputs'!H43<='Model inputs'!C37,IF(OR('Model inputs'!H43="",'Model inputs'!C37=""),"",'Model inputs'!H43<='Model inputs'!C37))),('Model inputs'!C49-'Model inputs'!C46)/'Model inputs'!C37,0)="",0,IF(IF(IF(ISERROR('Model inputs'!H43<='Model inputs'!C37),'Model inputs'!H43<='Model inputs'!C37,IF(OR('Model inputs'!H43="",'Model inputs'!C37=""),"",'Model inputs'!H43<='Model inputs'!C37))="",FALSE,IF(ISERROR('Model inputs'!H43<='Model inputs'!C37),'Model inputs'!H43<='Model inputs'!C37,IF(OR('Model inputs'!H43="",'Model inputs'!C37=""),"",'Model inputs'!H43<='Model inputs'!C37))),('Model inputs'!C49-'Model inputs'!C46)/'Model inputs'!C37,0))+'Model inputs'!H24*'Model inputs'!C52 -> 22.533333 | I17: =IF(IF(IF(IF(ISERROR('Model inputs'!I43<='Model inputs'!C37),'Model inputs'!I43<='Model inputs'!C37,IF(OR('Model inputs'!I43="",'Model inputs'!C37=""),"",'Model inputs'!I43<='Model inputs'!C37))="",FALSE,IF(ISERROR('Model inputs'!I43<='Model inputs'!C37),'Model inputs'!I43<='Model inputs'!C37,IF(OR('Model inputs'!I43="",'Model inputs'!C37=""),"",'Model inputs'!I43<='Model inputs'!C37))),('Model inputs'!C49-'Model inputs'!C46)/'Model inputs'!C37,0)="",0,IF(IF(IF(ISERROR('Model inputs'!I43<='Model inputs'!C37),'Model inputs'!I43<='Model inputs'!C37,IF(OR('Model inputs'!I43="",'Model inputs'!C37=""),"",'Model inputs'!I43<='Model inputs'!C37))="",FALSE,IF(ISERROR('Model inputs'!I43<='Model inputs'!C37),'Model inputs'!I43<='Model inputs'!C37,IF(OR('Model inputs'!I43="",'Model inputs'!C37=""),"",'Model inputs'!I43<='Model inputs'!C37))),('Model inputs'!C49-'Model inputs'!C46)/'Model inputs'!C37,0))+'Model inputs'!I24*'Model inputs'!C52 -> 22.75 | J17: =IF(IF(IF(IF(ISERROR('Model inputs'!J43<='Model inputs'!C37),'Model inputs'!J43<='Model inputs'!C37,IF(OR('Model inputs'!J43="",'Model inputs'!C37=""),"",'Model inputs'!J43<='Model inputs'!C37))="",FALSE,IF(ISERROR('Model inputs'!J43<='Model inputs'!C37),'Model inputs'!J43<='Model inputs'!C37,IF(OR('Model inputs'!J43="",'Model inputs'!C37=""),"",'Model inputs'!J43<='Model inputs'!C37))),('Model inputs'!C49-'Model inputs'!C46)/'Model inputs'!C37,0)="",0,IF(IF(IF(ISERROR('Model inputs'!J43<='Model inputs'!C37),'Model inputs'!J43<='Model inputs'!C37,IF(OR('Model inputs'!J43="",'Model inputs'!C37=""),"",'Model inputs'!J43<='Model inputs'!C37))="",FALSE,IF(ISERROR('Model inputs'!J43<='Model inputs'!C37),'Model inputs'!J43<='Model inputs'!C37,IF(OR('Model inputs'!J43="",'Model inputs'!C37=""),"",'Model inputs'!J43<='Model inputs'!C37))),('Model inputs'!C49-'Model inputs'!C46)/'Model inputs'!C37,0))+'Model inputs'!J24*'Model inputs'!C52 -> 22.966667 | K17: =IF(IF(IF(IF(ISERROR('Model inputs'!K43<='Model inputs'!C37),'Model inputs'!K43<='Model inputs'!C37,IF(OR('Model inputs'!K43="",'Model inputs'!C37=""),"",'Model inputs'!K43<='Model inputs'!C37))="",FALSE,IF(ISERROR('Model inputs'!K43<='Model inputs'!C37),'Model inputs'!K43<='Model inputs'!C37,IF(OR('Model inputs'!K43="",'Model inputs'!C37=""),"",'Model inputs'!K43<='Model inputs'!C37))),('Model inputs'!C49-'Model inputs'!C46)/'Model inputs'!C37,0)="",0,IF(IF(IF(ISERROR('Model inputs'!K43<='Model inputs'!C37),'Model inputs'!K43<='Model inputs'!C37,IF(OR('Model inputs'!K43="",'Model inputs'!C37=""),"",'Model inputs'!K43<='Model inputs'!C37))="",FALSE,IF(ISERROR('Model inputs'!K43<='Model inputs'!C37),'Model inputs'!K43<='Model inputs'!C37,IF(OR('Model inputs'!K43="",'Model inputs'!C37=""),"",'Model inputs'!K43<='Model inputs'!C37))),('Model inputs'!C49-'Model inputs'!C46)/'Model inputs'!C37,0))+'Model inputs'!K24*'Model inputs'!C52 -> 23.183333 | L17: =IF(IF(IF(IF(ISERROR('Model inputs'!L43<='Model inputs'!C37),'Model inputs'!L43<='Model inputs'!C37,IF(OR('Model inputs'!L43="",'Model inputs'!C37=""),"",'Model inputs'!L43<='Model inputs'!C37))="",FALSE,IF(ISERROR('Model inputs'!L43<='Model inputs'!C37),'Model inputs'!L43<='Model inputs'!C37,IF(OR('Model inputs'!L43="",'Model inputs'!C37=""),"",'Model inputs'!L43<='Model inputs'!C37))),('Model inputs'!C49-'Model inputs'!C46)/'Model inputs'!C37,0)="",0,IF(IF(IF(ISERROR('Model inputs'!L43<='Model inputs'!C37),'Model inputs'!L43<='Model inputs'!C37,IF(OR('Model inputs'!L43="",'Model inputs'!C37=""),"",'Model inputs'!L43<='Model inputs'!C37))="",FALSE,IF(ISERROR('Model inputs'!L43<='Model inputs'!C37),'Model inputs'!L43<='Model inputs'!C37,IF(OR('Model inputs'!L43="",'Model inputs'!C37=""),"",'Model inputs'!L43<='Model inputs'!C37))),('Model inputs'!C49-'Model inputs'!C46)/'Model inputs'!C37,0))+'Model inputs'!L24*'Model inputs'!C52 -> 23.4 | M17: =IF(IF(IF(IF(ISERROR('Model inputs'!M43<='Model inputs'!C37),'Model inputs'!M43<='Model inputs'!C37,IF(OR('Model inputs'!M43="",'Model inputs'!C37=""),"",'Model inputs'!M43<='Model inputs'!C37))="",FALSE,IF(ISERROR('Model inputs'!M43<='Model inputs'!C37),'Model inputs'!M43<='Model inputs'!C37,IF(OR('Model inputs'!M43="",'Model inputs'!C37=""),"",'Model inputs'!M43<='Model inputs'!C37))),('Model inputs'!C49-'Model inputs'!C46)/'Model inputs'!C37,0)="",0,IF(IF(IF(ISERROR('Model inputs'!M43<='Model inputs'!C37),'Model inputs'!M43<='Model inputs'!C37,IF(OR('Model inputs'!M43="",'Model inputs'!C37=""),"",'Model inputs'!M43<='Model inputs'!C37))="",FALSE,IF(ISERROR('Model inputs'!M43<='Model inputs'!C37),'Model inputs'!M43<='Model inputs'!C37,IF(OR('Model inputs'!M43="",'Model inputs'!C37=""),"",'Model inputs'!M43<='Model inputs'!C37))),('Model inputs'!C49-'Model inputs'!C46)/'Model inputs'!C37,0))+'Model inputs'!M24*'Model inputs'!C52 -> 23.616667 | N17: =IF(IF(IF(IF(ISERROR('Model inputs'!N43<='Model inputs'!C37),'Model inputs'!N43<='Model inputs'!C37,IF(OR('Model inputs'!N43="",'Model inputs'!C37=""),"",'Model inputs'!N43<='Model inputs'!C37))="",FALSE,IF(ISERROR('Model inputs'!N43<='Model inputs'!C37),'Model inputs'!N43<='Model inputs'!C37,IF(OR('Model inputs'!N43="",'Model inputs'!C37=""),"",'Model inputs'!N43<='Model inputs'!C37))),('Model inputs'!C49-'Model inputs'!C46)/'Model inputs'!C37,0)="",0,IF(IF(IF(ISERROR('Model inputs'!N43<='Model inputs'!C37),'Model inputs'!N43<='Model inputs'!C37,IF(OR('Model inputs'!N43="",'Model inputs'!C37=""),"",'Model inputs'!N43<='Model inputs'!C37))="",FALSE,IF(ISERROR('Model inputs'!N43<='Model inputs'!C37),'Model inputs'!N43<='Model inputs'!C37,IF(OR('Model inputs'!N43="",'Model inputs'!C37=""),"",'Model inputs'!N43<='Model inputs'!C37))),('Model inputs'!C49-'Model inputs'!C46)/'Model inputs'!C37,0))+'Model inputs'!N24*'Model inputs'!C52 -> 23.833333 | O17: =IF(IF(IF(IF(ISERROR('Model inputs'!O43<='Model inputs'!C37),'Model inputs'!O43<='Model inputs'!C37,IF(OR('Model inputs'!O43="",'Model inputs'!C37=""),"",'Model inputs'!O43<='Model inputs'!C37))="",FALSE,IF(ISERROR('Model inputs'!O43<='Model inputs'!C37),'Model inputs'!O43<='Model inputs'!C37,IF(OR('Model inputs'!O43="",'Model inputs'!C37=""),"",'Model inputs'!O43<='Model inputs'!C37))),('Model inputs'!C49-'Model inputs'!C46)/'Model inputs'!C37,0)="",0,IF(IF(IF(ISERROR('Model inputs'!O43<='Model inputs'!C37),'Model inputs'!O43<='Model inputs'!C37,IF(OR('Model inputs'!O43="",'Model inputs'!C37=""),"",'Model inputs'!O43<='Model inputs'!C37))="",FALSE,IF(ISERROR('Model inputs'!O43<='Model inputs'!C37),'Model inputs'!O43<='Model inputs'!C37,IF(OR('Model inputs'!O43="",'Model inputs'!C37=""),"",'Model inputs'!O43<='Model inputs'!C37))),('Model inputs'!C49-'Model inputs'!C46)/'Model inputs'!C37,0))+'Model inputs'!O24*'Model inputs'!C52 -> 24.05 | X17: 0
A18: Gross customer additions · TenantGuard — Low | D18: =IF(IF(IF(IF(ISERROR('Model inputs'!D44<='Model inputs'!C38),'Model inputs'!D44<='Model inputs'!C38,IF(OR('Model inputs'!D44="",'Model inputs'!C38=""),"",'Model inputs'!D44<='Model inputs'!C38))="",FALSE,IF(ISERROR('Model inputs'!D44<='Model inputs'!C38),'Model inputs'!D44<='Model inputs'!C38,IF(OR('Model inputs'!D44="",'Model inputs'!C38=""),"",'Model inputs'!D44<='Model inputs'!C38))),('Model inputs'!C50-'Model inputs'!C47)/'Model inputs'!C38,0)="",0,IF(IF(IF(ISERROR('Model inputs'!D44<='Model inputs'!C38),'Model inputs'!D44<='Model inputs'!C38,IF(OR('Model inputs'!D44="",'Model inputs'!C38=""),"",'Model inputs'!D44<='Model inputs'!C38))="",FALSE,IF(ISERROR('Model inputs'!D44<='Model inputs'!C38),'Model inputs'!D44<='Model inputs'!C38,IF(OR('Model inputs'!D44="",'Model inputs'!C38=""),"",'Model inputs'!D44<='Model inputs'!C38))),('Model inputs'!C50-'Model inputs'!C47)/'Model inputs'!C38,0))+'Model inputs'!D25*'Model inputs'!C53 -> 3.3333333 | E18: =IF(IF(IF(IF(ISERROR('Model inputs'!E44<='Model inputs'!C38),'Model inputs'!E44<='Model inputs'!C38,IF(OR('Model inputs'!E44="",'Model inputs'!C38=""),"",'Model inputs'!E44<='Model inputs'!C38))="",FALSE,IF(ISERROR('Model inputs'!E44<='Model inputs'!C38),'Model inputs'!E44<='Model inputs'!C38,IF(OR('Model inputs'!E44="",'Model inputs'!C38=""),"",'Model inputs'!E44<='Model inputs'!C38))),('Model inputs'!C50-'Model inputs'!C47)/'Model inputs'!C38,0)="",0,IF(IF(IF(ISERROR('Model inputs'!E44<='Model inputs'!C38),'Model inputs'!E44<='Model inputs'!C38,IF(OR('Model inputs'!E44="",'Model inputs'!C38=""),"",'Model inputs'!E44<='Model inputs'!C38))="",FALSE,IF(ISERROR('Model inputs'!E44<='Model inputs'!C38),'Model inputs'!E44<='Model inputs'!C38,IF(OR('Model inputs'!E44="",'Model inputs'!C38=""),"",'Model inputs'!E44<='Model inputs'!C38))),('Model inputs'!C50-'Model inputs'!C47)/'Model inputs'!C38,0))+'Model inputs'!E25*'Model inputs'!C53 -> 3.3666667 | F18: =IF(IF(IF(IF(ISERROR('Model inputs'!F44<='Model inputs'!C38),'Model inputs'!F44<='Model inputs'!C38,IF(OR('Model inputs'!F44="",'Model inputs'!C38=""),"",'Model inputs'!F44<='Model inputs'!C38))="",FALSE,IF(ISERROR('Model inputs'!F44<='Model inputs'!C38),'Model inputs'!F44<='Model inputs'!C38,IF(OR('Model inputs'!F44="",'Model inputs'!C38=""),"",'Model inputs'!F44<='Model inputs'!C38))),('Model inputs'!C50-'Model inputs'!C47)/'Model inputs'!C38,0)="",0,IF(IF(IF(ISERROR('Model inputs'!F44<='Model inputs'!C38),'Model inputs'!F44<='Model inputs'!C38,IF(OR('Model inputs'!F44="",'Model inputs'!C38=""),"",'Model inputs'!F44<='Model inputs'!C38))="",FALSE,IF(ISERROR('Model inputs'!F44<='Model inputs'!C38),'Model inputs'!F44<='Model inputs'!C38,IF(OR('Model inputs'!F44="",'Model inputs'!C38=""),"",'Model inputs'!F44<='Model inputs'!C38))),('Model inputs'!C50-'Model inputs'!C47)/'Model inputs'!C38,0))+'Model inputs'!F25*'Model inputs'!C53 -> 3.4 | G18: =IF(IF(IF(IF(ISERROR('Model inputs'!G44<='Model inputs'!C38),'Model inputs'!G44<='Model inputs'!C38,IF(OR('Model inputs'!G44="",'Model inputs'!C38=""),"",'Model inputs'!G44<='Model inputs'!C38))="",FALSE,IF(ISERROR('Model inputs'!G44<='Model inputs'!C38),'Model inputs'!G44<='Model inputs'!C38,IF(OR('Model inputs'!G44="",'Model inputs'!C38=""),"",'Model inputs'!G44<='Model inputs'!C38))),('Model inputs'!C50-'Model inputs'!C47)/'Model inputs'!C38,0)="",0,IF(IF(IF(ISERROR('Model inputs'!G44<='Model inputs'!C38),'Model inputs'!G44<='Model inputs'!C38,IF(OR('Model inputs'!G44="",'Model inputs'!C38=""),"",'Model inputs'!G44<='Model inputs'!C38))="",FALSE,IF(ISERROR('Model inputs'!G44<='Model inputs'!C38),'Model inputs'!G44<='Model inputs'!C38,IF(OR('Model inputs'!G44="",'Model inputs'!C38=""),"",'Model inputs'!G44<='Model inputs'!C38))),('Model inputs'!C50-'Model inputs'!C47)/'Model inputs'!C38,0))+'Model inputs'!G25*'Model inputs'!C53 -> 3.4333333 | H18: =IF(IF(IF(IF(ISERROR('Model inputs'!H44<='Model inputs'!C38),'Model inputs'!H44<='Model inputs'!C38,IF(OR('Model inputs'!H44="",'Model inputs'!C38=""),"",'Model inputs'!H44<='Model inputs'!C38))="",FALSE,IF(ISERROR('Model inputs'!H44<='Model inputs'!C38),'Model inputs'!H44<='Model inputs'!C38,IF(OR('Model inputs'!H44="",'Model inputs'!C38=""),"",'Model inputs'!H44<='Model inputs'!C38))),('Model inputs'!C50-'Model inputs'!C47)/'Model inputs'!C38,0)="",0,IF(IF(IF(ISERROR('Model inputs'!H44<='Model inputs'!C38),'Model inputs'!H44<='Model inputs'!C38,IF(OR('Model inputs'!H44="",'Model inputs'!C38=""),"",'Model inputs'!H44<='Model inputs'!C38))="",FALSE,IF(ISERROR('Model inputs'!H44<='Model inputs'!C38),'Model inputs'!H44<='Model inputs'!C38,IF(OR('Model inputs'!H44="",'Model inputs'!C38=""),"",'Model inputs'!H44<='Model inputs'!C38))),('Model inputs'!C50-'Model inputs'!C47)/'Model inputs'!C38,0))+'Model inputs'!H25*'Model inputs'!C53 -> 3.4666667 | I18: =IF(IF(IF(IF(ISERROR('Model inputs'!I44<='Model inputs'!C38),'Model inputs'!I44<='Model inputs'!C38,IF(OR('Model inputs'!I44="",'Model inputs'!C38=""),"",'Model inputs'!I44<='Model inputs'!C38))="",FALSE,IF(ISERROR('Model inputs'!I44<='Model inputs'!C38),'Model inputs'!I44<='Model inputs'!C38,IF(OR('Model inputs'!I44="",'Model inputs'!C38=""),"",'Model inputs'!I44<='Model inputs'!C38))),('Model inputs'!C50-'Model inputs'!C47)/'Model inputs'!C38,0)="",0,IF(IF(IF(ISERROR('Model inputs'!I44<='Model inputs'!C38),'Model inputs'!I44<='Model inputs'!C38,IF(OR('Model inputs'!I44="",'Model inputs'!C38=""),"",'Model inputs'!I44<='Model inputs'!C38))="",FALSE,IF(ISERROR('Model inputs'!I44<='Model inputs'!C38),'Model inputs'!I44<='Model inputs'!C38,IF(OR('Model inputs'!I44="",'Model inputs'!C38=""),"",'Model inputs'!I44<='Model inputs'!C38))),('Model inputs'!C50-'Model inputs'!C47)/'Model inputs'!C38,0))+'Model inputs'!I25*'Model inputs'!C53 -> 3.5 | J18: =IF(IF(IF(IF(ISERROR('Model inputs'!J44<='Model inputs'!C38),'Model inputs'!J44<='Model inputs'!C38,IF(OR('Model inputs'!J44="",'Model inputs'!C38=""),"",'Model inputs'!J44<='Model inputs'!C38))="",FALSE,IF(ISERROR('Model inputs'!J44<='Model inputs'!C38),'Model inputs'!J44<='Model inputs'!C38,IF(OR('Model inputs'!J44="",'Model inputs'!C38=""),"",'Model inputs'!J44<='Model inputs'!C38))),('Model inputs'!C50-'Model inputs'!C47)/'Model inputs'!C38,0)="",0,IF(IF(IF(ISERROR('Model inputs'!J44<='Model inputs'!C38),'Model inputs'!J44<='Model inputs'!C38,IF(OR('Model inputs'!J44="",'Model inputs'!C38=""),"",'Model inputs'!J44<='Model inputs'!C38))="",FALSE,IF(ISERROR('Model inputs'!J44<='Model inputs'!C38),'Model inputs'!J44<='Model inputs'!C38,IF(OR('Model inputs'!J44="",'Model inputs'!C38=""),"",'Model inputs'!J44<='Model inputs'!C38))),('Model inputs'!C50-'Model inputs'!C47)/'Model inputs'!C38,0))+'Model inputs'!J25*'Model inputs'!C53 -> 3.5333333 | K18: =IF(IF(IF(IF(ISERROR('Model inputs'!K44<='Model inputs'!C38),'Model inputs'!K44<='Model inputs'!C38,IF(OR('Model inputs'!K44="",'Model inputs'!C38=""),"",'Model inputs'!K44<='Model inputs'!C38))="",FALSE,IF(ISERROR('Model inputs'!K44<='Model inputs'!C38),'Model inputs'!K44<='Model inputs'!C38,IF(OR('Model inputs'!K44="",'Model inputs'!C38=""),"",'Model inputs'!K44<='Model inputs'!C38))),('Model inputs'!C50-'Model inputs'!C47)/'Model inputs'!C38,0)="",0,IF(IF(IF(ISERROR('Model inputs'!K44<='Model inputs'!C38),'Model inputs'!K44<='Model inputs'!C38,IF(OR('Model inputs'!K44="",'Model inputs'!C38=""),"",'Model inputs'!K44<='Model inputs'!C38))="",FALSE,IF(ISERROR('Model inputs'!K44<='Model inputs'!C38),'Model inputs'!K44<='Model inputs'!C38,IF(OR('Model inputs'!K44="",'Model inputs'!C38=""),"",'Model inputs'!K44<='Model inputs'!C38))),('Model inputs'!C50-'Model inputs'!C47)/'Model inputs'!C38,0))+'Model inputs'!K25*'Model inputs'!C53 -> 3.5666667 | L18: =IF(IF(IF(IF(ISERROR('Model inputs'!L44<='Model inputs'!C38),'Model inputs'!L44<='Model inputs'!C38,IF(OR('Model inputs'!L44="",'Model inputs'!C38=""),"",'Model inputs'!L44<='Model inputs'!C38))="",FALSE,IF(ISERROR('Model inputs'!L44<='Model inputs'!C38),'Model inputs'!L44<='Model inputs'!C38,IF(OR('Model inputs'!L44="",'Model inputs'!C38=""),"",'Model inputs'!L44<='Model inputs'!C38))),('Model inputs'!C50-'Model inputs'!C47)/'Model inputs'!C38,0)="",0,IF(IF(IF(ISERROR('Model inputs'!L44<='Model inputs'!C38),'Model inputs'!L44<='Model inputs'!C38,IF(OR('Model inputs'!L44="",'Model inputs'!C38=""),"",'Model inputs'!L44<='Model inputs'!C38))="",FALSE,IF(ISERROR('Model inputs'!L44<='Model inputs'!C38),'Model inputs'!L44<='Model inputs'!C38,IF(OR('Model inputs'!L44="",'Model inputs'!C38=""),"",'Model inputs'!L44<='Model inputs'!C38))),('Model inputs'!C50-'Model inputs'!C47)/'Model inputs'!C38,0))+'Model inputs'!L25*'Model inputs'!C53 -> 3.6 | M18: =IF(IF(IF(IF(ISERROR('Model inputs'!M44<='Model inputs'!C38),'Model inputs'!M44<='Model inputs'!C38,IF(OR('Model inputs'!M44="",'Model inputs'!C38=""),"",'Model inputs'!M44<='Model inputs'!C38))="",FALSE,IF(ISERROR('Model inputs'!M44<='Model inputs'!C38),'Model inputs'!M44<='Model inputs'!C38,IF(OR('Model inputs'!M44="",'Model inputs'!C38=""),"",'Model inputs'!M44<='Model inputs'!C38))),('Model inputs'!C50-'Model inputs'!C47)/'Model inputs'!C38,0)="",0,IF(IF(IF(ISERROR('Model inputs'!M44<='Model inputs'!C38),'Model inputs'!M44<='Model inputs'!C38,IF(OR('Model inputs'!M44="",'Model inputs'!C38=""),"",'Model inputs'!M44<='Model inputs'!C38))="",FALSE,IF(ISERROR('Model inputs'!M44<='Model inputs'!C38),'Model inputs'!M44<='Model inputs'!C38,IF(OR('Model inputs'!M44="",'Model inputs'!C38=""),"",'Model inputs'!M44<='Model inputs'!C38))),('Model inputs'!C50-'Model inputs'!C47)/'Model inputs'!C38,0))+'Model inputs'!M25*'Model inputs'!C53 -> 3.6333333 | N18: =IF(IF(IF(IF(ISERROR('Model inputs'!N44<='Model inputs'!C38),'Model inputs'!N44<='Model inputs'!C38,IF(OR('Model inputs'!N44="",'Model inputs'!C38=""),"",'Model inputs'!N44<='Model inputs'!C38))="",FALSE,IF(ISERROR('Model inputs'!N44<='Model inputs'!C38),'Model inputs'!N44<='Model inputs'!C38,IF(OR('Model inputs'!N44="",'Model inputs'!C38=""),"",'Model inputs'!N44<='Model inputs'!C38))),('Model inputs'!C50-'Model inputs'!C47)/'Model inputs'!C38,0)="",0,IF(IF(IF(ISERROR('Model inputs'!N44<='Model inputs'!C38),'Model inputs'!N44<='Model inputs'!C38,IF(OR('Model inputs'!N44="",'Model inputs'!C38=""),"",'Model inputs'!N44<='Model inputs'!C38))="",FALSE,IF(ISERROR('Model inputs'!N44<='Model inputs'!C38),'Model inputs'!N44<='Model inputs'!C38,IF(OR('Model inputs'!N44="",'Model inputs'!C38=""),"",'Model inputs'!N44<='Model inputs'!C38))),('Model inputs'!C50-'Model inputs'!C47)/'Model inputs'!C38,0))+'Model inputs'!N25*'Model inputs'!C53 -> 3.6666667 | O18: =IF(IF(IF(IF(ISERROR('Model inputs'!O44<='Model inputs'!C38),'Model inputs'!O44<='Model inputs'!C38,IF(OR('Model inputs'!O44="",'Model inputs'!C38=""),"",'Model inputs'!O44<='Model inputs'!C38))="",FALSE,IF(ISERROR('Model inputs'!O44<='Model inputs'!C38),'Model inputs'!O44<='Model inputs'!C38,IF(OR('Model inputs'!O44="",'Model inputs'!C38=""),"",'Model inputs'!O44<='Model inputs'!C38))),('Model inputs'!C50-'Model inputs'!C47)/'Model inputs'!C38,0)="",0,IF(IF(IF(ISERROR('Model inputs'!O44<='Model inputs'!C38),'Model inputs'!O44<='Model inputs'!C38,IF(OR('Model inputs'!O44="",'Model inputs'!C38=""),"",'Model inputs'!O44<='Model inputs'!C38))="",FALSE,IF(ISERROR('Model inputs'!O44<='Model inputs'!C38),'Model inputs'!O44<='Model inputs'!C38,IF(OR('Model inputs'!O44="",'Model inputs'!C38=""),"",'Model inputs'!O44<='Model inputs'!C38))),('Model inputs'!C50-'Model inputs'!C47)/'Model inputs'!C38,0))+'Model inputs'!O25*'Model inputs'!C53 -> 3.7 | X18: 0
A19: Launch cash · TenantGuard unit economics · Main Scenario | B19: ='TenantGuard inputs'!B13 -> 900000
A20: Launch cash · TenantGuard three-case revenue ramp · Main Scenario | C20: ='TenantGuard inputs'!B13 -> 900000
A21: Launch cash · TenantGuard — High | C21: ='TenantGuard inputs'!B13 -> 900000
A22: Launch cash · TenantGuard — Low | C22: ='TenantGuard inputs'!B13 -> 900000
A23: Opening customers · TenantGuard three-case revenue ramp · Main Scenario | D23: =IF(IF(IF(ISERROR('Model inputs'!D42=1),'Model inputs'!D42=1,IF('Model inputs'!D42="","",'Model inputs'!D42=1))="",FALSE,IF(ISERROR('Model inputs'!D42=1),'Model inputs'!D42=1,IF('Model inputs'!D42="","",'Model inputs'!D42=1))),IF('Model inputs'!C45="","",'Model inputs'!C45),IF('Model inputs'!X33="","",'Model inputs'!X33)) -> 0 | E23: =IF(IF(IF(ISERROR('Model inputs'!E42=1),'Model inputs'!E42=1,IF('Model inputs'!E42="","",'Model inputs'!E42=1))="",FALSE,IF(ISERROR('Model inputs'!E42=1),'Model inputs'!E42=1,IF('Model inputs'!E42="","",'Model inputs'!E42=1))),IF('Model inputs'!C45="","",'Model inputs'!C45),IF('Model inputs'!D33="","",'Model inputs'!D33)) -> 10 | F23: =IF(IF(IF(ISERROR('Model inputs'!F42=1),'Model inputs'!F42=1,IF('Model inputs'!F42="","",'Model inputs'!F42=1))="",FALSE,IF(ISERROR('Model inputs'!F42=1),'Model inputs'!F42=1,IF('Model inputs'!F42="","",'Model inputs'!F42=1))),IF('Model inputs'!C45="","",'Model inputs'!C45),IF('Model inputs'!E33="","",'Model inputs'!E33)) -> 20 | G23: =IF(IF(IF(ISERROR('Model inputs'!G42=1),'Model inputs'!G42=1,IF('Model inputs'!G42="","",'Model inputs'!G42=1))="",FALSE,IF(ISERROR('Model inputs'!G42=1),'Model inputs'!G42=1,IF('Model inputs'!G42="","",'Model inputs'!G42=1))),IF('Model inputs'!C45="","",'Model inputs'!C45),IF('Model inputs'!F33="","",'Model inputs'!F33)) -> 30 | H23: =IF(IF(IF(ISERROR('Model inputs'!H42=1),'Model inputs'!H42=1,IF('Model inputs'!H42="","",'Model inputs'!H42=1))="",FALSE,IF(ISERROR('Model inputs'!H42=1),'Model inputs'!H42=1,IF('Model inputs'!H42="","",'Model inputs'!H42=1))),IF('Model inputs'!C45="","",'Model inputs'!C45),IF('Model inputs'!G33="","",'Model inputs'!G33)) -> 40 | I23: =IF(IF(IF(ISERROR('Model inputs'!I42=1),'Model inputs'!I42=1,IF('Model inputs'!I42="","",'Model inputs'!I42=1))="",FALSE,IF(ISERROR('Model inputs'!I42=1),'Model inputs'!I42=1,IF('Model inputs'!I42="","",'Model inputs'!I42=1))),IF('Model inputs'!C45="","",'Model inputs'!C45),IF('Model inputs'!H33="","",'Model inputs'!H33)) -> 50 | J23: =IF(IF(IF(ISERROR('Model inputs'!J42=1),'Model inputs'!J42=1,IF('Model inputs'!J42="","",'Model inputs'!J42=1))="",FALSE,IF(ISERROR('Model inputs'!J42=1),'Model inputs'!J42=1,IF('Model inputs'!J42="","",'Model inputs'!J42=1))),IF('Model inputs'!C45="","",'Model inputs'!C45),IF('Model inputs'!I33="","",'Model inputs'!I33)) -> 60 | K23: =IF(IF(IF(ISERROR('Model inputs'!K42=1),'Model inputs'!K42=1,IF('Model inputs'!K42="","",'Model inputs'!K42=1))="",FALSE,IF(ISERROR('Model inputs'!K42=1),'Model inputs'!K42=1,IF('Model inputs'!K42="","",'Model inputs'!K42=1))),IF('Model inputs'!C45="","",'Model inputs'!C45),IF('Model inputs'!J33="","",'Model inputs'!J33)) -> 70 | L23: =IF(IF(IF(ISERROR('Model inputs'!L42=1),'Model inputs'!L42=1,IF('Model inputs'!L42="","",'Model inputs'!L42=1))="",FALSE,IF(ISERROR('Model inputs'!L42=1),'Model inputs'!L42=1,IF('Model inputs'!L42="","",'Model inputs'!L42=1))),IF('Model inputs'!C45="","",'Model inputs'!C45),IF('Model inputs'!K33="","",'Model inputs'!K33)) -> 80 | M23: =IF(IF(IF(ISERROR('Model inputs'!M42=1),'Model inputs'!M42=1,IF('Model inputs'!M42="","",'Model inputs'!M42=1))="",FALSE,IF(ISERROR('Model inputs'!M42=1),'Model inputs'!M42=1,IF('Model inputs'!M42="","",'Model inputs'!M42=1))),IF('Model inputs'!C45="","",'Model inputs'!C45),IF('Model inputs'!L33="","",'Model inputs'!L33)) -> 90 | N23: =IF(IF(IF(ISERROR('Model inputs'!N42=1),'Model inputs'!N42=1,IF('Model inputs'!N42="","",'Model inputs'!N42=1))="",FALSE,IF(ISERROR('Model inputs'!N42=1),'Model inputs'!N42=1,IF('Model inputs'!N42="","",'Model inputs'!N42=1))),IF('Model inputs'!C45="","",'Model inputs'!C45),IF('Model inputs'!M33="","",'Model inputs'!M33)) -> 100 | O23: =IF(IF(IF(ISERROR('Model inputs'!O42=1),'Model inputs'!O42=1,IF('Model inputs'!O42="","",'Model inputs'!O42=1))="",FALSE,IF(ISERROR('Model inputs'!O42=1),'Model inputs'!O42=1,IF('Model inputs'!O42="","",'Model inputs'!O42=1))),IF('Model inputs'!C45="","",'Model inputs'!C45),IF('Model inputs'!N33="","",'Model inputs'!N33)) -> 110 | P23: 0 | Q23: 0 | R23: 0 | S23: 0 | T23: 0 | U23: 0 | V23: 0 | W23: 0 | X23: 0
A24: Opening customers · TenantGuard — High | D24: =IF(IF(IF(ISERROR('Model inputs'!D43=1),'Model inputs'!D43=1,IF('Model inputs'!D43="","",'Model inputs'!D43=1))="",FALSE,IF(ISERROR('Model inputs'!D43=1),'Model inputs'!D43=1,IF('Model inputs'!D43="","",'Model inputs'!D43=1))),IF('Model inputs'!C46="","",'Model inputs'!C46),IF('Model inputs'!X40="","",'Model inputs'!X40)) -> 0 | E24: =IF(IF(IF(ISERROR('Model inputs'!E43=1),'Model inputs'!E43=1,IF('Model inputs'!E43="","",'Model inputs'!E43=1))="",FALSE,IF(ISERROR('Model inputs'!E43=1),'Model inputs'!E43=1,IF('Model inputs'!E43="","",'Model inputs'!E43=1))),IF('Model inputs'!C46="","",'Model inputs'!C46),IF('Model inputs'!D40="","",'Model inputs'!D40)) -> 21.666667 | F24: =IF(IF(IF(ISERROR('Model inputs'!F43=1),'Model inputs'!F43=1,IF('Model inputs'!F43="","",'Model inputs'!F43=1))="",FALSE,IF(ISERROR('Model inputs'!F43=1),'Model inputs'!F43=1,IF('Model inputs'!F43="","",'Model inputs'!F43=1))),IF('Model inputs'!C46="","",'Model inputs'!C46),IF('Model inputs'!E40="","",'Model inputs'!E40)) -> 43.333333 | G24: =IF(IF(IF(ISERROR('Model inputs'!G43=1),'Model inputs'!G43=1,IF('Model inputs'!G43="","",'Model inputs'!G43=1))="",FALSE,IF(ISERROR('Model inputs'!G43=1),'Model inputs'!G43=1,IF('Model inputs'!G43="","",'Model inputs'!G43=1))),IF('Model inputs'!C46="","",'Model inputs'!C46),IF('Model inputs'!F40="","",'Model inputs'!F40)) -> 65 | H24: =IF(IF(IF(ISERROR('Model inputs'!H43=1),'Model inputs'!H43=1,IF('Model inputs'!H43="","",'Model inputs'!H43=1))="",FALSE,IF(ISERROR('Model inputs'!H43=1),'Model inputs'!H43=1,IF('Model inputs'!H43="","",'Model inputs'!H43=1))),IF('Model inputs'!C46="","",'Model inputs'!C46),IF('Model inputs'!G40="","",'Model inputs'!G40)) -> 86.666667 | I24: =IF(IF(IF(ISERROR('Model inputs'!I43=1),'Model inputs'!I43=1,IF('Model inputs'!I43="","",'Model inputs'!I43=1))="",FALSE,IF(ISERROR('Model inputs'!I43=1),'Model inputs'!I43=1,IF('Model inputs'!I43="","",'Model inputs'!I43=1))),IF('Model inputs'!C46="","",'Model inputs'!C46),IF('Model inputs'!H40="","",'Model inputs'!H40)) -> 108.33333 | J24: =IF(IF(IF(ISERROR('Model inputs'!J43=1),'Model inputs'!J43=1,IF('Model inputs'!J43="","",'Model inputs'!J43=1))="",FALSE,IF(ISERROR('Model inputs'!J43=1),'Model inputs'!J43=1,IF('Model inputs'!J43="","",'Model inputs'!J43=1))),IF('Model inputs'!C46="","",'Model inputs'!C46),IF('Model inputs'!I40="","",'Model inputs'!I40)) -> 130 | K24: =IF(IF(IF(ISERROR('Model inputs'!K43=1),'Model inputs'!K43=1,IF('Model inputs'!K43="","",'Model inputs'!K43=1))="",FALSE,IF(ISERROR('Model inputs'!K43=1),'Model inputs'!K43=1,IF('Model inputs'!K43="","",'Model inputs'!K43=1))),IF('Model inputs'!C46="","",'Model inputs'!C46),IF('Model inputs'!J40="","",'Model inputs'!J40)) -> 151.66667 | L24: =IF(IF(IF(ISERROR('Model inputs'!L43=1),'Model inputs'!L43=1,IF('Model inputs'!L43="","",'Model inputs'!L43=1))="",FALSE,IF(ISERROR('Model inputs'!L43=1),'Model inputs'!L43=1,IF('Model inputs'!L43="","",'Model inputs'!L43=1))),IF('Model inputs'!C46="","",'Model inputs'!C46),IF('Model inputs'!K40="","",'Model inputs'!K40)) -> 173.33333 | M24: =IF(IF(IF(ISERROR('Model inputs'!M43=1),'Model inputs'!M43=1,IF('Model inputs'!M43="","",'Model inputs'!M43=1))="",FALSE,IF(ISERROR('Model inputs'!M43=1),'Model inputs'!M43=1,IF('Model inputs'!M43="","",'Model inputs'!M43=1))),IF('Model inputs'!C46="","",'Model inputs'!C46),IF('Model inputs'!L40="","",'Model inputs'!L40)) -> 195 | N24: =IF(IF(IF(ISERROR('Model inputs'!N43=1),'Model inputs'!N43=1,IF('Model inputs'!N43="","",'Model inputs'!N43=1))="",FALSE,IF(ISERROR('Model inputs'!N43=1),'Model inputs'!N43=1,IF('Model inputs'!N43="","",'Model inputs'!N43=1))),IF('Model inputs'!C46="","",'Model inputs'!C46),IF('Model inputs'!M40="","",'Model inputs'!M40)) -> 216.66667 | O24: =IF(IF(IF(ISERROR('Model inputs'!O43=1),'Model inputs'!O43=1,IF('Model inputs'!O43="","",'Model inputs'!O43=1))="",FALSE,IF(ISERROR('Model inputs'!O43=1),'Model inputs'!O43=1,IF('Model inputs'!O43="","",'Model inputs'!O43=1))),IF('Model inputs'!C46="","",'Model inputs'!C46),IF('Model inputs'!N40="","",'Model inputs'!N40)) -> 238.33333 | X24: 0
A25: Opening customers · TenantGuard — Low | D25: =IF(IF(IF(ISERROR('Model inputs'!D44=1),'Model inputs'!D44=1,IF('Model inputs'!D44="","",'Model inputs'!D44=1))="",FALSE,IF(ISERROR('Model inputs'!D44=1),'Model inputs'!D44=1,IF('Model inputs'!D44="","",'Model inputs'!D44=1))),IF('Model inputs'!C47="","",'Model inputs'!C47),IF('Model inputs'!X41="","",'Model inputs'!X41)) -> 0 | E25: =IF(IF(IF(ISERROR('Model inputs'!E44=1),'Model inputs'!E44=1,IF('Model inputs'!E44="","",'Model inputs'!E44=1))="",FALSE,IF(ISERROR('Model inputs'!E44=1),'Model inputs'!E44=1,IF('Model inputs'!E44="","",'Model inputs'!E44=1))),IF('Model inputs'!C47="","",'Model inputs'!C47),IF('Model inputs'!D41="","",'Model inputs'!D41)) -> 3.3333333 | F25: =IF(IF(IF(ISERROR('Model inputs'!F44=1),'Model inputs'!F44=1,IF('Model inputs'!F44="","",'Model inputs'!F44=1))="",FALSE,IF(ISERROR('Model inputs'!F44=1),'Model inputs'!F44=1,IF('Model inputs'!F44="","",'Model inputs'!F44=1))),IF('Model inputs'!C47="","",'Model inputs'!C47),IF('Model inputs'!E41="","",'Model inputs'!E41)) -> 6.6666667 | G25: =IF(IF(IF(ISERROR('Model inputs'!G44=1),'Model inputs'!G44=1,IF('Model inputs'!G44="","",'Model inputs'!G44=1))="",FALSE,IF(ISERROR('Model inputs'!G44=1),'Model inputs'!G44=1,IF('Model inputs'!G44="","",'Model inputs'!G44=1))),IF('Model inputs'!C47="","",'Model inputs'!C47),IF('Model inputs'!F41="","",'Model inputs'!F41)) -> 10 | H25: =IF(IF(IF(ISERROR('Model inputs'!H44=1),'Model inputs'!H44=1,IF('Model inputs'!H44="","",'Model inputs'!H44=1))="",FALSE,IF(ISERROR('Model inputs'!H44=1),'Model inputs'!H44=1,IF('Model inputs'!H44="","",'Model inputs'!H44=1))),IF('Model inputs'!C47="","",'Model inputs'!C47),IF('Model inputs'!G41="","",'Model inputs'!G41)) -> 13.333333 | I25: =IF(IF(IF(ISERROR('Model inputs'!I44=1),'Model inputs'!I44=1,IF('Model inputs'!I44="","",'Model inputs'!I44=1))="",FALSE,IF(ISERROR('Model inputs'!I44=1),'Model inputs'!I44=1,IF('Model inputs'!I44="","",'Model inputs'!I44=1))),IF('Model inputs'!C47="","",'Model inputs'!C47),IF('Model inputs'!H41="","",'Model inputs'!H41)) -> 16.666667 | J25: =IF(IF(IF(ISERROR('Model inputs'!J44=1),'Model inputs'!J44=1,IF('Model inputs'!J44="","",'Model inputs'!J44=1))="",FALSE,IF(ISERROR('Model inputs'!J44=1),'Model inputs'!J44=1,IF('Model inputs'!J44="","",'Model inputs'!J44=1))),IF('Model inputs'!C47="","",'Model inputs'!C47),IF('Model inputs'!I41="","",'Model inputs'!I41)) -> 20 | K25: =IF(IF(IF(ISERROR('Model inputs'!K44=1),'Model inputs'!K44=1,IF('Model inputs'!K44="","",'Model inputs'!K44=1))="",FALSE,IF(ISERROR('Model inputs'!K44=1),'Model inputs'!K44=1,IF('Model inputs'!K44="","",'Model inputs'!K44=1))),IF('Model inputs'!C47="","",'Model inputs'!C47),IF('Model inputs'!J41="","",'Model inputs'!J41)) -> 23.333333 | L25: =IF(IF(IF(ISERROR('Model inputs'!L44=1),'Model inputs'!L44=1,IF('Model inputs'!L44="","",'Model inputs'!L44=1))="",FALSE,IF(ISERROR('Model inputs'!L44=1),'Model inputs'!L44=1,IF('Model inputs'!L44="","",'Model inputs'!L44=1))),IF('Model inputs'!C47="","",'Model inputs'!C47),IF('Model inputs'!K41="","",'Model inputs'!K41)) -> 26.666667 | M25: =IF(IF(IF(ISERROR('Model inputs'!M44=1),'Model inputs'!M44=1,IF('Model inputs'!M44="","",'Model inputs'!M44=1))="",FALSE,IF(ISERROR('Model inputs'!M44=1),'Model inputs'!M44=1,IF('Model inputs'!M44="","",'Model inputs'!M44=1))),IF('Model inputs'!C47="","",'Model inputs'!C47),IF('Model inputs'!L41="","",'Model inputs'!L41)) -> 30 | N25: =IF(IF(IF(ISERROR('Model inputs'!N44=1),'Model inputs'!N44=1,IF('Model inputs'!N44="","",'Model inputs'!N44=1))="",FALSE,IF(ISERROR('Model inputs'!N44=1),'Model inputs'!N44=1,IF('Model inputs'!N44="","",'Model inputs'!N44=1))),IF('Model inputs'!C47="","",'Model inputs'!C47),IF('Model inputs'!M41="","",'Model inputs'!M41)) -> 33.333333 | O25: =IF(IF(IF(ISERROR('Model inputs'!O44=1),'Model inputs'!O44=1,IF('Model inputs'!O44="","",'Model inputs'!O44=1))="",FALSE,IF(ISERROR('Model inputs'!O44=1),'Model inputs'!O44=1,IF('Model inputs'!O44="","",'Model inputs'!O44=1))),IF('Model inputs'!C47="","",'Model inputs'!C47),IF('Model inputs'!N41="","",'Model inputs'!N41)) -> 36.666667 | X25: 0
A26: TenantGuard ending cash · TenantGuard unit economics · Main Scenario | D26: =IF(IF(DATE(2026,10,1)=DATE(2026,10,1),IF('Model inputs'!B19="","",'Model inputs'!B19),IF('Model inputs'!X26="","",'Model inputs'!X26))="",0,IF(DATE(2026,10,1)=DATE(2026,10,1),IF('Model inputs'!B19="","",'Model inputs'!B19),IF('Model inputs'!X26="","",'Model inputs'!X26)))+'Model inputs'!D29 -> 856457.5 | E26: =IF(IF(DATE(2026,11,1)=DATE(2026,10,1),IF('Model inputs'!B19="","",'Model inputs'!B19),IF('Model inputs'!D26="","",'Model inputs'!D26))="",0,IF(DATE(2026,11,1)=DATE(2026,10,1),IF('Model inputs'!B19="","",'Model inputs'!B19),IF('Model inputs'!D26="","",'Model inputs'!D26)))+'Model inputs'!E29 -> 819372.5 | F26: =IF(IF(DATE(2026,12,1)=DATE(2026,10,1),IF('Model inputs'!B19="","",'Model inputs'!B19),IF('Model inputs'!E26="","",'Model inputs'!E26))="",0,IF(DATE(2026,12,1)=DATE(2026,10,1),IF('Model inputs'!B19="","",'Model inputs'!B19),IF('Model inputs'!E26="","",'Model inputs'!E26)))+'Model inputs'!F29 -> 788745 | G26: =IF(IF(DATE(2027,1,1)=DATE(2026,10,1),IF('Model inputs'!B19="","",'Model inputs'!B19),IF('Model inputs'!F26="","",'Model inputs'!F26))="",0,IF(DATE(2027,1,1)=DATE(2026,10,1),IF('Model inputs'!B19="","",'Model inputs'!B19),IF('Model inputs'!F26="","",'Model inputs'!F26)))+'Model inputs'!G29 -> 764575 | H26: =IF(IF(DATE(2027,2,1)=DATE(2026,10,1),IF('Model inputs'!B19="","",'Model inputs'!B19),IF('Model inputs'!G26="","",'Model inputs'!G26))="",0,IF(DATE(2027,2,1)=DATE(2026,10,1),IF('Model inputs'!B19="","",'Model inputs'!B19),IF('Model inputs'!G26="","",'Model inputs'!G26)))+'Model inputs'!H29 -> 746862.5 | I26: =IF(IF(DATE(2027,3,1)=DATE(2026,10,1),IF('Model inputs'!B19="","",'Model inputs'!B19),IF('Model inputs'!H26="","",'Model inputs'!H26))="",0,IF(DATE(2027,3,1)=DATE(2026,10,1),IF('Model inputs'!B19="","",'Model inputs'!B19),IF('Model inputs'!H26="","",'Model inputs'!H26)))+'Model inputs'!I29 -> 735607.5 | J26: =IF(IF(DATE(2027,4,1)=DATE(2026,10,1),IF('Model inputs'!B19="","",'Model inputs'!B19),IF('Model inputs'!I26="","",'Model inputs'!I26))="",0,IF(DATE(2027,4,1)=DATE(2026,10,1),IF('Model inputs'!B19="","",'Model inputs'!B19),IF('Model inputs'!I26="","",'Model inputs'!I26)))+'Model inputs'!J29 -> 730810 | K26: =IF(IF(DATE(2027,5,1)=DATE(2026,10,1),IF('Model inputs'!B19="","",'Model inputs'!B19),IF('Model inputs'!J26="","",'Model inputs'!J26))="",0,IF(DATE(2027,5,1)=DATE(2026,10,1),IF('Model inputs'!B19="","",'Model inputs'!B19),IF('Model inputs'!J26="","",'Model inputs'!J26)))+'Model inputs'!K29 -> 732470 | L26: =IF(IF(DATE(2027,6,1)=DATE(2026,10,1),IF('Model inputs'!B19="","",'Model inputs'!B19),IF('Model inputs'!K26="","",'Model inputs'!K26))="",0,IF(DATE(2027,6,1)=DATE(2026,10,1),IF('Model inputs'!B19="","",'Model inputs'!B19),IF('Model inputs'!K26="","",'Model inputs'!K26)))+'Model inputs'!L29 -> 740587.5 | M26: =IF(IF(DATE(2027,7,1)=DATE(2026,10,1),IF('Model inputs'!B19="","",'Model inputs'!B19),IF('Model inputs'!L26="","",'Model inputs'!L26))="",0,IF(DATE(2027,7,1)=DATE(2026,10,1),IF('Model inputs'!B19="","",'Model inputs'!B19),IF('Model inputs'!L26="","",'Model inputs'!L26)))+'Model inputs'!M29 -> 755162.5 | N26: =IF(IF(DATE(2027,8,1)=DATE(2026,10,1),IF('Model inputs'!B19="","",'Model inputs'!B19),IF('Model inputs'!M26="","",'Model inputs'!M26))="",0,IF(DATE(2027,8,1)=DATE(2026,10,1),IF('Model inputs'!B19="","",'Model inputs'!B19),IF('Model inputs'!M26="","",'Model inputs'!M26)))+'Model inputs'!N29 -> 776195 | O26: =IF(IF(DATE(2027,9,1)=DATE(2026,10,1),IF('Model inputs'!B19="","",'Model inputs'!B19),IF('Model inputs'!N26="","",'Model inputs'!N26))="",0,IF(DATE(2027,9,1)=DATE(2026,10,1),IF('Model inputs'!B19="","",'Model inputs'!B19),IF('Model inputs'!N26="","",'Model inputs'!N26)))+'Model inputs'!O29 -> 803685 | P26: 0 | Q26: 0 | R26: 0 | S26: 0 | T26: 0 | U26: 0 | V26: 0 | W26: 0 | X26: 0
A27: TenantGuard ending cash · TenantGuard — High | D27: =IF(IF(DATE(2026,10,1)=DATE(2026,10,1),IF('Model inputs'!C21="","",'Model inputs'!C21),IF('Model inputs'!X27="","",'Model inputs'!X27))="",0,IF(DATE(2026,10,1)=DATE(2026,10,1),IF('Model inputs'!C21="","",'Model inputs'!C21),IF('Model inputs'!X27="","",'Model inputs'!X27)))+'Model inputs'!D30 -> 868330 | E27: =IF(IF(DATE(2026,11,1)=DATE(2026,10,1),IF('Model inputs'!C21="","",'Model inputs'!C21),IF('Model inputs'!D27="","",'Model inputs'!D27))="",0,IF(DATE(2026,11,1)=DATE(2026,10,1),IF('Model inputs'!C21="","",'Model inputs'!C21),IF('Model inputs'!D27="","",'Model inputs'!D27)))+'Model inputs'!E30 -> 854990 | F27: =IF(IF(DATE(2026,12,1)=DATE(2026,10,1),IF('Model inputs'!C21="","",'Model inputs'!C21),IF('Model inputs'!E27="","",'Model inputs'!E27))="",0,IF(DATE(2026,12,1)=DATE(2026,10,1),IF('Model inputs'!C21="","",'Model inputs'!C21),IF('Model inputs'!E27="","",'Model inputs'!E27)))+'Model inputs'!F30 -> 859980 | G27: =IF(IF(DATE(2027,1,1)=DATE(2026,10,1),IF('Model inputs'!C21="","",'Model inputs'!C21),IF('Model inputs'!F27="","",'Model inputs'!F27))="",0,IF(DATE(2027,1,1)=DATE(2026,10,1),IF('Model inputs'!C21="","",'Model inputs'!C21),IF('Model inputs'!F27="","",'Model inputs'!F27)))+'Model inputs'!G30 -> 883300 | H27: =IF(IF(DATE(2027,2,1)=DATE(2026,10,1),IF('Model inputs'!C21="","",'Model inputs'!C21),IF('Model inputs'!G27="","",'Model inputs'!G27))="",0,IF(DATE(2027,2,1)=DATE(2026,10,1),IF('Model inputs'!C21="","",'Model inputs'!C21),IF('Model inputs'!G27="","",'Model inputs'!G27)))+'Model inputs'!H30 -> 924950 | I27: =IF(IF(DATE(2027,3,1)=DATE(2026,10,1),IF('Model inputs'!C21="","",'Model inputs'!C21),IF('Model inputs'!H27="","",'Model inputs'!H27))="",0,IF(DATE(2027,3,1)=DATE(2026,10,1),IF('Model inputs'!C21="","",'Model inputs'!C21),IF('Model inputs'!H27="","",'Model inputs'!H27)))+'Model inputs'!I30 -> 984930 | J27: =IF(IF(DATE(2027,4,1)=DATE(2026,10,1),IF('Model inputs'!C21="","",'Model inputs'!C21),IF('Model inputs'!I27="","",'Model inputs'!I27))="",0,IF(DATE(2027,4,1)=DATE(2026,10,1),IF('Model inputs'!C21="","",'Model inputs'!C21),IF('Model inputs'!I27="","",'Model inputs'!I27)))+'Model inputs'!J30 -> 1063240 | K27: =IF(IF(DATE(2027,5,1)=DATE(2026,10,1),IF('Model inputs'!C21="","",'Model inputs'!C21),IF('Model inputs'!J27="","",'Model inputs'!J27))="",0,IF(DATE(2027,5,1)=DATE(2026,10,1),IF('Model inputs'!C21="","",'Model inputs'!C21),IF('Model inputs'!J27="","",'Model inputs'!J27)))+'Model inputs'!K30 -> 1159880 | L27: =IF(IF(DATE(2027,6,1)=DATE(2026,10,1),IF('Model inputs'!C21="","",'Model inputs'!C21),IF('Model inputs'!K27="","",'Model inputs'!K27))="",0,IF(DATE(2027,6,1)=DATE(2026,10,1),IF('Model inputs'!C21="","",'Model inputs'!C21),IF('Model inputs'!K27="","",'Model inputs'!K27)))+'Model inputs'!L30 -> 1274850 | M27: =IF(IF(DATE(2027,7,1)=DATE(2026,10,1),IF('Model inputs'!C21="","",'Model inputs'!C21),IF('Model inputs'!L27="","",'Model inputs'!L27))="",0,IF(DATE(2027,7,1)=DATE(2026,10,1),IF('Model inputs'!C21="","",'Model inputs'!C21),IF('Model inputs'!L27="","",'Model inputs'!L27)))+'Model inputs'!M30 -> 1408150 | N27: =IF(IF(DATE(2027,8,1)=DATE(2026,10,1),IF('Model inputs'!C21="","",'Model inputs'!C21),IF('Model inputs'!M27="","",'Model inputs'!M27))="",0,IF(DATE(2027,8,1)=DATE(2026,10,1),IF('Model inputs'!C21="","",'Model inputs'!C21),IF('Model inputs'!M27="","",'Model inputs'!M27)))+'Model inputs'!N30 -> 1559780 | O27: =IF(IF(DATE(2027,9,1)=DATE(2026,10,1),IF('Model inputs'!C21="","",'Model inputs'!C21),IF('Model inputs'!N27="","",'Model inputs'!N27))="",0,IF(DATE(2027,9,1)=DATE(2026,10,1),IF('Model inputs'!C21="","",'Model inputs'!C21),IF('Model inputs'!N27="","",'Model inputs'!N27)))+'Model inputs'!O30 -> 1729740 | X27: 0
A28: TenantGuard ending cash · TenantGuard — Low | D28: =IF(IF(DATE(2026,10,1)=DATE(2026,10,1),IF('Model inputs'!C22="","",'Model inputs'!C22),IF('Model inputs'!X28="","",'Model inputs'!X28))="",0,IF(DATE(2026,10,1)=DATE(2026,10,1),IF('Model inputs'!C22="","",'Model inputs'!C22),IF('Model inputs'!X28="","",'Model inputs'!X28)))+'Model inputs'!D31 -> 851481.67 | E28: =IF(IF(DATE(2026,11,1)=DATE(2026,10,1),IF('Model inputs'!C22="","",'Model inputs'!C22),IF('Model inputs'!D28="","",'Model inputs'!D28))="",0,IF(DATE(2026,11,1)=DATE(2026,10,1),IF('Model inputs'!C22="","",'Model inputs'!C22),IF('Model inputs'!D28="","",'Model inputs'!D28)))+'Model inputs'!E31 -> 804445 | F28: =IF(IF(DATE(2026,12,1)=DATE(2026,10,1),IF('Model inputs'!C22="","",'Model inputs'!C22),IF('Model inputs'!E28="","",'Model inputs'!E28))="",0,IF(DATE(2026,12,1)=DATE(2026,10,1),IF('Model inputs'!C22="","",'Model inputs'!C22),IF('Model inputs'!E28="","",'Model inputs'!E28)))+'Model inputs'!F31 -> 758890 | G28: =IF(IF(DATE(2027,1,1)=DATE(2026,10,1),IF('Model inputs'!C22="","",'Model inputs'!C22),IF('Model inputs'!F28="","",'Model inputs'!F28))="",0,IF(DATE(2027,1,1)=DATE(2026,10,1),IF('Model inputs'!C22="","",'Model inputs'!C22),IF('Model inputs'!F28="","",'Model inputs'!F28)))+'Model inputs'!G31 -> 714816.67 | H28: =IF(IF(DATE(2027,2,1)=DATE(2026,10,1),IF('Model inputs'!C22="","",'Model inputs'!C22),IF('Model inputs'!G28="","",'Model inputs'!G28))="",0,IF(DATE(2027,2,1)=DATE(2026,10,1),IF('Model inputs'!C22="","",'Model inputs'!C22),IF('Model inputs'!G28="","",'Model inputs'!G28)))+'Model inputs'!H31 -> 672225 | I28: =IF(IF(DATE(2027,3,1)=DATE(2026,10,1),IF('Model inputs'!C22="","",'Model inputs'!C22),IF('Model inputs'!H28="","",'Model inputs'!H28))="",0,IF(DATE(2027,3,1)=DATE(2026,10,1),IF('Model inputs'!C22="","",'Model inputs'!C22),IF('Model inputs'!H28="","",'Model inputs'!H28)))+'Model inputs'!I31 -> 631115 | J28: =IF(IF(DATE(2027,4,1)=DATE(2026,10,1),IF('Model inputs'!C22="","",'Model inputs'!C22),IF('Model inputs'!I28="","",'Model inputs'!I28))="",0,IF(DATE(2027,4,1)=DATE(2026,10,1),IF('Model inputs'!C22="","",'Model inputs'!C22),IF('Model inputs'!I28="","",'Model inputs'!I28)))+'Model inputs'!J31 -> 591486.67 | K28: =IF(IF(DATE(2027,5,1)=DATE(2026,10,1),IF('Model inputs'!C22="","",'Model inputs'!C22),IF('Model inputs'!J28="","",'Model inputs'!J28))="",0,IF(DATE(2027,5,1)=DATE(2026,10,1),IF('Model inputs'!C22="","",'Model inputs'!C22),IF('Model inputs'!J28="","",'Model inputs'!J28)))+'Model inputs'!K31 -> 553340 | L28: =IF(IF(DATE(2027,6,1)=DATE(2026,10,1),IF('Model inputs'!C22="","",'Model inputs'!C22),IF('Model inputs'!K28="","",'Model inputs'!K28))="",0,IF(DATE(2027,6,1)=DATE(2026,10,1),IF('Model inputs'!C22="","",'Model inputs'!C22),IF('Model inputs'!K28="","",'Model inputs'!K28)))+'Model inputs'!L31 -> 516675 | M28: =IF(IF(DATE(2027,7,1)=DATE(2026,10,1),IF('Model inputs'!C22="","",'Model inputs'!C22),IF('Model inputs'!L28="","",'Model inputs'!L28))="",0,IF(DATE(2027,7,1)=DATE(2026,10,1),IF('Model inputs'!C22="","",'Model inputs'!C22),IF('Model inputs'!L28="","",'Model inputs'!L28)))+'Model inputs'!M31 -> 481491.67 | N28: =IF(IF(DATE(2027,8,1)=DATE(2026,10,1),IF('Model inputs'!C22="","",'Model inputs'!C22),IF('Model inputs'!M28="","",'Model inputs'!M28))="",0,IF(DATE(2027,8,1)=DATE(2026,10,1),IF('Model inputs'!C22="","",'Model inputs'!C22),IF('Model inputs'!M28="","",'Model inputs'!M28)))+'Model inputs'!N31 -> 447790 | O28: =IF(IF(DATE(2027,9,1)=DATE(2026,10,1),IF('Model inputs'!C22="","",'Model inputs'!C22),IF('Model inputs'!N28="","",'Model inputs'!N28))="",0,IF(DATE(2027,9,1)=DATE(2026,10,1),IF('Model inputs'!C22="","",'Model inputs'!C22),IF('Model inputs'!N28="","",'Model inputs'!N28)))+'Model inputs'!O31 -> 415570 | X28: 0
A29: TenantGuard net cash flow · TenantGuard unit economics · Main Scenario | D29: ='Model inputs'!D32-'Model inputs'!D56-'Model inputs'!D59 -> -43542.5 | E29: ='Model inputs'!E32-'Model inputs'!E56-'Model inputs'!E59 -> -37085 | F29: ='Model inputs'!F32-'Model inputs'!F56-'Model inputs'!F59 -> -30627.5 | G29: ='Model inputs'!G32-'Model inputs'!G56-'Model inputs'!G59 -> -24170 | H29: ='Model inputs'!H32-'Model inputs'!H56-'Model inputs'!H59 -> -17712.5 | I29: ='Model inputs'!I32-'Model inputs'!I56-'Model inputs'!I59 -> -11255 | J29: ='Model inputs'!J32-'Model inputs'!J56-'Model inputs'!J59 -> -4797.5 | K29: ='Model inputs'!K32-'Model inputs'!K56-'Model inputs'!K59 -> 1660 | ... O29: ='Model inputs'!O32-'Model inputs'!O56-'Model inputs'!O59 -> 27490 | P29: 0 | Q29: 0 | R29: 0 | S29: 0 | T29: 0 | U29: 0 | V29: 0 | W29: 0 | X29: 0
A30: TenantGuard net cash flow · TenantGuard — High | D30: ='Model inputs'!D62-'Model inputs'!D57-'Model inputs'!D60 -> -31670 | E30: ='Model inputs'!E62-'Model inputs'!E57-'Model inputs'!E60 -> -13340 | F30: ='Model inputs'!F62-'Model inputs'!F57-'Model inputs'!F60 -> 4990 | G30: ='Model inputs'!G62-'Model inputs'!G57-'Model inputs'!G60 -> 23320 | H30: ='Model inputs'!H62-'Model inputs'!H57-'Model inputs'!H60 -> 41650 | I30: ='Model inputs'!I62-'Model inputs'!I57-'Model inputs'!I60 -> 59980 | J30: ='Model inputs'!J62-'Model inputs'!J57-'Model inputs'!J60 -> 78310 | K30: ='Model inputs'!K62-'Model inputs'!K57-'Model inputs'!K60 -> 96640 | ... O30: ='Model inputs'!O62-'Model inputs'!O57-'Model inputs'!O60 -> 169960 | X30: 0
A31: TenantGuard net cash flow · TenantGuard — Low | D31: ='Model inputs'!D63-'Model inputs'!D58-'Model inputs'!D61 -> -48518.333 | E31: ='Model inputs'!E63-'Model inputs'!E58-'Model inputs'!E61 -> -47036.667 | F31: ='Model inputs'!F63-'Model inputs'!F58-'Model inputs'!F61 -> -45555 | G31: ='Model inputs'!G63-'Model inputs'!G58-'Model inputs'!G61 -> -44073.333 | H31: ='Model inputs'!H63-'Model inputs'!H58-'Model inputs'!H61 -> -42591.667 | I31: ='Model inputs'!I63-'Model inputs'!I58-'Model inputs'!I61 -> -41110 | J31: ='Model inputs'!J63-'Model inputs'!J58-'Model inputs'!J61 -> -39628.333 | K31: ='Model inputs'!K63-'Model inputs'!K58-'Model inputs'!K61 -> -38146.667 | ... O31: ='Model inputs'!O63-'Model inputs'!O58-'Model inputs'!O61 -> -32220 | X31: 0
A32: TenantGuard revenue · TenantGuard unit economics | D32: ='Model inputs'!D33*'Model inputs'!B6 -> 6500 | E32: ='Model inputs'!E33*'Model inputs'!B6 -> 13000 | F32: ='Model inputs'!F33*'Model inputs'!B6 -> 19500 | G32: ='Model inputs'!G33*'Model inputs'!B6 -> 26000 | H32: ='Model inputs'!H33*'Model inputs'!B6 -> 32500 | I32: ='Model inputs'!I33*'Model inputs'!B6 -> 39000 | J32: ='Model inputs'!J33*'Model inputs'!B6 -> 45500 | K32: ='Model inputs'!K33*'Model inputs'!B6 -> 52000 | L32: ='Model inputs'!L33*'Model inputs'!B6 -> 58500 | M32: ='Model inputs'!M33*'Model inputs'!B6 -> 65000 | N32: ='Model inputs'!N33*'Model inputs'!B6 -> 71500 | O32: ='Model inputs'!O33*'Model inputs'!B6 -> 78000 | P32: 0 | Q32: 0 | R32: 0 | S32: 0 | T32: 0 | U32: 0 | V32: 0 | W32: 0 | X32: 0 | Y32: ='Model inputs'!Y39*'Model inputs'!B6 -> 78000 | Z32: ='Model inputs'!Z39*'Model inputs'!B6 -> 78000 | AA32: ='Model inputs'!AA39*'Model inputs'!B6 -> 78000 | AB32: ='Model inputs'!AB39*'Model inputs'!B6 -> 78000 | AC32: ='Model inputs'!AC39*'Model inputs'!B6 -> 78000 | AD32: ='Model inputs'!AD39*'Model inputs'!B6 -> 78000 | AE32: ='Model inputs'!AE39*'Model inputs'!B6 -> 78000 | AF32: ='Model inputs'!AF39*'Model inputs'!B6 -> 78000 | AG32: ='Model inputs'!AG39*'Model inputs'!B6 -> 78000 | AH32: ='Model inputs'!AH39*'Model inputs'!B6 -> 78000 | AI32: ='Model inputs'!AI39*'Model inputs'!B6 -> 78000 | AJ32: ='Model inputs'!AJ39*'Model inputs'!B6 -> 78000 | AK32: ='Model inputs'!AK39*'Model inputs'!B6 -> 78000 | AL32: ='Model inputs'!AL39*'Model inputs'!B6 -> 78000 | AM32: ='Model inputs'!AM39*'Model inputs'!B6 -> 78000 | AN32: ='Model inputs'!AN39*'Model inputs'!B6 -> 78000 | AO32: ='Model inputs'!AO39*'Model inputs'!B6 -> 78000 | AP32: ='Model inputs'!AP39*'Model inputs'!B6 -> 78000 | AQ32: ='Model inputs'!AQ39*'Model inputs'!B6 -> 78000 | AR32: ='Model inputs'!AR39*'Model inputs'!B6 -> 78000 | AS32: ='Model inputs'!AS39*'Model inputs'!B6 -> 78000 | AT32: ='Model inputs'!AT39*'Model inputs'!B6 -> 78000 | AU32: ='Model inputs'!AU39*'Model inputs'!B6 -> 78000 | AV32: ='Model inputs'!AV39*'Model inputs'!B6 -> 78000
A33: Ending customers · TenantGuard three-case revenue ramp | D33: ='Model inputs'!D23+'Model inputs'!D16-'Model inputs'!D13 -> 10 | E33: ='Model inputs'!E23+'Model inputs'!E16-'Model inputs'!E13 -> 20 | F33: ='Model inputs'!F23+'Model inputs'!F16-'Model inputs'!F13 -> 30 | G33: ='Model inputs'!G23+'Model inputs'!G16-'Model inputs'!G13 -> 40 | H33: ='Model inputs'!H23+'Model inputs'!H16-'Model inputs'!H13 -> 50 | I33: ='Model inputs'!I23+'Model inputs'!I16-'Model inputs'!I13 -> 60 | J33: ='Model inputs'!J23+'Model inputs'!J16-'Model inputs'!J13 -> 70 | K33: ='Model inputs'!K23+'Model inputs'!K16-'Model inputs'!K13 -> 80 | ... O33: ='Model inputs'!O23+'Model inputs'!O16-'Model inputs'!O13 -> 120 | P33: 0 | Q33: 0 | R33: 0 | S33: 0 | T33: 0 | U33: 0 | V33: 0 | W33: 0 | X33: 0
A34: Customer losses · TenantGuard three-case revenue ramp · TenantGuard — High | D34: =IF('Model inputs'!D14="","",'Model inputs'!D14) -> 0 | E34: =IF('Model inputs'!E14="","",'Model inputs'!E14) -> 0.21666667 | F34: =IF('Model inputs'!F14="","",'Model inputs'!F14) -> 0.43333333 | G34: =IF('Model inputs'!G14="","",'Model inputs'!G14) -> 0.65 | H34: =IF('Model inputs'!H14="","",'Model inputs'!H14) -> 0.86666667 | I34: =IF('Model inputs'!I14="","",'Model inputs'!I14) -> 1.0833333 | J34: =IF('Model inputs'!J14="","",'Model inputs'!J14) -> 1.3 | K34: =IF('Model inputs'!K14="","",'Model inputs'!K14) -> 1.5166667 | ... O34: =IF('Model inputs'!O14="","",'Model inputs'!O14) -> 2.3833333 | P34: 0 | Q34: 0 | R34: 0 | S34: 0 | T34: 0 | U34: 0 | V34: 0 | W34: 0 | X34: =IF('Model inputs'!X14="","",'Model inputs'!X14) -> 0
A35: Customer losses · TenantGuard three-case revenue ramp · TenantGuard — Low | D35: =IF('Model inputs'!D15="","",'Model inputs'!D15) -> 0 | E35: =IF('Model inputs'!E15="","",'Model inputs'!E15) -> 0.033333333 | F35: =IF('Model inputs'!F15="","",'Model inputs'!F15) -> 0.066666667 | G35: =IF('Model inputs'!G15="","",'Model inputs'!G15) -> 0.1 | H35: =IF('Model inputs'!H15="","",'Model inputs'!H15) -> 0.13333333 | I35: =IF('Model inputs'!I15="","",'Model inputs'!I15) -> 0.16666667 | J35: =IF('Model inputs'!J15="","",'Model inputs'!J15) -> 0.2 | K35: =IF('Model inputs'!K15="","",'Model inputs'!K15) -> 0.23333333 | ... O35: =IF('Model inputs'!O15="","",'Model inputs'!O15) -> 0.36666667 | P35: 0 | Q35: 0 | R35: 0 | S35: 0 | T35: 0 | U35: 0 | V35: 0 | W35: 0 | X35: =IF('Model inputs'!X15="","",'Model inputs'!X15) -> 0
A36: Customer ramp months · Gross customer additions · TenantGuard three-case revenue ramp · Main Scenario · Main Scenario | C36: ='TenantGuard launch settings'!B6 -> 12
A37: Customer ramp months · Gross customer additions · TenantGuard — High · TenantGuard — High | C37: ='TenantGuard launch settings'!B6 -> 12
A38: Customer ramp months · Gross customer additions · TenantGuard — Low · TenantGuard — Low | C38: ='TenantGuard launch settings'!B6 -> 12
A39: Ending customers · TenantGuard revenue · TenantGuard unit economics · Main Scenario | D39: =IF('Model inputs'!D33="","",'Model inputs'!D33) -> 10 | E39: =IF('Model inputs'!E33="","",'Model inputs'!E33) -> 20 | F39: =IF('Model inputs'!F33="","",'Model inputs'!F33) -> 30 | G39: =IF('Model inputs'!G33="","",'Model inputs'!G33) -> 40 | H39: =IF('Model inputs'!H33="","",'Model inputs'!H33) -> 50 | I39: =IF('Model inputs'!I33="","",'Model inputs'!I33) -> 60 | J39: =IF('Model inputs'!J33="","",'Model inputs'!J33) -> 70 | K39: =IF('Model inputs'!K33="","",'Model inputs'!K33) -> 80 | ... X39: =IF('Model inputs'!X33="","",'Model inputs'!X33) -> 0 | Y39: ='Model inputs'!Y81+'Model inputs'!Y80-'Model inputs'!Y75 -> 120 | Z39: ='Model inputs'!Z81+'Model inputs'!Z80-'Model inputs'!Z75 -> 120 | AA39: ='Model inputs'!AA81+'Model inputs'!AA80-'Model inputs'!AA75 -> 120 | AB39: ='Model inputs'!AB81+'Model inputs'!AB80-'Model inputs'!AB75 -> 120 | AC39: ='Model inputs'!AC81+'Model inputs'!AC80-'Model inputs'!AC75 -> 120 | AD39: ='Model inputs'!AD81+'Model inputs'!AD80-'Model inputs'!AD75 -> 120 | AE39: ='Model inputs'!AE81+'Model inputs'!AE80-'Model inputs'!AE75 -> 120 | AF39: ='Model inputs'!AF81+'Model inputs'!AF80-'Model inputs'!AF75 -> 120 | ... AV39: ='Model inputs'!AV81+'Model inputs'!AV80-'Model inputs'!AV75 -> 120
A40: Ending customers · TenantGuard three-case revenue ramp · TenantGuard — High | D40: ='Model inputs'!D24+'Model inputs'!D17-'Model inputs'!D14 -> 21.666667 | E40: ='Model inputs'!E24+'Model inputs'!E17-'Model inputs'!E14 -> 43.333333 | F40: ='Model inputs'!F24+'Model inputs'!F17-'Model inputs'!F14 -> 65 | G40: ='Model inputs'!G24+'Model inputs'!G17-'Model inputs'!G14 -> 86.666667 | H40: ='Model inputs'!H24+'Model inputs'!H17-'Model inputs'!H14 -> 108.33333 | I40: ='Model inputs'!I24+'Model inputs'!I17-'Model inputs'!I14 -> 130 | J40: ='Model inputs'!J24+'Model inputs'!J17-'Model inputs'!J14 -> 151.66667 | K40: ='Model inputs'!K24+'Model inputs'!K17-'Model inputs'!K14 -> 173.33333 | ... O40: ='Model inputs'!O24+'Model inputs'!O17-'Model inputs'!O14 -> 260 | P40: 0 | Q40: 0 | R40: 0 | S40: 0 | T40: 0 | U40: 0 | V40: 0 | W40: 0 | X40: 0
A41: Ending customers · TenantGuard three-case revenue ramp · TenantGuard — Low | D41: ='Model inputs'!D25+'Model inputs'!D18-'Model inputs'!D15 -> 3.3333333 | E41: ='Model inputs'!E25+'Model inputs'!E18-'Model inputs'!E15 -> 6.6666667 | F41: ='Model inputs'!F25+'Model inputs'!F18-'Model inputs'!F15 -> 10 | G41: ='Model inputs'!G25+'Model inputs'!G18-'Model inputs'!G15 -> 13.333333 | H41: ='Model inputs'!H25+'Model inputs'!H18-'Model inputs'!H15 -> 16.666667 | I41: ='Model inputs'!I25+'Model inputs'!I18-'Model inputs'!I15 -> 20 | J41: ='Model inputs'!J25+'Model inputs'!J18-'Model inputs'!J15 -> 23.333333 | K41: ='Model inputs'!K25+'Model inputs'!K18-'Model inputs'!K15 -> 26.666667 | ... O41: ='Model inputs'!O25+'Model inputs'!O18-'Model inputs'!O15 -> 40 | P41: 0 | Q41: 0 | R41: 0 | S41: 0 | T41: 0 | U41: 0 | V41: 0 | W41: 0 | X41: 0
A42: Forecast month · TenantGuard three-case revenue ramp · Main Scenario | D42: =DATEDIF(DATE(2026,10,1),DATE(2026,10,1),"M")+1 -> 1 | E42: =DATEDIF(DATE(2026,10,1),DATE(2026,11,1),"M")+1 -> 2 | F42: =DATEDIF(DATE(2026,10,1),DATE(2026,12,1),"M")+1 -> 3 | G42: =DATEDIF(DATE(2026,10,1),DATE(2027,1,1),"M")+1 -> 4 | H42: =DATEDIF(DATE(2026,10,1),DATE(2027,2,1),"M")+1 -> 5 | I42: =DATEDIF(DATE(2026,10,1),DATE(2027,3,1),"M")+1 -> 6 | J42: =DATEDIF(DATE(2026,10,1),DATE(2027,4,1),"M")+1 -> 7 | K42: =DATEDIF(DATE(2026,10,1),DATE(2027,5,1),"M")+1 -> 8 | L42: =DATEDIF(DATE(2026,10,1),DATE(2027,6,1),"M")+1 -> 9 | M42: =DATEDIF(DATE(2026,10,1),DATE(2027,7,1),"M")+1 -> 10 | N42: =DATEDIF(DATE(2026,10,1),DATE(2027,8,1),"M")+1 -> 11 | O42: =DATEDIF(DATE(2026,10,1),DATE(2027,9,1),"M")+1 -> 12 | P42: 0 | Q42: 0 | R42: 0 | S42: 0 | T42: 0 | U42: 0 | V42: 0 | W42: 0 | X42: 0
A43: Forecast month · TenantGuard three-case revenue ramp · TenantGuard — High | D43: =DATEDIF(DATE(2026,10,1),DATE(2026,10,1),"M")+1 -> 1 | E43: =DATEDIF(DATE(2026,10,1),DATE(2026,11,1),"M")+1 -> 2 | F43: =DATEDIF(DATE(2026,10,1),DATE(2026,12,1),"M")+1 -> 3 | G43: =DATEDIF(DATE(2026,10,1),DATE(2027,1,1),"M")+1 -> 4 | H43: =DATEDIF(DATE(2026,10,1),DATE(2027,2,1),"M")+1 -> 5 | I43: =DATEDIF(DATE(2026,10,1),DATE(2027,3,1),"M")+1 -> 6 | J43: =DATEDIF(DATE(2026,10,1),DATE(2027,4,1),"M")+1 -> 7 | K43: =DATEDIF(DATE(2026,10,1),DATE(2027,5,1),"M")+1 -> 8 | L43: =DATEDIF(DATE(2026,10,1),DATE(2027,6,1),"M")+1 -> 9 | M43: =DATEDIF(DATE(2026,10,1),DATE(2027,7,1),"M")+1 -> 10 | N43: =DATEDIF(DATE(2026,10,1),DATE(2027,8,1),"M")+1 -> 11 | O43: =DATEDIF(DATE(2026,10,1),DATE(2027,9,1),"M")+1 -> 12 | P43: 0 | Q43: 0 | R43: 0 | S43: 0 | T43: 0 | U43: 0 | V43: 0 | W43: 0 | X43: 0
A44: Forecast month · TenantGuard three-case revenue ramp · TenantGuard — Low | D44: =DATEDIF(DATE(2026,10,1),DATE(2026,10,1),"M")+1 -> 1 | E44: =DATEDIF(DATE(2026,10,1),DATE(2026,11,1),"M")+1 -> 2 | F44: =DATEDIF(DATE(2026,10,1),DATE(2026,12,1),"M")+1 -> 3 | G44: =DATEDIF(DATE(2026,10,1),DATE(2027,1,1),"M")+1 -> 4 | H44: =DATEDIF(DATE(2026,10,1),DATE(2027,2,1),"M")+1 -> 5 | I44: =DATEDIF(DATE(2026,10,1),DATE(2027,3,1),"M")+1 -> 6 | J44: =DATEDIF(DATE(2026,10,1),DATE(2027,4,1),"M")+1 -> 7 | K44: =DATEDIF(DATE(2026,10,1),DATE(2027,5,1),"M")+1 -> 8 | L44: =DATEDIF(DATE(2026,10,1),DATE(2027,6,1),"M")+1 -> 9 | M44: =DATEDIF(DATE(2026,10,1),DATE(2027,7,1),"M")+1 -> 10 | N44: =DATEDIF(DATE(2026,10,1),DATE(2027,8,1),"M")+1 -> 11 | O44: =DATEDIF(DATE(2026,10,1),DATE(2027,9,1),"M")+1 -> 12 | P44: 0 | Q44: 0 | R44: 0 | S44: 0 | T44: 0 | U44: 0 | V44: 0 | W44: 0 | X44: 0
A45: Launch customers · Gross customer additions · TenantGuard three-case revenue ramp · Main Scenario · Main Scenario | C45: ='TenantGuard launch settings'!B5 -> 0
A46: Launch customers · Gross customer additions · TenantGuard — High · TenantGuard — High | C46: ='TenantGuard launch settings'!B5 -> 0
A47: Launch customers · Gross customer additions · TenantGuard — Low · TenantGuard — Low | C47: ='TenantGuard launch settings'!B5 -> 0
A48: Month 12 customers · Gross customer additions · TenantGuard three-case revenue ramp · Main Scenario · Main Scenario | C48: ='TenantGuard inputs'!B5 -> 120
A49: Month 12 customers · Gross customer additions · TenantGuard — High · TenantGuard — High | C49: =260 -> 260
A50: Month 12 customers · Gross customer additions · TenantGuard — Low · TenantGuard — Low | C50: =40 -> 40
A51: Monthly customer churn · Customer losses · TenantGuard three-case revenue ramp · Main Scenario · Main Scenario | C51: ='TenantGuard inputs'!B11 -> 0.01
A52: Monthly customer churn · Customer losses · TenantGuard — High · TenantGuard — High | C52: ='TenantGuard inputs'!B11 -> 0.01
A53: Monthly customer churn · Customer losses · TenantGuard — Low · TenantGuard — Low | C53: ='TenantGuard inputs'!B11 -> 0.01
A54: Opening customers · TenantGuard — High | D54: =IF('Model inputs'!D24="","",'Model inputs'!D24) -> 0 | E54: =IF('Model inputs'!E24="","",'Model inputs'!E24) -> 21.666667 | F54: =IF('Model inputs'!F24="","",'Model inputs'!F24) -> 43.333333 | G54: =IF('Model inputs'!G24="","",'Model inputs'!G24) -> 65 | H54: =IF('Model inputs'!H24="","",'Model inputs'!H24) -> 86.666667 | I54: =IF('Model inputs'!I24="","",'Model inputs'!I24) -> 108.33333 | J54: =IF('Model inputs'!J24="","",'Model inputs'!J24) -> 130 | K54: =IF('Model inputs'!K24="","",'Model inputs'!K24) -> 151.66667 | ... O54: =IF('Model inputs'!O24="","",'Model inputs'!O24) -> 238.33333 | P54: 0 | Q54: 0 | R54: 0 | S54: 0 | T54: 0 | U54: 0 | V54: 0 | W54: 0 | X54: =IF('Model inputs'!X24="","",'Model inputs'!X24) -> 0
A55: Opening customers · TenantGuard — Low | D55: =IF('Model inputs'!D25="","",'Model inputs'!D25) -> 0 | E55: =IF('Model inputs'!E25="","",'Model inputs'!E25) -> 3.3333333 | F55: =IF('Model inputs'!F25="","",'Model inputs'!F25) -> 6.6666667 | G55: =IF('Model inputs'!G25="","",'Model inputs'!G25) -> 10 | H55: =IF('Model inputs'!H25="","",'Model inputs'!H25) -> 13.333333 | I55: =IF('Model inputs'!I25="","",'Model inputs'!I25) -> 16.666667 | J55: =IF('Model inputs'!J25="","",'Model inputs'!J25) -> 20 | K55: =IF('Model inputs'!K25="","",'Model inputs'!K25) -> 23.333333 | ... O55: =IF('Model inputs'!O25="","",'Model inputs'!O25) -> 36.666667 | P55: 0 | Q55: 0 | R55: 0 | S55: 0 | T55: 0 | U55: 0 | V55: 0 | W55: 0 | X55: =IF('Model inputs'!X25="","",'Model inputs'!X25) -> 0
A56: Remediation compute COGS · Compute gross profit · Main Scenario · Main Scenario | D56: ='Model inputs'!D68*('Model inputs'!B82*'Model inputs'!B64+'Model inputs'!B71) -> 42.5 | E56: ='Model inputs'!E68*('Model inputs'!B82*'Model inputs'!B64+'Model inputs'!B71) -> 85 | F56: ='Model inputs'!F68*('Model inputs'!B82*'Model inputs'!B64+'Model inputs'!B71) -> 127.5 | G56: ='Model inputs'!G68*('Model inputs'!B82*'Model inputs'!B64+'Model inputs'!B71) -> 170 | H56: ='Model inputs'!H68*('Model inputs'!B82*'Model inputs'!B64+'Model inputs'!B71) -> 212.5 | I56: ='Model inputs'!I68*('Model inputs'!B82*'Model inputs'!B64+'Model inputs'!B71) -> 255 | J56: ='Model inputs'!J68*('Model inputs'!B82*'Model inputs'!B64+'Model inputs'!B71) -> 297.5 | K56: ='Model inputs'!K68*('Model inputs'!B82*'Model inputs'!B64+'Model inputs'!B71) -> 340 | L56: ='Model inputs'!L68*('Model inputs'!B82*'Model inputs'!B64+'Model inputs'!B71) -> 382.5 | M56: ='Model inputs'!M68*('Model inputs'!B82*'Model inputs'!B64+'Model inputs'!B71) -> 425 | N56: ='Model inputs'!N68*('Model inputs'!B82*'Model inputs'!B64+'Model inputs'!B71) -> 467.5 | O56: ='Model inputs'!O68*('Model inputs'!B82*'Model inputs'!B64+'Model inputs'!B71) -> 510 | P56: 0 | Q56: 0 | R56: 0 | S56: 0 | T56: 0 | U56: 0 | V56: 0 | W56: 0 | X56: 0
A57: Remediation compute COGS · TenantGuard three-case revenue ramp · TenantGuard — High | D57: ='Model inputs'!D69*('Model inputs'!C84*'Model inputs'!C66+'Model inputs'!C73) -> 86.666667 | E57: ='Model inputs'!E69*('Model inputs'!C84*'Model inputs'!C66+'Model inputs'!C73) -> 173.33333 | F57: ='Model inputs'!F69*('Model inputs'!C84*'Model inputs'!C66+'Model inputs'!C73) -> 260 | G57: ='Model inputs'!G69*('Model inputs'!C84*'Model inputs'!C66+'Model inputs'!C73) -> 346.66667 | H57: ='Model inputs'!H69*('Model inputs'!C84*'Model inputs'!C66+'Model inputs'!C73) -> 433.33333 | I57: ='Model inputs'!I69*('Model inputs'!C84*'Model inputs'!C66+'Model inputs'!C73) -> 520 | J57: ='Model inputs'!J69*('Model inputs'!C84*'Model inputs'!C66+'Model inputs'!C73) -> 606.66667 | K57: ='Model inputs'!K69*('Model inputs'!C84*'Model inputs'!C66+'Model inputs'!C73) -> 693.33333 | L57: ='Model inputs'!L69*('Model inputs'!C84*'Model inputs'!C66+'Model inputs'!C73) -> 780 | M57: ='Model inputs'!M69*('Model inputs'!C84*'Model inputs'!C66+'Model inputs'!C73) -> 866.66667 | N57: ='Model inputs'!N69*('Model inputs'!C84*'Model inputs'!C66+'Model inputs'!C73) -> 953.33333 | O57: ='Model inputs'!O69*('Model inputs'!C84*'Model inputs'!C66+'Model inputs'!C73) -> 1040 | P57: 0 | Q57: 0 | R57: 0 | S57: 0 | T57: 0 | U57: 0 | V57: 0 | W57: 0 | X57: 0
A58: Remediation compute COGS · TenantGuard three-case revenue ramp · TenantGuard — Low | D58: ='Model inputs'!D70*('Model inputs'!C85*'Model inputs'!C67+'Model inputs'!C74) -> 18.333333 | E58: ='Model inputs'!E70*('Model inputs'!C85*'Model inputs'!C67+'Model inputs'!C74) -> 36.666667 | F58: ='Model inputs'!F70*('Model inputs'!C85*'Model inputs'!C67+'Model inputs'!C74) -> 55 | G58: ='Model inputs'!G70*('Model inputs'!C85*'Model inputs'!C67+'Model inputs'!C74) -> 73.333333 | H58: ='Model inputs'!H70*('Model inputs'!C85*'Model inputs'!C67+'Model inputs'!C74) -> 91.666667 | I58: ='Model inputs'!I70*('Model inputs'!C85*'Model inputs'!C67+'Model inputs'!C74) -> 110 | J58: ='Model inputs'!J70*('Model inputs'!C85*'Model inputs'!C67+'Model inputs'!C74) -> 128.33333 | K58: ='Model inputs'!K70*('Model inputs'!C85*'Model inputs'!C67+'Model inputs'!C74) -> 146.66667 | L58: ='Model inputs'!L70*('Model inputs'!C85*'Model inputs'!C67+'Model inputs'!C74) -> 165 | M58: ='Model inputs'!M70*('Model inputs'!C85*'Model inputs'!C67+'Model inputs'!C74) -> 183.33333 | N58: ='Model inputs'!N70*('Model inputs'!C85*'Model inputs'!C67+'Model inputs'!C74) -> 201.66667 | O58: ='Model inputs'!O70*('Model inputs'!C85*'Model inputs'!C67+'Model inputs'!C74) -> 220 | P58: 0 | Q58: 0 | R58: 0 | S58: 0 | T58: 0 | U58: 0 | V58: 0 | W58: 0 | X58: 0
A59: TenantGuard fixed operating spend · TenantGuard ending cash · TenantGuard unit economics · Main Scenario · Main Scenario | D59: =IF('Model inputs'!B76="","",'Model inputs'!B76) -> 50000 | E59: =IF('Model inputs'!B76="","",'Model inputs'!B76) -> 50000 | F59: =IF('Model inputs'!B76="","",'Model inputs'!B76) -> 50000 | G59: =IF('Model inputs'!B76="","",'Model inputs'!B76) -> 50000 | H59: =IF('Model inputs'!B76="","",'Model inputs'!B76) -> 50000 | I59: =IF('Model inputs'!B76="","",'Model inputs'!B76) -> 50000 | J59: =IF('Model inputs'!B76="","",'Model inputs'!B76) -> 50000 | K59: =IF('Model inputs'!B76="","",'Model inputs'!B76) -> 50000 | L59: =IF('Model inputs'!B76="","",'Model inputs'!B76) -> 50000 | M59: =IF('Model inputs'!B76="","",'Model inputs'!B76) -> 50000 | N59: =IF('Model inputs'!B76="","",'Model inputs'!B76) -> 50000 | O59: =IF('Model inputs'!B76="","",'Model inputs'!B76) -> 50000 | P59: 0 | Q59: 0 | R59: 0 | S59: 0 | T59: 0 | U59: 0 | V59: 0 | W59: 0 | X59: 0
A60: TenantGuard fixed operating spend · TenantGuard — High | D60: =IF('Model inputs'!C78="","",'Model inputs'!C78) -> 50000 | E60: =IF('Model inputs'!C78="","",'Model inputs'!C78) -> 50000 | F60: =IF('Model inputs'!C78="","",'Model inputs'!C78) -> 50000 | G60: =IF('Model inputs'!C78="","",'Model inputs'!C78) -> 50000 | H60: =IF('Model inputs'!C78="","",'Model inputs'!C78) -> 50000 | I60: =IF('Model inputs'!C78="","",'Model inputs'!C78) -> 50000 | J60: =IF('Model inputs'!C78="","",'Model inputs'!C78) -> 50000 | K60: =IF('Model inputs'!C78="","",'Model inputs'!C78) -> 50000 | L60: =IF('Model inputs'!C78="","",'Model inputs'!C78) -> 50000 | M60: =IF('Model inputs'!C78="","",'Model inputs'!C78) -> 50000 | N60: =IF('Model inputs'!C78="","",'Model inputs'!C78) -> 50000 | O60: =IF('Model inputs'!C78="","",'Model inputs'!C78) -> 50000 | P60: 0 | Q60: 0 | R60: 0 | S60: 0 | T60: 0 | U60: 0 | V60: 0 | W60: 0 | X60: 0
A61: TenantGuard fixed operating spend · TenantGuard — Low | D61: =IF('Model inputs'!C79="","",'Model inputs'!C79) -> 50000 | E61: =IF('Model inputs'!C79="","",'Model inputs'!C79) -> 50000 | F61: =IF('Model inputs'!C79="","",'Model inputs'!C79) -> 50000 | G61: =IF('Model inputs'!C79="","",'Model inputs'!C79) -> 50000 | H61: =IF('Model inputs'!C79="","",'Model inputs'!C79) -> 50000 | I61: =IF('Model inputs'!C79="","",'Model inputs'!C79) -> 50000 | J61: =IF('Model inputs'!C79="","",'Model inputs'!C79) -> 50000 | K61: =IF('Model inputs'!C79="","",'Model inputs'!C79) -> 50000 | L61: =IF('Model inputs'!C79="","",'Model inputs'!C79) -> 50000 | M61: =IF('Model inputs'!C79="","",'Model inputs'!C79) -> 50000 | N61: =IF('Model inputs'!C79="","",'Model inputs'!C79) -> 50000 | O61: =IF('Model inputs'!C79="","",'Model inputs'!C79) -> 50000 | P61: 0 | Q61: 0 | R61: 0 | S61: 0 | T61: 0 | U61: 0 | V61: 0 | W61: 0 | X61: 0
A62: TenantGuard revenue · TenantGuard three-case revenue ramp · TenantGuard — High | D62: ='Model inputs'!D40*'Model inputs'!C8 -> 18416.667 | E62: ='Model inputs'!E40*'Model inputs'!C8 -> 36833.333 | F62: ='Model inputs'!F40*'Model inputs'!C8 -> 55250 | G62: ='Model inputs'!G40*'Model inputs'!C8 -> 73666.667 | H62: ='Model inputs'!H40*'Model inputs'!C8 -> 92083.333 | I62: ='Model inputs'!I40*'Model inputs'!C8 -> 110500 | J62: ='Model inputs'!J40*'Model inputs'!C8 -> 128916.67 | K62: ='Model inputs'!K40*'Model inputs'!C8 -> 147333.33 | L62: ='Model inputs'!L40*'Model inputs'!C8 -> 165750 | M62: ='Model inputs'!M40*'Model inputs'!C8 -> 184166.67 | N62: ='Model inputs'!N40*'Model inputs'!C8 -> 202583.33 | O62: ='Model inputs'!O40*'Model inputs'!C8 -> 221000 | P62: 0 | Q62: 0 | R62: 0 | S62: 0 | T62: 0 | U62: 0 | V62: 0 | W62: 0 | X62: 0
A63: TenantGuard revenue · TenantGuard three-case revenue ramp · TenantGuard — Low | D63: ='Model inputs'!D41*'Model inputs'!C9 -> 1500 | E63: ='Model inputs'!E41*'Model inputs'!C9 -> 3000 | F63: ='Model inputs'!F41*'Model inputs'!C9 -> 4500 | G63: ='Model inputs'!G41*'Model inputs'!C9 -> 6000 | H63: ='Model inputs'!H41*'Model inputs'!C9 -> 7500 | I63: ='Model inputs'!I41*'Model inputs'!C9 -> 9000 | J63: ='Model inputs'!J41*'Model inputs'!C9 -> 10500 | K63: ='Model inputs'!K41*'Model inputs'!C9 -> 12000 | L63: ='Model inputs'!L41*'Model inputs'!C9 -> 13500 | M63: ='Model inputs'!M41*'Model inputs'!C9 -> 15000 | N63: ='Model inputs'!N41*'Model inputs'!C9 -> 16500 | O63: ='Model inputs'!O41*'Model inputs'!C9 -> 18000 | P63: 0 | Q63: 0 | R63: 0 | S63: 0 | T63: 0 | U63: 0 | V63: 0 | W63: 0 | X63: 0
A64: Attempts per completed fix · TenantGuard unit economics · Main Scenario | B64: ='TenantGuard inputs'!B7 -> 2.5
A65: Attempts per completed fix · Remediation compute COGS · Compute gross profit · Main Scenario · Main Scenario · Main Scenario | C65: ='TenantGuard inputs'!B7 -> 2.5
A66: Attempts per completed fix · Remediation compute COGS · TenantGuard three-case revenue ramp · TenantGuard — High · TenantGuard — High | C66: =2 -> 2
A67: Attempts per completed fix · Remediation compute COGS · TenantGuard three-case revenue ramp · TenantGuard — Low · TenantGuard — Low | C67: =5 -> 5
A68: Completed remediations · Remediation compute COGS · Compute gross profit · Main Scenario · Main Scenario · Main Scenario | D68: ='Model inputs'!D33*'Model inputs'!B86 -> 1000 | E68: ='Model inputs'!E33*'Model inputs'!B86 -> 2000 | F68: ='Model inputs'!F33*'Model inputs'!B86 -> 3000 | G68: ='Model inputs'!G33*'Model inputs'!B86 -> 4000 | H68: ='Model inputs'!H33*'Model inputs'!B86 -> 5000 | I68: ='Model inputs'!I33*'Model inputs'!B86 -> 6000 | J68: ='Model inputs'!J33*'Model inputs'!B86 -> 7000 | K68: ='Model inputs'!K33*'Model inputs'!B86 -> 8000 | L68: ='Model inputs'!L33*'Model inputs'!B86 -> 9000 | M68: ='Model inputs'!M33*'Model inputs'!B86 -> 10000 | N68: ='Model inputs'!N33*'Model inputs'!B86 -> 11000 | O68: ='Model inputs'!O33*'Model inputs'!B86 -> 12000 | P68: 0 | Q68: 0 | R68: 0 | S68: 0 | T68: 0 | U68: 0 | V68: 0 | W68: 0 | X68: 0
A69: Completed remediations · Remediation compute COGS · TenantGuard three-case revenue ramp · TenantGuard — High · TenantGuard — High | D69: ='Model inputs'!D40*'Model inputs'!C88 -> 2166.6667 | E69: ='Model inputs'!E40*'Model inputs'!C88 -> 4333.3333 | F69: ='Model inputs'!F40*'Model inputs'!C88 -> 6500 | G69: ='Model inputs'!G40*'Model inputs'!C88 -> 8666.6667 | H69: ='Model inputs'!H40*'Model inputs'!C88 -> 10833.333 | I69: ='Model inputs'!I40*'Model inputs'!C88 -> 13000 | J69: ='Model inputs'!J40*'Model inputs'!C88 -> 15166.667 | K69: ='Model inputs'!K40*'Model inputs'!C88 -> 17333.333 | L69: ='Model inputs'!L40*'Model inputs'!C88 -> 19500 | M69: ='Model inputs'!M40*'Model inputs'!C88 -> 21666.667 | N69: ='Model inputs'!N40*'Model inputs'!C88 -> 23833.333 | O69: ='Model inputs'!O40*'Model inputs'!C88 -> 26000 | P69: 0 | Q69: 0 | R69: 0 | S69: 0 | T69: 0 | U69: 0 | V69: 0 | W69: 0 | X69: 0
A70: Completed remediations · Remediation compute COGS · TenantGuard three-case revenue ramp · TenantGuard — Low · TenantGuard — Low | D70: ='Model inputs'!D41*'Model inputs'!C89 -> 333.33333 | E70: ='Model inputs'!E41*'Model inputs'!C89 -> 666.66667 | F70: ='Model inputs'!F41*'Model inputs'!C89 -> 1000 | G70: ='Model inputs'!G41*'Model inputs'!C89 -> 1333.3333 | H70: ='Model inputs'!H41*'Model inputs'!C89 -> 1666.6667 | I70: ='Model inputs'!I41*'Model inputs'!C89 -> 2000 | J70: ='Model inputs'!J41*'Model inputs'!C89 -> 2333.3333 | K70: ='Model inputs'!K41*'Model inputs'!C89 -> 2666.6667 | L70: ='Model inputs'!L41*'Model inputs'!C89 -> 3000 | M70: ='Model inputs'!M41*'Model inputs'!C89 -> 3333.3333 | N70: ='Model inputs'!N41*'Model inputs'!C89 -> 3666.6667 | O70: ='Model inputs'!O41*'Model inputs'!C89 -> 4000 | P70: 0 | Q70: 0 | R70: 0 | S70: 0 | T70: 0 | U70: 0 | V70: 0 | W70: 0 | X70: 0
A71: Compute cost per completed fix · TenantGuard unit economics · Main Scenario | B71: ='TenantGuard inputs'!B10 -> 0.03
A72: Compute cost per completed fix · Remediation compute COGS · Compute gross profit · Main Scenario · Main Scenario · Main Scenario | C72: ='TenantGuard inputs'!B10 -> 0.03
A73: Compute cost per completed fix · Remediation compute COGS · TenantGuard three-case revenue ramp · TenantGuard — High · TenantGuard — High | C73: ='TenantGuard inputs'!B10 -> 0.03
A74: Compute cost per completed fix · Remediation compute COGS · TenantGuard three-case revenue ramp · TenantGuard — Low · TenantGuard — Low | C74: ='TenantGuard inputs'!B10 -> 0.03
A75: Customer losses · TenantGuard revenue · TenantGuard unit economics | D75: =IF('Model inputs'!D13="","",'Model inputs'!D13) -> 0 | E75: =IF('Model inputs'!E13="","",'Model inputs'!E13) -> 0.1 | F75: =IF('Model inputs'!F13="","",'Model inputs'!F13) -> 0.2 | G75: =IF('Model inputs'!G13="","",'Model inputs'!G13) -> 0.3 | H75: =IF('Model inputs'!H13="","",'Model inputs'!H13) -> 0.4 | I75: =IF('Model inputs'!I13="","",'Model inputs'!I13) -> 0.5 | J75: =IF('Model inputs'!J13="","",'Model inputs'!J13) -> 0.6 | K75: =IF('Model inputs'!K13="","",'Model inputs'!K13) -> 0.7 | ... X75: =IF('Model inputs'!X13="","",'Model inputs'!X13) -> 0 | Y75: ='Model inputs'!Y81*'Model inputs'!C51 -> 1.2 | Z75: ='Model inputs'!Z81*'Model inputs'!C51 -> 1.2 | AA75: ='Model inputs'!AA81*'Model inputs'!C51 -> 1.2 | AB75: ='Model inputs'!AB81*'Model inputs'!C51 -> 1.2 | AC75: ='Model inputs'!AC81*'Model inputs'!C51 -> 1.2 | AD75: ='Model inputs'!AD81*'Model inputs'!C51 -> 1.2 | AE75: ='Model inputs'!AE81*'Model inputs'!C51 -> 1.2 | AF75: ='Model inputs'!AF81*'Model inputs'!C51 -> 1.2 | AG75: ='Model inputs'!AG81*'Model inputs'!C51 -> 1.2 | AH75: ='Model inputs'!AH81*'Model inputs'!C51 -> 1.2 | AI75: ='Model inputs'!AI81*'Model inputs'!C51 -> 1.2 | AJ75: ='Model inputs'!AJ81*'Model inputs'!C51 -> 1.2 | AK75: ='Model inputs'!AK81*'Model inputs'!C51 -> 1.2 | AL75: ='Model inputs'!AL81*'Model inputs'!C51 -> 1.2 | AM75: ='Model inputs'!AM81*'Model inputs'!C51 -> 1.2 | AN75: ='Model inputs'!AN81*'Model inputs'!C51 -> 1.2 | AO75: ='Model inputs'!AO81*'Model inputs'!C51 -> 1.2 | AP75: ='Model inputs'!AP81*'Model inputs'!C51 -> 1.2 | AQ75: ='Model inputs'!AQ81*'Model inputs'!C51 -> 1.2 | AR75: ='Model inputs'!AR81*'Model inputs'!C51 -> 1.2 | AS75: ='Model inputs'!AS81*'Model inputs'!C51 -> 1.2 | AT75: ='Model inputs'!AT81*'Model inputs'!C51 -> 1.2 | AU75: ='Model inputs'!AU81*'Model inputs'!C51 -> 1.2 | AV75: ='Model inputs'!AV81*'Model inputs'!C51 -> 1.2
A76: Fixed monthly operating spend · TenantGuard unit economics · Main Scenario | B76: ='TenantGuard inputs'!B12 -> 50000
A77: Fixed monthly operating spend · TenantGuard fixed operating spend · TenantGuard ending cash · TenantGuard unit economics · Main Scenario · Main Scenario · Main Scenario | C77: ='TenantGuard inputs'!B12 -> 50000
A78: Fixed monthly operating spend · TenantGuard fixed operating spend · TenantGuard — High · TenantGuard — High | C78: ='TenantGuard inputs'!B12 -> 50000
A79: Fixed monthly operating spend · TenantGuard fixed operating spend · TenantGuard — Low · TenantGuard — Low | C79: ='TenantGuard inputs'!B12 -> 50000
A80: Gross customer additions · Ending customers · TenantGuard revenue · TenantGuard unit economics · Main Scenario | D80: =IF('Model inputs'!D16="","",'Model inputs'!D16) -> 10 | E80: =IF('Model inputs'!E16="","",'Model inputs'!E16) -> 10.1 | F80: =IF('Model inputs'!F16="","",'Model inputs'!F16) -> 10.2 | G80: =IF('Model inputs'!G16="","",'Model inputs'!G16) -> 10.3 | H80: =IF('Model inputs'!H16="","",'Model inputs'!H16) -> 10.4 | I80: =IF('Model inputs'!I16="","",'Model inputs'!I16) -> 10.5 | J80: =IF('Model inputs'!J16="","",'Model inputs'!J16) -> 10.6 | K80: =IF('Model inputs'!K16="","",'Model inputs'!K16) -> 10.7 | ... X80: =IF('Model inputs'!X16="","",'Model inputs'!X16) -> 0 | Y80: =IF(IF(IF(IF(ISERROR('Model inputs'!Y90<='Model inputs'!C36),'Model inputs'!Y90<='Model inputs'!C36,IF(OR('Model inputs'!Y90="",'Model inputs'!C36=""),"",'Model inputs'!Y90<='Model inputs'!C36))="",FALSE,IF(ISERROR('Model inputs'!Y90<='Model inputs'!C36),'Model inputs'!Y90<='Model inputs'!C36,IF(OR('Model inputs'!Y90="",'Model inputs'!C36=""),"",'Model inputs'!Y90<='Model inputs'!C36))),('Model inputs'!C48-'Model inputs'!C45)/'Model inputs'!C36,0)="",0,IF(IF(IF(ISERROR('Model inputs'!Y90<='Model inputs'!C36),'Model inputs'!Y90<='Model inputs'!C36,IF(OR('Model inputs'!Y90="",'Model inputs'!C36=""),"",'Model inputs'!Y90<='Model inputs'!C36))="",FALSE,IF(ISERROR('Model inputs'!Y90<='Model inputs'!C36),'Model inputs'!Y90<='Model inputs'!C36,IF(OR('Model inputs'!Y90="",'Model inputs'!C36=""),"",'Model inputs'!Y90<='Model inputs'!C36))),('Model inputs'!C48-'Model inputs'!C45)/'Model inputs'!C36,0))+'Model inputs'!Y81*'Model inputs'!C51 -> 1.2 | Z80: =IF(IF(IF(IF(ISERROR('Model inputs'!Z90<='Model inputs'!C36),'Model inputs'!Z90<='Model inputs'!C36,IF(OR('Model inputs'!Z90="",'Model inputs'!C36=""),"",'Model inputs'!Z90<='Model inputs'!C36))="",FALSE,IF(ISERROR('Model inputs'!Z90<='Model inputs'!C36),'Model inputs'!Z90<='Model inputs'!C36,IF(OR('Model inputs'!Z90="",'Model inputs'!C36=""),"",'Model inputs'!Z90<='Model inputs'!C36))),('Model inputs'!C48-'Model inputs'!C45)/'Model inputs'!C36,0)="",0,IF(IF(IF(ISERROR('Model inputs'!Z90<='Model inputs'!C36),'Model inputs'!Z90<='Model inputs'!C36,IF(OR('Model inputs'!Z90="",'Model inputs'!C36=""),"",'Model inputs'!Z90<='Model inputs'!C36))="",FALSE,IF(ISERROR('Model inputs'!Z90<='Model inputs'!C36),'Model inputs'!Z90<='Model inputs'!C36,IF(OR('Model inputs'!Z90="",'Model inputs'!C36=""),"",'Model inputs'!Z90<='Model inputs'!C36))),('Model inputs'!C48-'Model inputs'!C45)/'Model inputs'!C36,0))+'Model inputs'!Z81*'Model inputs'!C51 -> 1.2 | AA80: =IF(IF(IF(IF(ISERROR('Model inputs'!AA90<='Model inputs'!C36),'Model inputs'!AA90<='Model inputs'!C36,IF(OR('Model inputs'!AA90="",'Model inputs'!C36=""),"",'Model inputs'!AA90<='Model inputs'!C36))="",FALSE,IF(ISERROR('Model inputs'!AA90<='Model inputs'!C36),'Model inputs'!AA90<='Model inputs'!C36,IF(OR('Model inputs'!AA90="",'Model inputs'!C36=""),"",'Model inputs'!AA90<='Model inputs'!C36))),('Model inputs'!C48-'Model inputs'!C45)/'Model inputs'!C36,0)="",0,IF(IF(IF(ISERROR('Model inputs'!AA90<='Model inputs'!C36),'Model inputs'!AA90<='Model inputs'!C36,IF(OR('Model inputs'!AA90="",'Model inputs'!C36=""),"",'Model inputs'!AA90<='Model inputs'!C36))="",FALSE,IF(ISERROR('Model inputs'!AA90<='Model inputs'!C36),'Model inputs'!AA90<='Model inputs'!C36,IF(OR('Model inputs'!AA90="",'Model inputs'!C36=""),"",'Model inputs'!AA90<='Model inputs'!C36))),('Model inputs'!C48-'Model inputs'!C45)/'Model inputs'!C36,0))+'Model inputs'!AA81*'Model inputs'!C51 -> 1.2 | AB80: =IF(IF(IF(IF(ISERROR('Model inputs'!AB90<='Model inputs'!C36),'Model inputs'!AB90<='Model inputs'!C36,IF(OR('Model inputs'!AB90="",'Model inputs'!C36=""),"",'Model inputs'!AB90<='Model inputs'!C36))="",FALSE,IF(ISERROR('Model inputs'!AB90<='Model inputs'!C36),'Model inputs'!AB90<='Model inputs'!C36,IF(OR('Model inputs'!AB90="",'Model inputs'!C36=""),"",'Model inputs'!AB90<='Model inputs'!C36))),('Model inputs'!C48-'Model inputs'!C45)/'Model inputs'!C36,0)="",0,IF(IF(IF(ISERROR('Model inputs'!AB90<='Model inputs'!C36),'Model inputs'!AB90<='Model inputs'!C36,IF(OR('Model inputs'!AB90="",'Model inputs'!C36=""),"",'Model inputs'!AB90<='Model inputs'!C36))="",FALSE,IF(ISERROR('Model inputs'!AB90<='Model inputs'!C36),'Model inputs'!AB90<='Model inputs'!C36,IF(OR('Model inputs'!AB90="",'Model inputs'!C36=""),"",'Model inputs'!AB90<='Model inputs'!C36))),('Model inputs'!C48-'Model inputs'!C45)/'Model inputs'!C36,0))+'Model inputs'!AB81*'Model inputs'!C51 -> 1.2 | AC80: =IF(IF(IF(IF(ISERROR('Model inputs'!AC90<='Model inputs'!C36),'Model inputs'!AC90<='Model inputs'!C36,IF(OR('Model inputs'!AC90="",'Model inputs'!C36=""),"",'Model inputs'!AC90<='Model inputs'!C36))="",FALSE,IF(ISERROR('Model inputs'!AC90<='Model inputs'!C36),'Model inputs'!AC90<='Model inputs'!C36,IF(OR('Model inputs'!AC90="",'Model inputs'!C36=""),"",'Model inputs'!AC90<='Model inputs'!C36))),('Model inputs'!C48-'Model inputs'!C45)/'Model inputs'!C36,0)="",0,IF(IF(IF(ISERROR('Model inputs'!AC90<='Model inputs'!C36),'Model inputs'!AC90<='Model inputs'!C36,IF(OR('Model inputs'!AC90="",'Model inputs'!C36=""),"",'Model inputs'!AC90<='Model inputs'!C36))="",FALSE,IF(ISERROR('Model inputs'!AC90<='Model inputs'!C36),'Model inputs'!AC90<='Model inputs'!C36,IF(OR('Model inputs'!AC90="",'Model inputs'!C36=""),"",'Model inputs'!AC90<='Model inputs'!C36))),('Model inputs'!C48-'Model inputs'!C45)/'Model inputs'!C36,0))+'Model inputs'!AC81*'Model inputs'!C51 -> 1.2 | AD80: =IF(IF(IF(IF(ISERROR('Model inputs'!AD90<='Model inputs'!C36),'Model inputs'!AD90<='Model inputs'!C36,IF(OR('Model inputs'!AD90="",'Model inputs'!C36=""),"",'Model inputs'!AD90<='Model inputs'!C36))="",FALSE,IF(ISERROR('Model inputs'!AD90<='Model inputs'!C36),'Model inputs'!AD90<='Model inputs'!C36,IF(OR('Model inputs'!AD90="",'Model inputs'!C36=""),"",'Model inputs'!AD90<='Model inputs'!C36))),('Model inputs'!C48-'Model inputs'!C45)/'Model inputs'!C36,0)="",0,IF(IF(IF(ISERROR('Model inputs'!AD90<='Model inputs'!C36),'Model inputs'!AD90<='Model inputs'!C36,IF(OR('Model inputs'!AD90="",'Model inputs'!C36=""),"",'Model inputs'!AD90<='Model inputs'!C36))="",FALSE,IF(ISERROR('Model inputs'!AD90<='Model inputs'!C36),'Model inputs'!AD90<='Model inputs'!C36,IF(OR('Model inputs'!AD90="",'Model inputs'!C36=""),"",'Model inputs'!AD90<='Model inputs'!C36))),('Model inputs'!C48-'Model inputs'!C45)/'Model inputs'!C36,0))+'Model inputs'!AD81*'Model inputs'!C51 -> 1.2 | AE80: =IF(IF(IF(IF(ISERROR('Model inputs'!AE90<='Model inputs'!C36),'Model inputs'!AE90<='Model inputs'!C36,IF(OR('Model inputs'!AE90="",'Model inputs'!C36=""),"",'Model inputs'!AE90<='Model inputs'!C36))="",FALSE,IF(ISERROR('Model inputs'!AE90<='Model inputs'!C36),'Model inputs'!AE90<='Model inputs'!C36,IF(OR('Model inputs'!AE90="",'Model inputs'!C36=""),"",'Model inputs'!AE90<='Model inputs'!C36))),('Model inputs'!C48-'Model inputs'!C45)/'Model inputs'!C36,0)="",0,IF(IF(IF(ISERROR('Model inputs'!AE90<='Model inputs'!C36),'Model inputs'!AE90<='Model inputs'!C36,IF(OR('Model inputs'!AE90="",'Model inputs'!C36=""),"",'Model inputs'!AE90<='Model inputs'!C36))="",FALSE,IF(ISERROR('Model inputs'!AE90<='Model inputs'!C36),'Model inputs'!AE90<='Model inputs'!C36,IF(OR('Model inputs'!AE90="",'Model inputs'!C36=""),"",'Model inputs'!AE90<='Model inputs'!C36))),('Model inputs'!C48-'Model inputs'!C45)/'Model inputs'!C36,0))+'Model inputs'!AE81*'Model inputs'!C51 -> 1.2 | AF80: =IF(IF(IF(IF(ISERROR('Model inputs'!AF90<='Model inputs'!C36),'Model inputs'!AF90<='Model inputs'!C36,IF(OR('Model inputs'!AF90="",'Model inputs'!C36=""),"",'Model inputs'!AF90<='Model inputs'!C36))="",FALSE,IF(ISERROR('Model inputs'!AF90<='Model inputs'!C36),'Model inputs'!AF90<='Model inputs'!C36,IF(OR('Model inputs'!AF90="",'Model inputs'!C36=""),"",'Model inputs'!AF90<='Model inputs'!C36))),('Model inputs'!C48-'Model inputs'!C45)/'Model inputs'!C36,0)="",0,IF(IF(IF(ISERROR('Model inputs'!AF90<='Model inputs'!C36),'Model inputs'!AF90<='Model inputs'!C36,IF(OR('Model inputs'!AF90="",'Model inputs'!C36=""),"",'Model inputs'!AF90<='Model inputs'!C36))="",FALSE,IF(ISERROR('Model inputs'!AF90<='Model inputs'!C36),'Model inputs'!AF90<='Model inputs'!C36,IF(OR('Model inputs'!AF90="",'Model inputs'!C36=""),"",'Model inputs'!AF90<='Model inputs'!C36))),('Model inputs'!C48-'Model inputs'!C45)/'Model inputs'!C36,0))+'Model inputs'!AF81*'Model inputs'!C51 -> 1.2 | AG80: =IF(IF(IF(IF(ISERROR('Model inputs'!AG90<='Model inputs'!C36),'Model inputs'!AG90<='Model inputs'!C36,IF(OR('Model inputs'!AG90="",'Model inputs'!C36=""),"",'Model inputs'!AG90<='Model inputs'!C36))="",FALSE,IF(ISERROR('Model inputs'!AG90<='Model inputs'!C36),'Model inputs'!AG90<='Model inputs'!C36,IF(OR('Model inputs'!AG90="",'Model inputs'!C36=""),"",'Model inputs'!AG90<='Model inputs'!C36))),('Model inputs'!C48-'Model inputs'!C45)/'Model inputs'!C36,0)="",0,IF(IF(IF(ISERROR('Model inputs'!AG90<='Model inputs'!C36),'Model inputs'!AG90<='Model inputs'!C36,IF(OR('Model inputs'!AG90="",'Model inputs'!C36=""),"",'Model inputs'!AG90<='Model inputs'!C36))="",FALSE,IF(ISERROR('Model inputs'!AG90<='Model inputs'!C36),'Model inputs'!AG90<='Model inputs'!C36,IF(OR('Model inputs'!AG90="",'Model inputs'!C36=""),"",'Model inputs'!AG90<='Model inputs'!C36))),('Model inputs'!C48-'Model inputs'!C45)/'Model inputs'!C36,0))+'Model inputs'!AG81*'Model inputs'!C51 -> 1.2 | AH80: =IF(IF(IF(IF(ISERROR('Model inputs'!AH90<='Model inputs'!C36),'Model inputs'!AH90<='Model inputs'!C36,IF(OR('Model inputs'!AH90="",'Model inputs'!C36=""),"",'Model inputs'!AH90<='Model inputs'!C36))="",FALSE,IF(ISERROR('Model inputs'!AH90<='Model inputs'!C36),'Model inputs'!AH90<='Model inputs'!C36,IF(OR('Model inputs'!AH90="",'Model inputs'!C36=""),"",'Model inputs'!AH90<='Model inputs'!C36))),('Model inputs'!C48-'Model inputs'!C45)/'Model inputs'!C36,0)="",0,IF(IF(IF(ISERROR('Model inputs'!AH90<='Model inputs'!C36),'Model inputs'!AH90<='Model inputs'!C36,IF(OR('Model inputs'!AH90="",'Model inputs'!C36=""),"",'Model inputs'!AH90<='Model inputs'!C36))="",FALSE,IF(ISERROR('Model inputs'!AH90<='Model inputs'!C36),'Model inputs'!AH90<='Model inputs'!C36,IF(OR('Model inputs'!AH90="",'Model inputs'!C36=""),"",'Model inputs'!AH90<='Model inputs'!C36))),('Model inputs'!C48-'Model inputs'!C45)/'Model inputs'!C36,0))+'Model inputs'!AH81*'Model inputs'!C51 -> 1.2 | AI80: =IF(IF(IF(IF(ISERROR('Model inputs'!AI90<='Model inputs'!C36),'Model inputs'!AI90<='Model inputs'!C36,IF(OR('Model inputs'!AI90="",'Model inputs'!C36=""),"",'Model inputs'!AI90<='Model inputs'!C36))="",FALSE,IF(ISERROR('Model inputs'!AI90<='Model inputs'!C36),'Model inputs'!AI90<='Model inputs'!C36,IF(OR('Model inputs'!AI90="",'Model inputs'!C36=""),"",'Model inputs'!AI90<='Model inputs'!C36))),('Model inputs'!C48-'Model inputs'!C45)/'Model inputs'!C36,0)="",0,IF(IF(IF(ISERROR('Model inputs'!AI90<='Model inputs'!C36),'Model inputs'!AI90<='Model inputs'!C36,IF(OR('Model inputs'!AI90="",'Model inputs'!C36=""),"",'Model inputs'!AI90<='Model inputs'!C36))="",FALSE,IF(ISERROR('Model inputs'!AI90<='Model inputs'!C36),'Model inputs'!AI90<='Model inputs'!C36,IF(OR('Model inputs'!AI90="",'Model inputs'!C36=""),"",'Model inputs'!AI90<='Model inputs'!C36))),('Model inputs'!C48-'Model inputs'!C45)/'Model inputs'!C36,0))+'Model inputs'!AI81*'Model inputs'!C51 -> 1.2 | AJ80: =IF(IF(IF(IF(ISERROR('Model inputs'!AJ90<='Model inputs'!C36),'Model inputs'!AJ90<='Model inputs'!C36,IF(OR('Model inputs'!AJ90="",'Model inputs'!C36=""),"",'Model inputs'!AJ90<='Model inputs'!C36))="",FALSE,IF(ISERROR('Model inputs'!AJ90<='Model inputs'!C36),'Model inputs'!AJ90<='Model inputs'!C36,IF(OR('Model inputs'!AJ90="",'Model inputs'!C36=""),"",'Model inputs'!AJ90<='Model inputs'!C36))),('Model inputs'!C48-'Model inputs'!C45)/'Model inputs'!C36,0)="",0,IF(IF(IF(ISERROR('Model inputs'!AJ90<='Model inputs'!C36),'Model inputs'!AJ90<='Model inputs'!C36,IF(OR('Model inputs'!AJ90="",'Model inputs'!C36=""),"",'Model inputs'!AJ90<='Model inputs'!C36))="",FALSE,IF(ISERROR('Model inputs'!AJ90<='Model inputs'!C36),'Model inputs'!AJ90<='Model inputs'!C36,IF(OR('Model inputs'!AJ90="",'Model inputs'!C36=""),"",'Model inputs'!AJ90<='Model inputs'!C36))),('Model inputs'!C48-'Model inputs'!C45)/'Model inputs'!C36,0))+'Model inputs'!AJ81*'Model inputs'!C51 -> 1.2 | AK80: =IF(IF(IF(IF(ISERROR('Model inputs'!AK90<='Model inputs'!C36),'Model inputs'!AK90<='Model inputs'!C36,IF(OR('Model inputs'!AK90="",'Model inputs'!C36=""),"",'Model inputs'!AK90<='Model inputs'!C36))="",FALSE,IF(ISERROR('Model inputs'!AK90<='Model inputs'!C36),'Model inputs'!AK90<='Model inputs'!C36,IF(OR('Model inputs'!AK90="",'Model inputs'!C36=""),"",'Model inputs'!AK90<='Model inputs'!C36))),('Model inputs'!C48-'Model inputs'!C45)/'Model inputs'!C36,0)="",0,IF(IF(IF(ISERROR('Model inputs'!AK90<='Model inputs'!C36),'Model inputs'!AK90<='Model inputs'!C36,IF(OR('Model inputs'!AK90="",'Model inputs'!C36=""),"",'Model inputs'!AK90<='Model inputs'!C36))="",FALSE,IF(ISERROR('Model inputs'!AK90<='Model inputs'!C36),'Model inputs'!AK90<='Model inputs'!C36,IF(OR('Model inputs'!AK90="",'Model inputs'!C36=""),"",'Model inputs'!AK90<='Model inputs'!C36))),('Model inputs'!C48-'Model inputs'!C45)/'Model inputs'!C36,0))+'Model inputs'!AK81*'Model inputs'!C51 -> 1.2 | AL80: =IF(IF(IF(IF(ISERROR('Model inputs'!AL90<='Model inputs'!C36),'Model inputs'!AL90<='Model inputs'!C36,IF(OR('Model inputs'!AL90="",'Model inputs'!C36=""),"",'Model inputs'!AL90<='Model inputs'!C36))="",FALSE,IF(ISERROR('Model inputs'!AL90<='Model inputs'!C36),'Model inputs'!AL90<='Model inputs'!C36,IF(OR('Model inputs'!AL90="",'Model inputs'!C36=""),"",'Model inputs'!AL90<='Model inputs'!C36))),('Model inputs'!C48-'Model inputs'!C45)/'Model inputs'!C36,0)="",0,IF(IF(IF(ISERROR('Model inputs'!AL90<='Model inputs'!C36),'Model inputs'!AL90<='Model inputs'!C36,IF(OR('Model inputs'!AL90="",'Model inputs'!C36=""),"",'Model inputs'!AL90<='Model inputs'!C36))="",FALSE,IF(ISERROR('Model inputs'!AL90<='Model inputs'!C36),'Model inputs'!AL90<='Model inputs'!C36,IF(OR('Model inputs'!AL90="",'Model inputs'!C36=""),"",'Model inputs'!AL90<='Model inputs'!C36))),('Model inputs'!C48-'Model inputs'!C45)/'Model inputs'!C36,0))+'Model inputs'!AL81*'Model inputs'!C51 -> 1.2 | AM80: =IF(IF(IF(IF(ISERROR('Model inputs'!AM90<='Model inputs'!C36),'Model inputs'!AM90<='Model inputs'!C36,IF(OR('Model inputs'!AM90="",'Model inputs'!C36=""),"",'Model inputs'!AM90<='Model inputs'!C36))="",FALSE,IF(ISERROR('Model inputs'!AM90<='Model inputs'!C36),'Model inputs'!AM90<='Model inputs'!C36,IF(OR('Model inputs'!AM90="",'Model inputs'!C36=""),"",'Model inputs'!AM90<='Model inputs'!C36))),('Model inputs'!C48-'Model inputs'!C45)/'Model inputs'!C36,0)="",0,IF(IF(IF(ISERROR('Model inputs'!AM90<='Model inputs'!C36),'Model inputs'!AM90<='Model inputs'!C36,IF(OR('Model inputs'!AM90="",'Model inputs'!C36=""),"",'Model inputs'!AM90<='Model inputs'!C36))="",FALSE,IF(ISERROR('Model inputs'!AM90<='Model inputs'!C36),'Model inputs'!AM90<='Model inputs'!C36,IF(OR('Model inputs'!AM90="",'Model inputs'!C36=""),"",'Model inputs'!AM90<='Model inputs'!C36))),('Model inputs'!C48-'Model inputs'!C45)/'Model inputs'!C36,0))+'Model inputs'!AM81*'Model inputs'!C51 -> 1.2 | AN80: =IF(IF(IF(IF(ISERROR('Model inputs'!AN90<='Model inputs'!C36),'Model inputs'!AN90<='Model inputs'!C36,IF(OR('Model inputs'!AN90="",'Model inputs'!C36=""),"",'Model inputs'!AN90<='Model inputs'!C36))="",FALSE,IF(ISERROR('Model inputs'!AN90<='Model inputs'!C36),'Model inputs'!AN90<='Model inputs'!C36,IF(OR('Model inputs'!AN90="",'Model inputs'!C36=""),"",'Model inputs'!AN90<='Model inputs'!C36))),('Model inputs'!C48-'Model inputs'!C45)/'Model inputs'!C36,0)="",0,IF(IF(IF(ISERROR('Model inputs'!AN90<='Model inputs'!C36),'Model inputs'!AN90<='Model inputs'!C36,IF(OR('Model inputs'!AN90="",'Model inputs'!C36=""),"",'Model inputs'!AN90<='Model inputs'!C36))="",FALSE,IF(ISERROR('Model inputs'!AN90<='Model inputs'!C36),'Model inputs'!AN90<='Model inputs'!C36,IF(OR('Model inputs'!AN90="",'Model inputs'!C36=""),"",'Model inputs'!AN90<='Model inputs'!C36))),('Model inputs'!C48-'Model inputs'!C45)/'Model inputs'!C36,0))+'Model inputs'!AN81*'Model inputs'!C51 -> 1.2 | AO80: =IF(IF(IF(IF(ISERROR('Model inputs'!AO90<='Model inputs'!C36),'Model inputs'!AO90<='Model inputs'!C36,IF(OR('Model inputs'!AO90="",'Model inputs'!C36=""),"",'Model inputs'!AO90<='Model inputs'!C36))="",FALSE,IF(ISERROR('Model inputs'!AO90<='Model inputs'!C36),'Model inputs'!AO90<='Model inputs'!C36,IF(OR('Model inputs'!AO90="",'Model inputs'!C36=""),"",'Model inputs'!AO90<='Model inputs'!C36))),('Model inputs'!C48-'Model inputs'!C45)/'Model inputs'!C36,0)="",0,IF(IF(IF(ISERROR('Model inputs'!AO90<='Model inputs'!C36),'Model inputs'!AO90<='Model inputs'!C36,IF(OR('Model inputs'!AO90="",'Model inputs'!C36=""),"",'Model inputs'!AO90<='Model inputs'!C36))="",FALSE,IF(ISERROR('Model inputs'!AO90<='Model inputs'!C36),'Model inputs'!AO90<='Model inputs'!C36,IF(OR('Model inputs'!AO90="",'Model inputs'!C36=""),"",'Model inputs'!AO90<='Model inputs'!C36))),('Model inputs'!C48-'Model inputs'!C45)/'Model inputs'!C36,0))+'Model inputs'!AO81*'Model inputs'!C51 -> 1.2 | AP80: =IF(IF(IF(IF(ISERROR('Model inputs'!AP90<='Model inputs'!C36),'Model inputs'!AP90<='Model inputs'!C36,IF(OR('Model inputs'!AP90="",'Model inputs'!C36=""),"",'Model inputs'!AP90<='Model inputs'!C36))="",FALSE,IF(ISERROR('Model inputs'!AP90<='Model inputs'!C36),'Model inputs'!AP90<='Model inputs'!C36,IF(OR('Model inputs'!AP90="",'Model inputs'!C36=""),"",'Model inputs'!AP90<='Model inputs'!C36))),('Model inputs'!C48-'Model inputs'!C45)/'Model inputs'!C36,0)="",0,IF(IF(IF(ISERROR('Model inputs'!AP90<='Model inputs'!C36),'Model inputs'!AP90<='Model inputs'!C36,IF(OR('Model inputs'!AP90="",'Model inputs'!C36=""),"",'Model inputs'!AP90<='Model inputs'!C36))="",FALSE,IF(ISERROR('Model inputs'!AP90<='Model inputs'!C36),'Model inputs'!AP90<='Model inputs'!C36,IF(OR('Model inputs'!AP90="",'Model inputs'!C36=""),"",'Model inputs'!AP90<='Model inputs'!C36))),('Model inputs'!C48-'Model inputs'!C45)/'Model inputs'!C36,0))+'Model inputs'!AP81*'Model inputs'!C51 -> 1.2 | AQ80: =IF(IF(IF(IF(ISERROR('Model inputs'!AQ90<='Model inputs'!C36),'Model inputs'!AQ90<='Model inputs'!C36,IF(OR('Model inputs'!AQ90="",'Model inputs'!C36=""),"",'Model inputs'!AQ90<='Model inputs'!C36))="",FALSE,IF(ISERROR('Model inputs'!AQ90<='Model inputs'!C36),'Model inputs'!AQ90<='Model inputs'!C36,IF(OR('Model inputs'!AQ90="",'Model inputs'!C36=""),"",'Model inputs'!AQ90<='Model inputs'!C36))),('Model inputs'!C48-'Model inputs'!C45)/'Model inputs'!C36,0)="",0,IF(IF(IF(ISERROR('Model inputs'!AQ90<='Model inputs'!C36),'Model inputs'!AQ90<='Model inputs'!C36,IF(OR('Model inputs'!AQ90="",'Model inputs'!C36=""),"",'Model inputs'!AQ90<='Model inputs'!C36))="",FALSE,IF(ISERROR('Model inputs'!AQ90<='Model inputs'!C36),'Model inputs'!AQ90<='Model inputs'!C36,IF(OR('Model inputs'!AQ90="",'Model inputs'!C36=""),"",'Model inputs'!AQ90<='Model inputs'!C36))),('Model inputs'!C48-'Model inputs'!C45)/'Model inputs'!C36,0))+'Model inputs'!AQ81*'Model inputs'!C51 -> 1.2 | AR80: =IF(IF(IF(IF(ISERROR('Model inputs'!AR90<='Model inputs'!C36),'Model inputs'!AR90<='Model inputs'!C36,IF(OR('Model inputs'!AR90="",'Model inputs'!C36=""),"",'Model inputs'!AR90<='Model inputs'!C36))="",FALSE,IF(ISERROR('Model inputs'!AR90<='Model inputs'!C36),'Model inputs'!AR90<='Model inputs'!C36,IF(OR('Model inputs'!AR90="",'Model inputs'!C36=""),"",'Model inputs'!AR90<='Model inputs'!C36))),('Model inputs'!C48-'Model inputs'!C45)/'Model inputs'!C36,0)="",0,IF(IF(IF(ISERROR('Model inputs'!AR90<='Model inputs'!C36),'Model inputs'!AR90<='Model inputs'!C36,IF(OR('Model inputs'!AR90="",'Model inputs'!C36=""),"",'Model inputs'!AR90<='Model inputs'!C36))="",FALSE,IF(ISERROR('Model inputs'!AR90<='Model inputs'!C36),'Model inputs'!AR90<='Model inputs'!C36,IF(OR('Model inputs'!AR90="",'Model inputs'!C36=""),"",'Model inputs'!AR90<='Model inputs'!C36))),('Model inputs'!C48-'Model inputs'!C45)/'Model inputs'!C36,0))+'Model inputs'!AR81*'Model inputs'!C51 -> 1.2 | AS80: =IF(IF(IF(IF(ISERROR('Model inputs'!AS90<='Model inputs'!C36),'Model inputs'!AS90<='Model inputs'!C36,IF(OR('Model inputs'!AS90="",'Model inputs'!C36=""),"",'Model inputs'!AS90<='Model inputs'!C36))="",FALSE,IF(ISERROR('Model inputs'!AS90<='Model inputs'!C36),'Model inputs'!AS90<='Model inputs'!C36,IF(OR('Model inputs'!AS90="",'Model inputs'!C36=""),"",'Model inputs'!AS90<='Model inputs'!C36))),('Model inputs'!C48-'Model inputs'!C45)/'Model inputs'!C36,0)="",0,IF(IF(IF(ISERROR('Model inputs'!AS90<='Model inputs'!C36),'Model inputs'!AS90<='Model inputs'!C36,IF(OR('Model inputs'!AS90="",'Model inputs'!C36=""),"",'Model inputs'!AS90<='Model inputs'!C36))="",FALSE,IF(ISERROR('Model inputs'!AS90<='Model inputs'!C36),'Model inputs'!AS90<='Model inputs'!C36,IF(OR('Model inputs'!AS90="",'Model inputs'!C36=""),"",'Model inputs'!AS90<='Model inputs'!C36))),('Model inputs'!C48-'Model inputs'!C45)/'Model inputs'!C36,0))+'Model inputs'!AS81*'Model inputs'!C51 -> 1.2 | AT80: =IF(IF(IF(IF(ISERROR('Model inputs'!AT90<='Model inputs'!C36),'Model inputs'!AT90<='Model inputs'!C36,IF(OR('Model inputs'!AT90="",'Model inputs'!C36=""),"",'Model inputs'!AT90<='Model inputs'!C36))="",FALSE,IF(ISERROR('Model inputs'!AT90<='Model inputs'!C36),'Model inputs'!AT90<='Model inputs'!C36,IF(OR('Model inputs'!AT90="",'Model inputs'!C36=""),"",'Model inputs'!AT90<='Model inputs'!C36))),('Model inputs'!C48-'Model inputs'!C45)/'Model inputs'!C36,0)="",0,IF(IF(IF(ISERROR('Model inputs'!AT90<='Model inputs'!C36),'Model inputs'!AT90<='Model inputs'!C36,IF(OR('Model inputs'!AT90="",'Model inputs'!C36=""),"",'Model inputs'!AT90<='Model inputs'!C36))="",FALSE,IF(ISERROR('Model inputs'!AT90<='Model inputs'!C36),'Model inputs'!AT90<='Model inputs'!C36,IF(OR('Model inputs'!AT90="",'Model inputs'!C36=""),"",'Model inputs'!AT90<='Model inputs'!C36))),('Model inputs'!C48-'Model inputs'!C45)/'Model inputs'!C36,0))+'Model inputs'!AT81*'Model inputs'!C51 -> 1.2 | AU80: =IF(IF(IF(IF(ISERROR('Model inputs'!AU90<='Model inputs'!C36),'Model inputs'!AU90<='Model inputs'!C36,IF(OR('Model inputs'!AU90="",'Model inputs'!C36=""),"",'Model inputs'!AU90<='Model inputs'!C36))="",FALSE,IF(ISERROR('Model inputs'!AU90<='Model inputs'!C36),'Model inputs'!AU90<='Model inputs'!C36,IF(OR('Model inputs'!AU90="",'Model inputs'!C36=""),"",'Model inputs'!AU90<='Model inputs'!C36))),('Model inputs'!C48-'Model inputs'!C45)/'Model inputs'!C36,0)="",0,IF(IF(IF(ISERROR('Model inputs'!AU90<='Model inputs'!C36),'Model inputs'!AU90<='Model inputs'!C36,IF(OR('Model inputs'!AU90="",'Model inputs'!C36=""),"",'Model inputs'!AU90<='Model inputs'!C36))="",FALSE,IF(ISERROR('Model inputs'!AU90<='Model inputs'!C36),'Model inputs'!AU90<='Model inputs'!C36,IF(OR('Model inputs'!AU90="",'Model inputs'!C36=""),"",'Model inputs'!AU90<='Model inputs'!C36))),('Model inputs'!C48-'Model inputs'!C45)/'Model inputs'!C36,0))+'Model inputs'!AU81*'Model inputs'!C51 -> 1.2 | AV80: =IF(IF(IF(IF(ISERROR('Model inputs'!AV90<='Model inputs'!C36),'Model inputs'!AV90<='Model inputs'!C36,IF(OR('Model inputs'!AV90="",'Model inputs'!C36=""),"",'Model inputs'!AV90<='Model inputs'!C36))="",FALSE,IF(ISERROR('Model inputs'!AV90<='Model inputs'!C36),'Model inputs'!AV90<='Model inputs'!C36,IF(OR('Model inputs'!AV90="",'Model inputs'!C36=""),"",'Model inputs'!AV90<='Model inputs'!C36))),('Model inputs'!C48-'Model inputs'!C45)/'Model inputs'!C36,0)="",0,IF(IF(IF(ISERROR('Model inputs'!AV90<='Model inputs'!C36),'Model inputs'!AV90<='Model inputs'!C36,IF(OR('Model inputs'!AV90="",'Model inputs'!C36=""),"",'Model inputs'!AV90<='Model inputs'!C36))="",FALSE,IF(ISERROR('Model inputs'!AV90<='Model inputs'!C36),'Model inputs'!AV90<='Model inputs'!C36,IF(OR('Model inputs'!AV90="",'Model inputs'!C36=""),"",'Model inputs'!AV90<='Model inputs'!C36))),('Model inputs'!C48-'Model inputs'!C45)/'Model inputs'!C36,0))+'Model inputs'!AV81*'Model inputs'!C51 -> 1.2
A81: Opening customers · TenantGuard revenue · TenantGuard unit economics | D81: =IF('Model inputs'!D23="","",'Model inputs'!D23) -> 0 | E81: =IF('Model inputs'!E23="","",'Model inputs'!E23) -> 10 | F81: =IF('Model inputs'!F23="","",'Model inputs'!F23) -> 20 | G81: =IF('Model inputs'!G23="","",'Model inputs'!G23) -> 30 | H81: =IF('Model inputs'!H23="","",'Model inputs'!H23) -> 40 | I81: =IF('Model inputs'!I23="","",'Model inputs'!I23) -> 50 | J81: =IF('Model inputs'!J23="","",'Model inputs'!J23) -> 60 | K81: =IF('Model inputs'!K23="","",'Model inputs'!K23) -> 70 | ... X81: =IF('Model inputs'!X23="","",'Model inputs'!X23) -> 0 | Y81: =IF(IF(IF(ISERROR('Model inputs'!Y90=1),'Model inputs'!Y90=1,IF('Model inputs'!Y90="","",'Model inputs'!Y90=1))="",FALSE,IF(ISERROR('Model inputs'!Y90=1),'Model inputs'!Y90=1,IF('Model inputs'!Y90="","",'Model inputs'!Y90=1))),IF('Model inputs'!C45="","",'Model inputs'!C45),IF('Model inputs'!O33="","",'Model inputs'!O33)) -> 120 | Z81: =IF(IF(IF(ISERROR('Model inputs'!Z90=1),'Model inputs'!Z90=1,IF('Model inputs'!Z90="","",'Model inputs'!Z90=1))="",FALSE,IF(ISERROR('Model inputs'!Z90=1),'Model inputs'!Z90=1,IF('Model inputs'!Z90="","",'Model inputs'!Z90=1))),IF('Model inputs'!C45="","",'Model inputs'!C45),IF('Model inputs'!Y39="","",'Model inputs'!Y39)) -> 120 | AA81: =IF(IF(IF(ISERROR('Model inputs'!AA90=1),'Model inputs'!AA90=1,IF('Model inputs'!AA90="","",'Model inputs'!AA90=1))="",FALSE,IF(ISERROR('Model inputs'!AA90=1),'Model inputs'!AA90=1,IF('Model inputs'!AA90="","",'Model inputs'!AA90=1))),IF('Model inputs'!C45="","",'Model inputs'!C45),IF('Model inputs'!Z39="","",'Model inputs'!Z39)) -> 120 | AB81: =IF(IF(IF(ISERROR('Model inputs'!AB90=1),'Model inputs'!AB90=1,IF('Model inputs'!AB90="","",'Model inputs'!AB90=1))="",FALSE,IF(ISERROR('Model inputs'!AB90=1),'Model inputs'!AB90=1,IF('Model inputs'!AB90="","",'Model inputs'!AB90=1))),IF('Model inputs'!C45="","",'Model inputs'!C45),IF('Model inputs'!AA39="","",'Model inputs'!AA39)) -> 120 | AC81: =IF(IF(IF(ISERROR('Model inputs'!AC90=1),'Model inputs'!AC90=1,IF('Model inputs'!AC90="","",'Model inputs'!AC90=1))="",FALSE,IF(ISERROR('Model inputs'!AC90=1),'Model inputs'!AC90=1,IF('Model inputs'!AC90="","",'Model inputs'!AC90=1))),IF('Model inputs'!C45="","",'Model inputs'!C45),IF('Model inputs'!AB39="","",'Model inputs'!AB39)) -> 120 | AD81: =IF(IF(IF(ISERROR('Model inputs'!AD90=1),'Model inputs'!AD90=1,IF('Model inputs'!AD90="","",'Model inputs'!AD90=1))="",FALSE,IF(ISERROR('Model inputs'!AD90=1),'Model inputs'!AD90=1,IF('Model inputs'!AD90="","",'Model inputs'!AD90=1))),IF('Model inputs'!C45="","",'Model inputs'!C45),IF('Model inputs'!AC39="","",'Model inputs'!AC39)) -> 120 | AE81: =IF(IF(IF(ISERROR('Model inputs'!AE90=1),'Model inputs'!AE90=1,IF('Model inputs'!AE90="","",'Model inputs'!AE90=1))="",FALSE,IF(ISERROR('Model inputs'!AE90=1),'Model inputs'!AE90=1,IF('Model inputs'!AE90="","",'Model inputs'!AE90=1))),IF('Model inputs'!C45="","",'Model inputs'!C45),IF('Model inputs'!AD39="","",'Model inputs'!AD39)) -> 120 | AF81: =IF(IF(IF(ISERROR('Model inputs'!AF90=1),'Model inputs'!AF90=1,IF('Model inputs'!AF90="","",'Model inputs'!AF90=1))="",FALSE,IF(ISERROR('Model inputs'!AF90=1),'Model inputs'!AF90=1,IF('Model inputs'!AF90="","",'Model inputs'!AF90=1))),IF('Model inputs'!C45="","",'Model inputs'!C45),IF('Model inputs'!AE39="","",'Model inputs'!AE39)) -> 120 | AG81: =IF(IF(IF(ISERROR('Model inputs'!AG90=1),'Model inputs'!AG90=1,IF('Model inputs'!AG90="","",'Model inputs'!AG90=1))="",FALSE,IF(ISERROR('Model inputs'!AG90=1),'Model inputs'!AG90=1,IF('Model inputs'!AG90="","",'Model inputs'!AG90=1))),IF('Model inputs'!C45="","",'Model inputs'!C45),IF('Model inputs'!AF39="","",'Model inputs'!AF39)) -> 120 | AH81: =IF(IF(IF(ISERROR('Model inputs'!AH90=1),'Model inputs'!AH90=1,IF('Model inputs'!AH90="","",'Model inputs'!AH90=1))="",FALSE,IF(ISERROR('Model inputs'!AH90=1),'Model inputs'!AH90=1,IF('Model inputs'!AH90="","",'Model inputs'!AH90=1))),IF('Model inputs'!C45="","",'Model inputs'!C45),IF('Model inputs'!AG39="","",'Model inputs'!AG39)) -> 120 | AI81: =IF(IF(IF(ISERROR('Model inputs'!AI90=1),'Model inputs'!AI90=1,IF('Model inputs'!AI90="","",'Model inputs'!AI90=1))="",FALSE,IF(ISERROR('Model inputs'!AI90=1),'Model inputs'!AI90=1,IF('Model inputs'!AI90="","",'Model inputs'!AI90=1))),IF('Model inputs'!C45="","",'Model inputs'!C45),IF('Model inputs'!AH39="","",'Model inputs'!AH39)) -> 120 | AJ81: =IF(IF(IF(ISERROR('Model inputs'!AJ90=1),'Model inputs'!AJ90=1,IF('Model inputs'!AJ90="","",'Model inputs'!AJ90=1))="",FALSE,IF(ISERROR('Model inputs'!AJ90=1),'Model inputs'!AJ90=1,IF('Model inputs'!AJ90="","",'Model inputs'!AJ90=1))),IF('Model inputs'!C45="","",'Model inputs'!C45),IF('Model inputs'!AI39="","",'Model inputs'!AI39)) -> 120 | AK81: =IF(IF(IF(ISERROR('Model inputs'!AK90=1),'Model inputs'!AK90=1,IF('Model inputs'!AK90="","",'Model inputs'!AK90=1))="",FALSE,IF(ISERROR('Model inputs'!AK90=1),'Model inputs'!AK90=1,IF('Model inputs'!AK90="","",'Model inputs'!AK90=1))),IF('Model inputs'!C45="","",'Model inputs'!C45),IF('Model inputs'!AJ39="","",'Model inputs'!AJ39)) -> 120 | AL81: =IF(IF(IF(ISERROR('Model inputs'!AL90=1),'Model inputs'!AL90=1,IF('Model inputs'!AL90="","",'Model inputs'!AL90=1))="",FALSE,IF(ISERROR('Model inputs'!AL90=1),'Model inputs'!AL90=1,IF('Model inputs'!AL90="","",'Model inputs'!AL90=1))),IF('Model inputs'!C45="","",'Model inputs'!C45),IF('Model inputs'!AK39="","",'Model inputs'!AK39)) -> 120 | AM81: =IF(IF(IF(ISERROR('Model inputs'!AM90=1),'Model inputs'!AM90=1,IF('Model inputs'!AM90="","",'Model inputs'!AM90=1))="",FALSE,IF(ISERROR('Model inputs'!AM90=1),'Model inputs'!AM90=1,IF('Model inputs'!AM90="","",'Model inputs'!AM90=1))),IF('Model inputs'!C45="","",'Model inputs'!C45),IF('Model inputs'!AL39="","",'Model inputs'!AL39)) -> 120 | AN81: =IF(IF(IF(ISERROR('Model inputs'!AN90=1),'Model inputs'!AN90=1,IF('Model inputs'!AN90="","",'Model inputs'!AN90=1))="",FALSE,IF(ISERROR('Model inputs'!AN90=1),'Model inputs'!AN90=1,IF('Model inputs'!AN90="","",'Model inputs'!AN90=1))),IF('Model inputs'!C45="","",'Model inputs'!C45),IF('Model inputs'!AM39="","",'Model inputs'!AM39)) -> 120 | AO81: =IF(IF(IF(ISERROR('Model inputs'!AO90=1),'Model inputs'!AO90=1,IF('Model inputs'!AO90="","",'Model inputs'!AO90=1))="",FALSE,IF(ISERROR('Model inputs'!AO90=1),'Model inputs'!AO90=1,IF('Model inputs'!AO90="","",'Model inputs'!AO90=1))),IF('Model inputs'!C45="","",'Model inputs'!C45),IF('Model inputs'!AN39="","",'Model inputs'!AN39)) -> 120 | AP81: =IF(IF(IF(ISERROR('Model inputs'!AP90=1),'Model inputs'!AP90=1,IF('Model inputs'!AP90="","",'Model inputs'!AP90=1))="",FALSE,IF(ISERROR('Model inputs'!AP90=1),'Model inputs'!AP90=1,IF('Model inputs'!AP90="","",'Model inputs'!AP90=1))),IF('Model inputs'!C45="","",'Model inputs'!C45),IF('Model inputs'!AO39="","",'Model inputs'!AO39)) -> 120 | AQ81: =IF(IF(IF(ISERROR('Model inputs'!AQ90=1),'Model inputs'!AQ90=1,IF('Model inputs'!AQ90="","",'Model inputs'!AQ90=1))="",FALSE,IF(ISERROR('Model inputs'!AQ90=1),'Model inputs'!AQ90=1,IF('Model inputs'!AQ90="","",'Model inputs'!AQ90=1))),IF('Model inputs'!C45="","",'Model inputs'!C45),IF('Model inputs'!AP39="","",'Model inputs'!AP39)) -> 120 | AR81: =IF(IF(IF(ISERROR('Model inputs'!AR90=1),'Model inputs'!AR90=1,IF('Model inputs'!AR90="","",'Model inputs'!AR90=1))="",FALSE,IF(ISERROR('Model inputs'!AR90=1),'Model inputs'!AR90=1,IF('Model inputs'!AR90="","",'Model inputs'!AR90=1))),IF('Model inputs'!C45="","",'Model inputs'!C45),IF('Model inputs'!AQ39="","",'Model inputs'!AQ39)) -> 120 | AS81: =IF(IF(IF(ISERROR('Model inputs'!AS90=1),'Model inputs'!AS90=1,IF('Model inputs'!AS90="","",'Model inputs'!AS90=1))="",FALSE,IF(ISERROR('Model inputs'!AS90=1),'Model inputs'!AS90=1,IF('Model inputs'!AS90="","",'Model inputs'!AS90=1))),IF('Model inputs'!C45="","",'Model inputs'!C45),IF('Model inputs'!AR39="","",'Model inputs'!AR39)) -> 120 | AT81: =IF(IF(IF(ISERROR('Model inputs'!AT90=1),'Model inputs'!AT90=1,IF('Model inputs'!AT90="","",'Model inputs'!AT90=1))="",FALSE,IF(ISERROR('Model inputs'!AT90=1),'Model inputs'!AT90=1,IF('Model inputs'!AT90="","",'Model inputs'!AT90=1))),IF('Model inputs'!C45="","",'Model inputs'!C45),IF('Model inputs'!AS39="","",'Model inputs'!AS39)) -> 120 | AU81: =IF(IF(IF(ISERROR('Model inputs'!AU90=1),'Model inputs'!AU90=1,IF('Model inputs'!AU90="","",'Model inputs'!AU90=1))="",FALSE,IF(ISERROR('Model inputs'!AU90=1),'Model inputs'!AU90=1,IF('Model inputs'!AU90="","",'Model inputs'!AU90=1))),IF('Model inputs'!C45="","",'Model inputs'!C45),IF('Model inputs'!AT39="","",'Model inputs'!AT39)) -> 120 | AV81: =IF(IF(IF(ISERROR('Model inputs'!AV90=1),'Model inputs'!AV90=1,IF('Model inputs'!AV90="","",'Model inputs'!AV90=1))="",FALSE,IF(ISERROR('Model inputs'!AV90=1),'Model inputs'!AV90=1,IF('Model inputs'!AV90="","",'Model inputs'!AV90=1))),IF('Model inputs'!C45="","",'Model inputs'!C45),IF('Model inputs'!AU39="","",'Model inputs'!AU39)) -> 120
A82: Token cost per attempt · TenantGuard unit economics · Main Scenario | B82: ='TenantGuard inputs'!B9 -> 0.005
A83: Token cost per attempt · Remediation compute COGS · Compute gross profit · Main Scenario · Main Scenario · Main Scenario | C83: ='TenantGuard inputs'!B9 -> 0.005
A84: Token cost per attempt · Remediation compute COGS · TenantGuard three-case revenue ramp · TenantGuard — High · TenantGuard — High | C84: ='TenantGuard inputs'!B9 -> 0.005
A85: Token cost per attempt · Remediation compute COGS · TenantGuard three-case revenue ramp · TenantGuard — Low · TenantGuard — Low | C85: ='TenantGuard inputs'!B9 -> 0.005
A86: Fixes per customer per month · TenantGuard unit economics · Main Scenario | B86: ='TenantGuard inputs'!B8 -> 100
A87: Fixes per customer per month · Completed remediations · Remediation compute COGS · Compute gross profit · Main Scenario · Main Scenario · Main Scenario · Main Scenario | C87: ='TenantGuard inputs'!B8 -> 100
A88: Fixes per customer per month · Completed remediations · Remediation compute COGS · TenantGuard three-case revenue ramp · TenantGuard — High · TenantGuard — High · TenantGuard — High | C88: ='TenantGuard inputs'!B8 -> 100
A89: Fixes per customer per month · Completed remediations · Remediation compute COGS · TenantGuard three-case revenue ramp · TenantGuard — Low · TenantGuard — Low · TenantGuard — Low | C89: ='TenantGuard inputs'!B8 -> 100
A90: Forecast month · TenantGuard revenue · TenantGuard unit economics | D90: =IF('Model inputs'!D42="","",'Model inputs'!D42) -> 1 | E90: =IF('Model inputs'!E42="","",'Model inputs'!E42) -> 2 | F90: =IF('Model inputs'!F42="","",'Model inputs'!F42) -> 3 | G90: =IF('Model inputs'!G42="","",'Model inputs'!G42) -> 4 | H90: =IF('Model inputs'!H42="","",'Model inputs'!H42) -> 5 | I90: =IF('Model inputs'!I42="","",'Model inputs'!I42) -> 6 | J90: =IF('Model inputs'!J42="","",'Model inputs'!J42) -> 7 | K90: =IF('Model inputs'!K42="","",'Model inputs'!K42) -> 8 | ... X90: =IF('Model inputs'!X42="","",'Model inputs'!X42) -> 0 | Y90: =DATEDIF(DATE(2026,10,1),DATE(2027,10,1),"M")+1 -> 13 | Z90: =DATEDIF(DATE(2026,10,1),DATE(2027,11,1),"M")+1 -> 14 | AA90: =DATEDIF(DATE(2026,10,1),DATE(2027,12,1),"M")+1 -> 15 | AB90: =DATEDIF(DATE(2026,10,1),DATE(2028,1,1),"M")+1 -> 16 | AC90: =DATEDIF(DATE(2026,10,1),DATE(2028,2,1),"M")+1 -> 17 | AD90: =DATEDIF(DATE(2026,10,1),DATE(2028,3,1),"M")+1 -> 18 | AE90: =DATEDIF(DATE(2026,10,1),DATE(2028,4,1),"M")+1 -> 19 | AF90: =DATEDIF(DATE(2026,10,1),DATE(2028,5,1),"M")+1 -> 20 | AG90: =DATEDIF(DATE(2026,10,1),DATE(2028,6,1),"M")+1 -> 21 | AH90: =DATEDIF(DATE(2026,10,1),DATE(2028,7,1),"M")+1 -> 22 | AI90: =DATEDIF(DATE(2026,10,1),DATE(2028,8,1),"M")+1 -> 23 | AJ90: =DATEDIF(DATE(2026,10,1),DATE(2028,9,1),"M")+1 -> 24 | AK90: =DATEDIF(DATE(2026,10,1),DATE(2028,10,1),"M")+1 -> 25 | AL90: =DATEDIF(DATE(2026,10,1),DATE(2028,11,1),"M")+1 -> 26 | AM90: =DATEDIF(DATE(2026,10,1),DATE(2028,12,1),"M")+1 -> 27 | AN90: =DATEDIF(DATE(2026,10,1),DATE(2029,1,1),"M")+1 -> 28 | AO90: =DATEDIF(DATE(2026,10,1),DATE(2029,2,1),"M")+1 -> 29 | AP90: =DATEDIF(DATE(2026,10,1),DATE(2029,3,1),"M")+1 -> 30 | AQ90: =DATEDIF(DATE(2026,10,1),DATE(2029,4,1),"M")+1 -> 31 | AR90: =DATEDIF(DATE(2026,10,1),DATE(2029,5,1),"M")+1 -> 32 | AS90: =DATEDIF(DATE(2026,10,1),DATE(2029,6,1),"M")+1 -> 33 | AT90: =DATEDIF(DATE(2026,10,1),DATE(2029,7,1),"M")+1 -> 34 | AU90: =DATEDIF(DATE(2026,10,1),DATE(2029,8,1),"M")+1 -> 35 | AV90: =DATEDIF(DATE(2026,10,1),DATE(2029,9,1),"M")+1 -> 36
