Workbook

Sheet TenantGuard revenue ramp
A1: TenantGuard revenue ramp
A2: TenantGuard — Revenue · Main Scenario
A4: Variable / dimension | B4: 2026-10 | C4: 2026-11 | D4: 2026-12 | E4: 2027-01 | F4: 2027-02 | G4: 2027-03 | H4: 2027-04 | I4: 2027-05 | J4: 2027-06 | K4: 2027-07 | L4: 2027-08 | M4: 2027-09
A5: Forecast month | B5: =DATEDIF(DATE(2026,10,1),DATE(2026,10,1),"M")+1 -> 1 | C5: =DATEDIF(DATE(2026,10,1),DATE(2026,11,1),"M")+1 -> 2 | D5: =DATEDIF(DATE(2026,10,1),DATE(2026,12,1),"M")+1 -> 3 | E5: =DATEDIF(DATE(2026,10,1),DATE(2027,1,1),"M")+1 -> 4 | F5: =DATEDIF(DATE(2026,10,1),DATE(2027,2,1),"M")+1 -> 5 | G5: =DATEDIF(DATE(2026,10,1),DATE(2027,3,1),"M")+1 -> 6 | H5: =DATEDIF(DATE(2026,10,1),DATE(2027,4,1),"M")+1 -> 7 | I5: =DATEDIF(DATE(2026,10,1),DATE(2027,5,1),"M")+1 -> 8 | J5: =DATEDIF(DATE(2026,10,1),DATE(2027,6,1),"M")+1 -> 9 | K5: =DATEDIF(DATE(2026,10,1),DATE(2027,7,1),"M")+1 -> 10 | L5: =DATEDIF(DATE(2026,10,1),DATE(2027,8,1),"M")+1 -> 11 | M5: =DATEDIF(DATE(2026,10,1),DATE(2027,9,1),"M")+1 -> 12
A6: Opening customers | B6: =IF(IF(IF(ISERROR('TenantGuard revenue ramp'!B5=1),'TenantGuard revenue ramp'!B5=1,IF('TenantGuard revenue ramp'!B5="","",'TenantGuard revenue ramp'!B5=1))="",FALSE,IF(ISERROR('TenantGuard revenue ramp'!B5=1),'TenantGuard revenue ramp'!B5=1,IF('TenantGuard revenue ramp'!B5="","",'TenantGuard revenue ramp'!B5=1))),IF('Model inputs'!B14="","",'Model inputs'!B14),IF('Model inputs'!D11="","",'Model inputs'!D11)) -> 0 | C6: =IF(IF(IF(ISERROR('TenantGuard revenue ramp'!C5=1),'TenantGuard revenue ramp'!C5=1,IF('TenantGuard revenue ramp'!C5="","",'TenantGuard revenue ramp'!C5=1))="",FALSE,IF(ISERROR('TenantGuard revenue ramp'!C5=1),'TenantGuard revenue ramp'!C5=1,IF('TenantGuard revenue ramp'!C5="","",'TenantGuard revenue ramp'!C5=1))),IF('Model inputs'!B14="","",'Model inputs'!B14),IF('TenantGuard revenue ramp'!B9="","",'TenantGuard revenue ramp'!B9)) -> 10 | D6: =IF(IF(IF(ISERROR('TenantGuard revenue ramp'!D5=1),'TenantGuard revenue ramp'!D5=1,IF('TenantGuard revenue ramp'!D5="","",'TenantGuard revenue ramp'!D5=1))="",FALSE,IF(ISERROR('TenantGuard revenue ramp'!D5=1),'TenantGuard revenue ramp'!D5=1,IF('TenantGuard revenue ramp'!D5="","",'TenantGuard revenue ramp'!D5=1))),IF('Model inputs'!B14="","",'Model inputs'!B14),IF('TenantGuard revenue ramp'!C9="","",'TenantGuard revenue ramp'!C9)) -> 20 | E6: =IF(IF(IF(ISERROR('TenantGuard revenue ramp'!E5=1),'TenantGuard revenue ramp'!E5=1,IF('TenantGuard revenue ramp'!E5="","",'TenantGuard revenue ramp'!E5=1))="",FALSE,IF(ISERROR('TenantGuard revenue ramp'!E5=1),'TenantGuard revenue ramp'!E5=1,IF('TenantGuard revenue ramp'!E5="","",'TenantGuard revenue ramp'!E5=1))),IF('Model inputs'!B14="","",'Model inputs'!B14),IF('TenantGuard revenue ramp'!D9="","",'TenantGuard revenue ramp'!D9)) -> 30 | F6: =IF(IF(IF(ISERROR('TenantGuard revenue ramp'!F5=1),'TenantGuard revenue ramp'!F5=1,IF('TenantGuard revenue ramp'!F5="","",'TenantGuard revenue ramp'!F5=1))="",FALSE,IF(ISERROR('TenantGuard revenue ramp'!F5=1),'TenantGuard revenue ramp'!F5=1,IF('TenantGuard revenue ramp'!F5="","",'TenantGuard revenue ramp'!F5=1))),IF('Model inputs'!B14="","",'Model inputs'!B14),IF('TenantGuard revenue ramp'!E9="","",'TenantGuard revenue ramp'!E9)) -> 40 | G6: =IF(IF(IF(ISERROR('TenantGuard revenue ramp'!G5=1),'TenantGuard revenue ramp'!G5=1,IF('TenantGuard revenue ramp'!G5="","",'TenantGuard revenue ramp'!G5=1))="",FALSE,IF(ISERROR('TenantGuard revenue ramp'!G5=1),'TenantGuard revenue ramp'!G5=1,IF('TenantGuard revenue ramp'!G5="","",'TenantGuard revenue ramp'!G5=1))),IF('Model inputs'!B14="","",'Model inputs'!B14),IF('TenantGuard revenue ramp'!F9="","",'TenantGuard revenue ramp'!F9)) -> 50 | H6: =IF(IF(IF(ISERROR('TenantGuard revenue ramp'!H5=1),'TenantGuard revenue ramp'!H5=1,IF('TenantGuard revenue ramp'!H5="","",'TenantGuard revenue ramp'!H5=1))="",FALSE,IF(ISERROR('TenantGuard revenue ramp'!H5=1),'TenantGuard revenue ramp'!H5=1,IF('TenantGuard revenue ramp'!H5="","",'TenantGuard revenue ramp'!H5=1))),IF('Model inputs'!B14="","",'Model inputs'!B14),IF('TenantGuard revenue ramp'!G9="","",'TenantGuard revenue ramp'!G9)) -> 60 | I6: =IF(IF(IF(ISERROR('TenantGuard revenue ramp'!I5=1),'TenantGuard revenue ramp'!I5=1,IF('TenantGuard revenue ramp'!I5="","",'TenantGuard revenue ramp'!I5=1))="",FALSE,IF(ISERROR('TenantGuard revenue ramp'!I5=1),'TenantGuard revenue ramp'!I5=1,IF('TenantGuard revenue ramp'!I5="","",'TenantGuard revenue ramp'!I5=1))),IF('Model inputs'!B14="","",'Model inputs'!B14),IF('TenantGuard revenue ramp'!H9="","",'TenantGuard revenue ramp'!H9)) -> 70 | J6: =IF(IF(IF(ISERROR('TenantGuard revenue ramp'!J5=1),'TenantGuard revenue ramp'!J5=1,IF('TenantGuard revenue ramp'!J5="","",'TenantGuard revenue ramp'!J5=1))="",FALSE,IF(ISERROR('TenantGuard revenue ramp'!J5=1),'TenantGuard revenue ramp'!J5=1,IF('TenantGuard revenue ramp'!J5="","",'TenantGuard revenue ramp'!J5=1))),IF('Model inputs'!B14="","",'Model inputs'!B14),IF('TenantGuard revenue ramp'!I9="","",'TenantGuard revenue ramp'!I9)) -> 80 | K6: =IF(IF(IF(ISERROR('TenantGuard revenue ramp'!K5=1),'TenantGuard revenue ramp'!K5=1,IF('TenantGuard revenue ramp'!K5="","",'TenantGuard revenue ramp'!K5=1))="",FALSE,IF(ISERROR('TenantGuard revenue ramp'!K5=1),'TenantGuard revenue ramp'!K5=1,IF('TenantGuard revenue ramp'!K5="","",'TenantGuard revenue ramp'!K5=1))),IF('Model inputs'!B14="","",'Model inputs'!B14),IF('TenantGuard revenue ramp'!J9="","",'TenantGuard revenue ramp'!J9)) -> 90 | L6: =IF(IF(IF(ISERROR('TenantGuard revenue ramp'!L5=1),'TenantGuard revenue ramp'!L5=1,IF('TenantGuard revenue ramp'!L5="","",'TenantGuard revenue ramp'!L5=1))="",FALSE,IF(ISERROR('TenantGuard revenue ramp'!L5=1),'TenantGuard revenue ramp'!L5=1,IF('TenantGuard revenue ramp'!L5="","",'TenantGuard revenue ramp'!L5=1))),IF('Model inputs'!B14="","",'Model inputs'!B14),IF('TenantGuard revenue ramp'!K9="","",'TenantGuard revenue ramp'!K9)) -> 100 | M6: =IF(IF(IF(ISERROR('TenantGuard revenue ramp'!M5=1),'TenantGuard revenue ramp'!M5=1,IF('TenantGuard revenue ramp'!M5="","",'TenantGuard revenue ramp'!M5=1))="",FALSE,IF(ISERROR('TenantGuard revenue ramp'!M5=1),'TenantGuard revenue ramp'!M5=1,IF('TenantGuard revenue ramp'!M5="","",'TenantGuard revenue ramp'!M5=1))),IF('Model inputs'!B14="","",'Model inputs'!B14),IF('TenantGuard revenue ramp'!L9="","",'TenantGuard revenue ramp'!L9)) -> 110
A7: Gross customer additions | B7: =IF(IF(IF(IF(ISERROR('TenantGuard revenue ramp'!B5<='Model inputs'!B10),'TenantGuard revenue ramp'!B5<='Model inputs'!B10,IF(OR('TenantGuard revenue ramp'!B5="",'Model inputs'!B10=""),"",'TenantGuard revenue ramp'!B5<='Model inputs'!B10))="",FALSE,IF(ISERROR('TenantGuard revenue ramp'!B5<='Model inputs'!B10),'TenantGuard revenue ramp'!B5<='Model inputs'!B10,IF(OR('TenantGuard revenue ramp'!B5="",'Model inputs'!B10=""),"",'TenantGuard revenue ramp'!B5<='Model inputs'!B10))),('Model inputs'!B15-'Model inputs'!B14)/'Model inputs'!B10,0)="",0,IF(IF(IF(ISERROR('TenantGuard revenue ramp'!B5<='Model inputs'!B10),'TenantGuard revenue ramp'!B5<='Model inputs'!B10,IF(OR('TenantGuard revenue ramp'!B5="",'Model inputs'!B10=""),"",'TenantGuard revenue ramp'!B5<='Model inputs'!B10))="",FALSE,IF(ISERROR('TenantGuard revenue ramp'!B5<='Model inputs'!B10),'TenantGuard revenue ramp'!B5<='Model inputs'!B10,IF(OR('TenantGuard revenue ramp'!B5="",'Model inputs'!B10=""),"",'TenantGuard revenue ramp'!B5<='Model inputs'!B10))),('Model inputs'!B15-'Model inputs'!B14)/'Model inputs'!B10,0))+'TenantGuard revenue ramp'!B6*'Model inputs'!B16 -> 10 | C7: =IF(IF(IF(IF(ISERROR('TenantGuard revenue ramp'!C5<='Model inputs'!B10),'TenantGuard revenue ramp'!C5<='Model inputs'!B10,IF(OR('TenantGuard revenue ramp'!C5="",'Model inputs'!B10=""),"",'TenantGuard revenue ramp'!C5<='Model inputs'!B10))="",FALSE,IF(ISERROR('TenantGuard revenue ramp'!C5<='Model inputs'!B10),'TenantGuard revenue ramp'!C5<='Model inputs'!B10,IF(OR('TenantGuard revenue ramp'!C5="",'Model inputs'!B10=""),"",'TenantGuard revenue ramp'!C5<='Model inputs'!B10))),('Model inputs'!B15-'Model inputs'!B14)/'Model inputs'!B10,0)="",0,IF(IF(IF(ISERROR('TenantGuard revenue ramp'!C5<='Model inputs'!B10),'TenantGuard revenue ramp'!C5<='Model inputs'!B10,IF(OR('TenantGuard revenue ramp'!C5="",'Model inputs'!B10=""),"",'TenantGuard revenue ramp'!C5<='Model inputs'!B10))="",FALSE,IF(ISERROR('TenantGuard revenue ramp'!C5<='Model inputs'!B10),'TenantGuard revenue ramp'!C5<='Model inputs'!B10,IF(OR('TenantGuard revenue ramp'!C5="",'Model inputs'!B10=""),"",'TenantGuard revenue ramp'!C5<='Model inputs'!B10))),('Model inputs'!B15-'Model inputs'!B14)/'Model inputs'!B10,0))+'TenantGuard revenue ramp'!C6*'Model inputs'!B16 -> 10.1 | D7: =IF(IF(IF(IF(ISERROR('TenantGuard revenue ramp'!D5<='Model inputs'!B10),'TenantGuard revenue ramp'!D5<='Model inputs'!B10,IF(OR('TenantGuard revenue ramp'!D5="",'Model inputs'!B10=""),"",'TenantGuard revenue ramp'!D5<='Model inputs'!B10))="",FALSE,IF(ISERROR('TenantGuard revenue ramp'!D5<='Model inputs'!B10),'TenantGuard revenue ramp'!D5<='Model inputs'!B10,IF(OR('TenantGuard revenue ramp'!D5="",'Model inputs'!B10=""),"",'TenantGuard revenue ramp'!D5<='Model inputs'!B10))),('Model inputs'!B15-'Model inputs'!B14)/'Model inputs'!B10,0)="",0,IF(IF(IF(ISERROR('TenantGuard revenue ramp'!D5<='Model inputs'!B10),'TenantGuard revenue ramp'!D5<='Model inputs'!B10,IF(OR('TenantGuard revenue ramp'!D5="",'Model inputs'!B10=""),"",'TenantGuard revenue ramp'!D5<='Model inputs'!B10))="",FALSE,IF(ISERROR('TenantGuard revenue ramp'!D5<='Model inputs'!B10),'TenantGuard revenue ramp'!D5<='Model inputs'!B10,IF(OR('TenantGuard revenue ramp'!D5="",'Model inputs'!B10=""),"",'TenantGuard revenue ramp'!D5<='Model inputs'!B10))),('Model inputs'!B15-'Model inputs'!B14)/'Model inputs'!B10,0))+'TenantGuard revenue ramp'!D6*'Model inputs'!B16 -> 10.2 | E7: =IF(IF(IF(IF(ISERROR('TenantGuard revenue ramp'!E5<='Model inputs'!B10),'TenantGuard revenue ramp'!E5<='Model inputs'!B10,IF(OR('TenantGuard revenue ramp'!E5="",'Model inputs'!B10=""),"",'TenantGuard revenue ramp'!E5<='Model inputs'!B10))="",FALSE,IF(ISERROR('TenantGuard revenue ramp'!E5<='Model inputs'!B10),'TenantGuard revenue ramp'!E5<='Model inputs'!B10,IF(OR('TenantGuard revenue ramp'!E5="",'Model inputs'!B10=""),"",'TenantGuard revenue ramp'!E5<='Model inputs'!B10))),('Model inputs'!B15-'Model inputs'!B14)/'Model inputs'!B10,0)="",0,IF(IF(IF(ISERROR('TenantGuard revenue ramp'!E5<='Model inputs'!B10),'TenantGuard revenue ramp'!E5<='Model inputs'!B10,IF(OR('TenantGuard revenue ramp'!E5="",'Model inputs'!B10=""),"",'TenantGuard revenue ramp'!E5<='Model inputs'!B10))="",FALSE,IF(ISERROR('TenantGuard revenue ramp'!E5<='Model inputs'!B10),'TenantGuard revenue ramp'!E5<='Model inputs'!B10,IF(OR('TenantGuard revenue ramp'!E5="",'Model inputs'!B10=""),"",'TenantGuard revenue ramp'!E5<='Model inputs'!B10))),('Model inputs'!B15-'Model inputs'!B14)/'Model inputs'!B10,0))+'TenantGuard revenue ramp'!E6*'Model inputs'!B16 -> 10.3 | F7: =IF(IF(IF(IF(ISERROR('TenantGuard revenue ramp'!F5<='Model inputs'!B10),'TenantGuard revenue ramp'!F5<='Model inputs'!B10,IF(OR('TenantGuard revenue ramp'!F5="",'Model inputs'!B10=""),"",'TenantGuard revenue ramp'!F5<='Model inputs'!B10))="",FALSE,IF(ISERROR('TenantGuard revenue ramp'!F5<='Model inputs'!B10),'TenantGuard revenue ramp'!F5<='Model inputs'!B10,IF(OR('TenantGuard revenue ramp'!F5="",'Model inputs'!B10=""),"",'TenantGuard revenue ramp'!F5<='Model inputs'!B10))),('Model inputs'!B15-'Model inputs'!B14)/'Model inputs'!B10,0)="",0,IF(IF(IF(ISERROR('TenantGuard revenue ramp'!F5<='Model inputs'!B10),'TenantGuard revenue ramp'!F5<='Model inputs'!B10,IF(OR('TenantGuard revenue ramp'!F5="",'Model inputs'!B10=""),"",'TenantGuard revenue ramp'!F5<='Model inputs'!B10))="",FALSE,IF(ISERROR('TenantGuard revenue ramp'!F5<='Model inputs'!B10),'TenantGuard revenue ramp'!F5<='Model inputs'!B10,IF(OR('TenantGuard revenue ramp'!F5="",'Model inputs'!B10=""),"",'TenantGuard revenue ramp'!F5<='Model inputs'!B10))),('Model inputs'!B15-'Model inputs'!B14)/'Model inputs'!B10,0))+'TenantGuard revenue ramp'!F6*'Model inputs'!B16 -> 10.4 | G7: =IF(IF(IF(IF(ISERROR('TenantGuard revenue ramp'!G5<='Model inputs'!B10),'TenantGuard revenue ramp'!G5<='Model inputs'!B10,IF(OR('TenantGuard revenue ramp'!G5="",'Model inputs'!B10=""),"",'TenantGuard revenue ramp'!G5<='Model inputs'!B10))="",FALSE,IF(ISERROR('TenantGuard revenue ramp'!G5<='Model inputs'!B10),'TenantGuard revenue ramp'!G5<='Model inputs'!B10,IF(OR('TenantGuard revenue ramp'!G5="",'Model inputs'!B10=""),"",'TenantGuard revenue ramp'!G5<='Model inputs'!B10))),('Model inputs'!B15-'Model inputs'!B14)/'Model inputs'!B10,0)="",0,IF(IF(IF(ISERROR('TenantGuard revenue ramp'!G5<='Model inputs'!B10),'TenantGuard revenue ramp'!G5<='Model inputs'!B10,IF(OR('TenantGuard revenue ramp'!G5="",'Model inputs'!B10=""),"",'TenantGuard revenue ramp'!G5<='Model inputs'!B10))="",FALSE,IF(ISERROR('TenantGuard revenue ramp'!G5<='Model inputs'!B10),'TenantGuard revenue ramp'!G5<='Model inputs'!B10,IF(OR('TenantGuard revenue ramp'!G5="",'Model inputs'!B10=""),"",'TenantGuard revenue ramp'!G5<='Model inputs'!B10))),('Model inputs'!B15-'Model inputs'!B14)/'Model inputs'!B10,0))+'TenantGuard revenue ramp'!G6*'Model inputs'!B16 -> 10.5 | H7: =IF(IF(IF(IF(ISERROR('TenantGuard revenue ramp'!H5<='Model inputs'!B10),'TenantGuard revenue ramp'!H5<='Model inputs'!B10,IF(OR('TenantGuard revenue ramp'!H5="",'Model inputs'!B10=""),"",'TenantGuard revenue ramp'!H5<='Model inputs'!B10))="",FALSE,IF(ISERROR('TenantGuard revenue ramp'!H5<='Model inputs'!B10),'TenantGuard revenue ramp'!H5<='Model inputs'!B10,IF(OR('TenantGuard revenue ramp'!H5="",'Model inputs'!B10=""),"",'TenantGuard revenue ramp'!H5<='Model inputs'!B10))),('Model inputs'!B15-'Model inputs'!B14)/'Model inputs'!B10,0)="",0,IF(IF(IF(ISERROR('TenantGuard revenue ramp'!H5<='Model inputs'!B10),'TenantGuard revenue ramp'!H5<='Model inputs'!B10,IF(OR('TenantGuard revenue ramp'!H5="",'Model inputs'!B10=""),"",'TenantGuard revenue ramp'!H5<='Model inputs'!B10))="",FALSE,IF(ISERROR('TenantGuard revenue ramp'!H5<='Model inputs'!B10),'TenantGuard revenue ramp'!H5<='Model inputs'!B10,IF(OR('TenantGuard revenue ramp'!H5="",'Model inputs'!B10=""),"",'TenantGuard revenue ramp'!H5<='Model inputs'!B10))),('Model inputs'!B15-'Model inputs'!B14)/'Model inputs'!B10,0))+'TenantGuard revenue ramp'!H6*'Model inputs'!B16 -> 10.6 | I7: =IF(IF(IF(IF(ISERROR('TenantGuard revenue ramp'!I5<='Model inputs'!B10),'TenantGuard revenue ramp'!I5<='Model inputs'!B10,IF(OR('TenantGuard revenue ramp'!I5="",'Model inputs'!B10=""),"",'TenantGuard revenue ramp'!I5<='Model inputs'!B10))="",FALSE,IF(ISERROR('TenantGuard revenue ramp'!I5<='Model inputs'!B10),'TenantGuard revenue ramp'!I5<='Model inputs'!B10,IF(OR('TenantGuard revenue ramp'!I5="",'Model inputs'!B10=""),"",'TenantGuard revenue ramp'!I5<='Model inputs'!B10))),('Model inputs'!B15-'Model inputs'!B14)/'Model inputs'!B10,0)="",0,IF(IF(IF(ISERROR('TenantGuard revenue ramp'!I5<='Model inputs'!B10),'TenantGuard revenue ramp'!I5<='Model inputs'!B10,IF(OR('TenantGuard revenue ramp'!I5="",'Model inputs'!B10=""),"",'TenantGuard revenue ramp'!I5<='Model inputs'!B10))="",FALSE,IF(ISERROR('TenantGuard revenue ramp'!I5<='Model inputs'!B10),'TenantGuard revenue ramp'!I5<='Model inputs'!B10,IF(OR('TenantGuard revenue ramp'!I5="",'Model inputs'!B10=""),"",'TenantGuard revenue ramp'!I5<='Model inputs'!B10))),('Model inputs'!B15-'Model inputs'!B14)/'Model inputs'!B10,0))+'TenantGuard revenue ramp'!I6*'Model inputs'!B16 -> 10.7 | J7: =IF(IF(IF(IF(ISERROR('TenantGuard revenue ramp'!J5<='Model inputs'!B10),'TenantGuard revenue ramp'!J5<='Model inputs'!B10,IF(OR('TenantGuard revenue ramp'!J5="",'Model inputs'!B10=""),"",'TenantGuard revenue ramp'!J5<='Model inputs'!B10))="",FALSE,IF(ISERROR('TenantGuard revenue ramp'!J5<='Model inputs'!B10),'TenantGuard revenue ramp'!J5<='Model inputs'!B10,IF(OR('TenantGuard revenue ramp'!J5="",'Model inputs'!B10=""),"",'TenantGuard revenue ramp'!J5<='Model inputs'!B10))),('Model inputs'!B15-'Model inputs'!B14)/'Model inputs'!B10,0)="",0,IF(IF(IF(ISERROR('TenantGuard revenue ramp'!J5<='Model inputs'!B10),'TenantGuard revenue ramp'!J5<='Model inputs'!B10,IF(OR('TenantGuard revenue ramp'!J5="",'Model inputs'!B10=""),"",'TenantGuard revenue ramp'!J5<='Model inputs'!B10))="",FALSE,IF(ISERROR('TenantGuard revenue ramp'!J5<='Model inputs'!B10),'TenantGuard revenue ramp'!J5<='Model inputs'!B10,IF(OR('TenantGuard revenue ramp'!J5="",'Model inputs'!B10=""),"",'TenantGuard revenue ramp'!J5<='Model inputs'!B10))),('Model inputs'!B15-'Model inputs'!B14)/'Model inputs'!B10,0))+'TenantGuard revenue ramp'!J6*'Model inputs'!B16 -> 10.8 | K7: =IF(IF(IF(IF(ISERROR('TenantGuard revenue ramp'!K5<='Model inputs'!B10),'TenantGuard revenue ramp'!K5<='Model inputs'!B10,IF(OR('TenantGuard revenue ramp'!K5="",'Model inputs'!B10=""),"",'TenantGuard revenue ramp'!K5<='Model inputs'!B10))="",FALSE,IF(ISERROR('TenantGuard revenue ramp'!K5<='Model inputs'!B10),'TenantGuard revenue ramp'!K5<='Model inputs'!B10,IF(OR('TenantGuard revenue ramp'!K5="",'Model inputs'!B10=""),"",'TenantGuard revenue ramp'!K5<='Model inputs'!B10))),('Model inputs'!B15-'Model inputs'!B14)/'Model inputs'!B10,0)="",0,IF(IF(IF(ISERROR('TenantGuard revenue ramp'!K5<='Model inputs'!B10),'TenantGuard revenue ramp'!K5<='Model inputs'!B10,IF(OR('TenantGuard revenue ramp'!K5="",'Model inputs'!B10=""),"",'TenantGuard revenue ramp'!K5<='Model inputs'!B10))="",FALSE,IF(ISERROR('TenantGuard revenue ramp'!K5<='Model inputs'!B10),'TenantGuard revenue ramp'!K5<='Model inputs'!B10,IF(OR('TenantGuard revenue ramp'!K5="",'Model inputs'!B10=""),"",'TenantGuard revenue ramp'!K5<='Model inputs'!B10))),('Model inputs'!B15-'Model inputs'!B14)/'Model inputs'!B10,0))+'TenantGuard revenue ramp'!K6*'Model inputs'!B16 -> 10.9 | L7: =IF(IF(IF(IF(ISERROR('TenantGuard revenue ramp'!L5<='Model inputs'!B10),'TenantGuard revenue ramp'!L5<='Model inputs'!B10,IF(OR('TenantGuard revenue ramp'!L5="",'Model inputs'!B10=""),"",'TenantGuard revenue ramp'!L5<='Model inputs'!B10))="",FALSE,IF(ISERROR('TenantGuard revenue ramp'!L5<='Model inputs'!B10),'TenantGuard revenue ramp'!L5<='Model inputs'!B10,IF(OR('TenantGuard revenue ramp'!L5="",'Model inputs'!B10=""),"",'TenantGuard revenue ramp'!L5<='Model inputs'!B10))),('Model inputs'!B15-'Model inputs'!B14)/'Model inputs'!B10,0)="",0,IF(IF(IF(ISERROR('TenantGuard revenue ramp'!L5<='Model inputs'!B10),'TenantGuard revenue ramp'!L5<='Model inputs'!B10,IF(OR('TenantGuard revenue ramp'!L5="",'Model inputs'!B10=""),"",'TenantGuard revenue ramp'!L5<='Model inputs'!B10))="",FALSE,IF(ISERROR('TenantGuard revenue ramp'!L5<='Model inputs'!B10),'TenantGuard revenue ramp'!L5<='Model inputs'!B10,IF(OR('TenantGuard revenue ramp'!L5="",'Model inputs'!B10=""),"",'TenantGuard revenue ramp'!L5<='Model inputs'!B10))),('Model inputs'!B15-'Model inputs'!B14)/'Model inputs'!B10,0))+'TenantGuard revenue ramp'!L6*'Model inputs'!B16 -> 11 | M7: =IF(IF(IF(IF(ISERROR('TenantGuard revenue ramp'!M5<='Model inputs'!B10),'TenantGuard revenue ramp'!M5<='Model inputs'!B10,IF(OR('TenantGuard revenue ramp'!M5="",'Model inputs'!B10=""),"",'TenantGuard revenue ramp'!M5<='Model inputs'!B10))="",FALSE,IF(ISERROR('TenantGuard revenue ramp'!M5<='Model inputs'!B10),'TenantGuard revenue ramp'!M5<='Model inputs'!B10,IF(OR('TenantGuard revenue ramp'!M5="",'Model inputs'!B10=""),"",'TenantGuard revenue ramp'!M5<='Model inputs'!B10))),('Model inputs'!B15-'Model inputs'!B14)/'Model inputs'!B10,0)="",0,IF(IF(IF(ISERROR('TenantGuard revenue ramp'!M5<='Model inputs'!B10),'TenantGuard revenue ramp'!M5<='Model inputs'!B10,IF(OR('TenantGuard revenue ramp'!M5="",'Model inputs'!B10=""),"",'TenantGuard revenue ramp'!M5<='Model inputs'!B10))="",FALSE,IF(ISERROR('TenantGuard revenue ramp'!M5<='Model inputs'!B10),'TenantGuard revenue ramp'!M5<='Model inputs'!B10,IF(OR('TenantGuard revenue ramp'!M5="",'Model inputs'!B10=""),"",'TenantGuard revenue ramp'!M5<='Model inputs'!B10))),('Model inputs'!B15-'Model inputs'!B14)/'Model inputs'!B10,0))+'TenantGuard revenue ramp'!M6*'Model inputs'!B16 -> 11.1
A8: Customer losses | B8: ='TenantGuard revenue ramp'!B6*'Model inputs'!B16 -> 0 | C8: ='TenantGuard revenue ramp'!C6*'Model inputs'!B16 -> 0.1 | D8: ='TenantGuard revenue ramp'!D6*'Model inputs'!B16 -> 0.2 | E8: ='TenantGuard revenue ramp'!E6*'Model inputs'!B16 -> 0.3 | F8: ='TenantGuard revenue ramp'!F6*'Model inputs'!B16 -> 0.4 | G8: ='TenantGuard revenue ramp'!G6*'Model inputs'!B16 -> 0.5 | H8: ='TenantGuard revenue ramp'!H6*'Model inputs'!B16 -> 0.6 | I8: ='TenantGuard revenue ramp'!I6*'Model inputs'!B16 -> 0.7 | J8: ='TenantGuard revenue ramp'!J6*'Model inputs'!B16 -> 0.8 | K8: ='TenantGuard revenue ramp'!K6*'Model inputs'!B16 -> 0.9 | L8: ='TenantGuard revenue ramp'!L6*'Model inputs'!B16 -> 1 | M8: ='TenantGuard revenue ramp'!M6*'Model inputs'!B16 -> 1.1
A9: Ending customers | B9: ='TenantGuard revenue ramp'!B6+'TenantGuard revenue ramp'!B7-'TenantGuard revenue ramp'!B8 -> 10 | C9: ='TenantGuard revenue ramp'!C6+'TenantGuard revenue ramp'!C7-'TenantGuard revenue ramp'!C8 -> 20 | D9: ='TenantGuard revenue ramp'!D6+'TenantGuard revenue ramp'!D7-'TenantGuard revenue ramp'!D8 -> 30 | E9: ='TenantGuard revenue ramp'!E6+'TenantGuard revenue ramp'!E7-'TenantGuard revenue ramp'!E8 -> 40 | F9: ='TenantGuard revenue ramp'!F6+'TenantGuard revenue ramp'!F7-'TenantGuard revenue ramp'!F8 -> 50 | G9: ='TenantGuard revenue ramp'!G6+'TenantGuard revenue ramp'!G7-'TenantGuard revenue ramp'!G8 -> 60 | H9: ='TenantGuard revenue ramp'!H6+'TenantGuard revenue ramp'!H7-'TenantGuard revenue ramp'!H8 -> 70 | I9: ='TenantGuard revenue ramp'!I6+'TenantGuard revenue ramp'!I7-'TenantGuard revenue ramp'!I8 -> 80 | ... M9: ='TenantGuard revenue ramp'!M6+'TenantGuard revenue ramp'!M7-'TenantGuard revenue ramp'!M8 -> 120
A10: TenantGuard revenue | B10: ='TenantGuard revenue ramp'!B9*'Model inputs'!B7 -> 6500 | C10: ='TenantGuard revenue ramp'!C9*'Model inputs'!B7 -> 13000 | D10: ='TenantGuard revenue ramp'!D9*'Model inputs'!B7 -> 19500 | E10: ='TenantGuard revenue ramp'!E9*'Model inputs'!B7 -> 26000 | F10: ='TenantGuard revenue ramp'!F9*'Model inputs'!B7 -> 32500 | G10: ='TenantGuard revenue ramp'!G9*'Model inputs'!B7 -> 39000 | H10: ='TenantGuard revenue ramp'!H9*'Model inputs'!B7 -> 45500 | I10: ='TenantGuard revenue ramp'!I9*'Model inputs'!B7 -> 52000 | J10: ='TenantGuard revenue ramp'!J9*'Model inputs'!B7 -> 58500 | K10: ='TenantGuard revenue ramp'!K9*'Model inputs'!B7 -> 65000 | L10: ='TenantGuard revenue ramp'!L9*'Model inputs'!B7 -> 71500 | M10: ='TenantGuard revenue ramp'!M9*'Model inputs'!B7 -> 78000
A11: Completed remediations | B11: ='TenantGuard revenue ramp'!B9*'Model inputs'!B12 -> 1000 | C11: ='TenantGuard revenue ramp'!C9*'Model inputs'!B12 -> 2000 | D11: ='TenantGuard revenue ramp'!D9*'Model inputs'!B12 -> 3000 | E11: ='TenantGuard revenue ramp'!E9*'Model inputs'!B12 -> 4000 | F11: ='TenantGuard revenue ramp'!F9*'Model inputs'!B12 -> 5000 | G11: ='TenantGuard revenue ramp'!G9*'Model inputs'!B12 -> 6000 | H11: ='TenantGuard revenue ramp'!H9*'Model inputs'!B12 -> 7000 | I11: ='TenantGuard revenue ramp'!I9*'Model inputs'!B12 -> 8000 | J11: ='TenantGuard revenue ramp'!J9*'Model inputs'!B12 -> 9000 | K11: ='TenantGuard revenue ramp'!K9*'Model inputs'!B12 -> 10000 | L11: ='TenantGuard revenue ramp'!L9*'Model inputs'!B12 -> 11000 | M11: ='TenantGuard revenue ramp'!M9*'Model inputs'!B12 -> 12000
A12: Remediation compute COGS | B12: ='TenantGuard revenue ramp'!B11*('Model inputs'!B18*'Model inputs'!B6+'Model inputs'!B8) -> 42.5 | C12: ='TenantGuard revenue ramp'!C11*('Model inputs'!B18*'Model inputs'!B6+'Model inputs'!B8) -> 85 | D12: ='TenantGuard revenue ramp'!D11*('Model inputs'!B18*'Model inputs'!B6+'Model inputs'!B8) -> 127.5 | E12: ='TenantGuard revenue ramp'!E11*('Model inputs'!B18*'Model inputs'!B6+'Model inputs'!B8) -> 170 | F12: ='TenantGuard revenue ramp'!F11*('Model inputs'!B18*'Model inputs'!B6+'Model inputs'!B8) -> 212.5 | G12: ='TenantGuard revenue ramp'!G11*('Model inputs'!B18*'Model inputs'!B6+'Model inputs'!B8) -> 255 | H12: ='TenantGuard revenue ramp'!H11*('Model inputs'!B18*'Model inputs'!B6+'Model inputs'!B8) -> 297.5 | I12: ='TenantGuard revenue ramp'!I11*('Model inputs'!B18*'Model inputs'!B6+'Model inputs'!B8) -> 340 | J12: ='TenantGuard revenue ramp'!J11*('Model inputs'!B18*'Model inputs'!B6+'Model inputs'!B8) -> 382.5 | K12: ='TenantGuard revenue ramp'!K11*('Model inputs'!B18*'Model inputs'!B6+'Model inputs'!B8) -> 425 | L12: ='TenantGuard revenue ramp'!L11*('Model inputs'!B18*'Model inputs'!B6+'Model inputs'!B8) -> 467.5 | M12: ='TenantGuard revenue ramp'!M11*('Model inputs'!B18*'Model inputs'!B6+'Model inputs'!B8) -> 510
A13: Compute gross profit | B13: ='TenantGuard revenue ramp'!B10-'TenantGuard revenue ramp'!B12 -> 6457.5 | C13: ='TenantGuard revenue ramp'!C10-'TenantGuard revenue ramp'!C12 -> 12915 | D13: ='TenantGuard revenue ramp'!D10-'TenantGuard revenue ramp'!D12 -> 19372.5 | E13: ='TenantGuard revenue ramp'!E10-'TenantGuard revenue ramp'!E12 -> 25830 | F13: ='TenantGuard revenue ramp'!F10-'TenantGuard revenue ramp'!F12 -> 32287.5 | G13: ='TenantGuard revenue ramp'!G10-'TenantGuard revenue ramp'!G12 -> 38745 | H13: ='TenantGuard revenue ramp'!H10-'TenantGuard revenue ramp'!H12 -> 45202.5 | I13: ='TenantGuard revenue ramp'!I10-'TenantGuard revenue ramp'!I12 -> 51660 | ... M13: ='TenantGuard revenue ramp'!M10-'TenantGuard revenue ramp'!M12 -> 77490
A14: Compute gross margin | B14: =IFERROR('TenantGuard revenue ramp'!B13/'TenantGuard revenue ramp'!B10,"") -> 0.99346154 | C14: =IFERROR('TenantGuard revenue ramp'!C13/'TenantGuard revenue ramp'!C10,"") -> 0.99346154 | D14: =IFERROR('TenantGuard revenue ramp'!D13/'TenantGuard revenue ramp'!D10,"") -> 0.99346154 | E14: =IFERROR('TenantGuard revenue ramp'!E13/'TenantGuard revenue ramp'!E10,"") -> 0.99346154 | F14: =IFERROR('TenantGuard revenue ramp'!F13/'TenantGuard revenue ramp'!F10,"") -> 0.99346154 | G14: =IFERROR('TenantGuard revenue ramp'!G13/'TenantGuard revenue ramp'!G10,"") -> 0.99346154 | H14: =IFERROR('TenantGuard revenue ramp'!H13/'TenantGuard revenue ramp'!H10,"") -> 0.99346154 | I14: =IFERROR('TenantGuard revenue ramp'!I13/'TenantGuard revenue ramp'!I10,"") -> 0.99346154 | ... M14: =IFERROR('TenantGuard revenue ramp'!M13/'TenantGuard revenue ramp'!M10,"") -> 0.99346154

Sheet Model inputs
A1: Model inputs
A2: Integration values are aggregated snapshots; raw source records are not included.
A4: Variables
A5: Variable / segment | B5: Value | C5: 2026-08 | D5: 2026-09 | E5: 2026-10 | F5: 2026-11 | G5: 2026-12 | H5: 2027-01 | I5: 2027-02 | J5: 2027-03 | K5: 2027-04 | L5: 2027-05 | M5: 2027-06 | N5: 2027-07 | O5: 2027-08 | P5: 2027-09
A6: Attempts per completed fix | B6: =2.5 -> 2.5
A7: Blended monthly ARPA | B7: =650 -> 650
A8: Compute cost per completed fix | B8: =0.03 -> 0.03
A9: Customer losses | C9: 0 | D9: 0 | E9: ='Model inputs'!E17*'Model inputs'!B16 -> 0 | F9: ='Model inputs'!F17*'Model inputs'!B16 -> 0.1 | G9: ='Model inputs'!G17*'Model inputs'!B16 -> 0.2 | H9: ='Model inputs'!H17*'Model inputs'!B16 -> 0.3 | I9: ='Model inputs'!I17*'Model inputs'!B16 -> 0.4 | J9: ='Model inputs'!J17*'Model inputs'!B16 -> 0.5 | K9: ='Model inputs'!K17*'Model inputs'!B16 -> 0.6 | L9: ='Model inputs'!L17*'Model inputs'!B16 -> 0.7 | M9: ='Model inputs'!M17*'Model inputs'!B16 -> 0.8 | N9: ='Model inputs'!N17*'Model inputs'!B16 -> 0.9 | O9: ='Model inputs'!O17*'Model inputs'!B16 -> 1 | P9: ='Model inputs'!P17*'Model inputs'!B16 -> 1.1
A10: Customer ramp months | B10: =12 -> 12
A11: Ending customers | C11: 0 | D11: 0 | E11: ='Model inputs'!E17+'TenantGuard revenue ramp'!B7-'Model inputs'!E9 -> 10 | F11: ='Model inputs'!F17+'TenantGuard revenue ramp'!C7-'Model inputs'!F9 -> 20 | G11: ='Model inputs'!G17+'TenantGuard revenue ramp'!D7-'Model inputs'!G9 -> 30 | H11: ='Model inputs'!H17+'TenantGuard revenue ramp'!E7-'Model inputs'!H9 -> 40 | I11: ='Model inputs'!I17+'TenantGuard revenue ramp'!F7-'Model inputs'!I9 -> 50 | J11: ='Model inputs'!J17+'TenantGuard revenue ramp'!G7-'Model inputs'!J9 -> 60 | K11: ='Model inputs'!K17+'TenantGuard revenue ramp'!H7-'Model inputs'!K9 -> 70 | L11: ='Model inputs'!L17+'TenantGuard revenue ramp'!I7-'Model inputs'!L9 -> 80 | ... P11: ='Model inputs'!P17+'TenantGuard revenue ramp'!M7-'Model inputs'!P9 -> 120
A12: Fixes per customer per month | B12: =100 -> 100
A13: Forecast month | C13: 0 | D13: 0 | E13: =DATEDIF(DATE(2026,10,1),DATE(2026,10,1),"M")+1 -> 1 | F13: =DATEDIF(DATE(2026,10,1),DATE(2026,11,1),"M")+1 -> 2 | G13: =DATEDIF(DATE(2026,10,1),DATE(2026,12,1),"M")+1 -> 3 | H13: =DATEDIF(DATE(2026,10,1),DATE(2027,1,1),"M")+1 -> 4 | I13: =DATEDIF(DATE(2026,10,1),DATE(2027,2,1),"M")+1 -> 5 | J13: =DATEDIF(DATE(2026,10,1),DATE(2027,3,1),"M")+1 -> 6 | K13: =DATEDIF(DATE(2026,10,1),DATE(2027,4,1),"M")+1 -> 7 | L13: =DATEDIF(DATE(2026,10,1),DATE(2027,5,1),"M")+1 -> 8 | M13: =DATEDIF(DATE(2026,10,1),DATE(2027,6,1),"M")+1 -> 9 | N13: =DATEDIF(DATE(2026,10,1),DATE(2027,7,1),"M")+1 -> 10 | O13: =DATEDIF(DATE(2026,10,1),DATE(2027,8,1),"M")+1 -> 11 | P13: =DATEDIF(DATE(2026,10,1),DATE(2027,9,1),"M")+1 -> 12
A14: Launch customers | B14: =0 -> 0
A15: Month 12 customers | B15: =120 -> 120
A16: Monthly customer churn | B16: =0.01 -> 0.01
A17: Opening customers | C17: 0 | D17: 0 | E17: =IF(IF(IF(ISERROR('Model inputs'!E13=1),'Model inputs'!E13=1,IF('Model inputs'!E13="","",'Model inputs'!E13=1))="",FALSE,IF(ISERROR('Model inputs'!E13=1),'Model inputs'!E13=1,IF('Model inputs'!E13="","",'Model inputs'!E13=1))),IF('Model inputs'!B14="","",'Model inputs'!B14),IF('Model inputs'!D11="","",'Model inputs'!D11)) -> 0 | F17: =IF(IF(IF(ISERROR('Model inputs'!F13=1),'Model inputs'!F13=1,IF('Model inputs'!F13="","",'Model inputs'!F13=1))="",FALSE,IF(ISERROR('Model inputs'!F13=1),'Model inputs'!F13=1,IF('Model inputs'!F13="","",'Model inputs'!F13=1))),IF('Model inputs'!B14="","",'Model inputs'!B14),IF('Model inputs'!E11="","",'Model inputs'!E11)) -> 10 | G17: =IF(IF(IF(ISERROR('Model inputs'!G13=1),'Model inputs'!G13=1,IF('Model inputs'!G13="","",'Model inputs'!G13=1))="",FALSE,IF(ISERROR('Model inputs'!G13=1),'Model inputs'!G13=1,IF('Model inputs'!G13="","",'Model inputs'!G13=1))),IF('Model inputs'!B14="","",'Model inputs'!B14),IF('Model inputs'!F11="","",'Model inputs'!F11)) -> 20 | H17: =IF(IF(IF(ISERROR('Model inputs'!H13=1),'Model inputs'!H13=1,IF('Model inputs'!H13="","",'Model inputs'!H13=1))="",FALSE,IF(ISERROR('Model inputs'!H13=1),'Model inputs'!H13=1,IF('Model inputs'!H13="","",'Model inputs'!H13=1))),IF('Model inputs'!B14="","",'Model inputs'!B14),IF('Model inputs'!G11="","",'Model inputs'!G11)) -> 30 | I17: =IF(IF(IF(ISERROR('Model inputs'!I13=1),'Model inputs'!I13=1,IF('Model inputs'!I13="","",'Model inputs'!I13=1))="",FALSE,IF(ISERROR('Model inputs'!I13=1),'Model inputs'!I13=1,IF('Model inputs'!I13="","",'Model inputs'!I13=1))),IF('Model inputs'!B14="","",'Model inputs'!B14),IF('Model inputs'!H11="","",'Model inputs'!H11)) -> 40 | J17: =IF(IF(IF(ISERROR('Model inputs'!J13=1),'Model inputs'!J13=1,IF('Model inputs'!J13="","",'Model inputs'!J13=1))="",FALSE,IF(ISERROR('Model inputs'!J13=1),'Model inputs'!J13=1,IF('Model inputs'!J13="","",'Model inputs'!J13=1))),IF('Model inputs'!B14="","",'Model inputs'!B14),IF('Model inputs'!I11="","",'Model inputs'!I11)) -> 50 | K17: =IF(IF(IF(ISERROR('Model inputs'!K13=1),'Model inputs'!K13=1,IF('Model inputs'!K13="","",'Model inputs'!K13=1))="",FALSE,IF(ISERROR('Model inputs'!K13=1),'Model inputs'!K13=1,IF('Model inputs'!K13="","",'Model inputs'!K13=1))),IF('Model inputs'!B14="","",'Model inputs'!B14),IF('Model inputs'!J11="","",'Model inputs'!J11)) -> 60 | L17: =IF(IF(IF(ISERROR('Model inputs'!L13=1),'Model inputs'!L13=1,IF('Model inputs'!L13="","",'Model inputs'!L13=1))="",FALSE,IF(ISERROR('Model inputs'!L13=1),'Model inputs'!L13=1,IF('Model inputs'!L13="","",'Model inputs'!L13=1))),IF('Model inputs'!B14="","",'Model inputs'!B14),IF('Model inputs'!K11="","",'Model inputs'!K11)) -> 70 | M17: =IF(IF(IF(ISERROR('Model inputs'!M13=1),'Model inputs'!M13=1,IF('Model inputs'!M13="","",'Model inputs'!M13=1))="",FALSE,IF(ISERROR('Model inputs'!M13=1),'Model inputs'!M13=1,IF('Model inputs'!M13="","",'Model inputs'!M13=1))),IF('Model inputs'!B14="","",'Model inputs'!B14),IF('Model inputs'!L11="","",'Model inputs'!L11)) -> 80 | N17: =IF(IF(IF(ISERROR('Model inputs'!N13=1),'Model inputs'!N13=1,IF('Model inputs'!N13="","",'Model inputs'!N13=1))="",FALSE,IF(ISERROR('Model inputs'!N13=1),'Model inputs'!N13=1,IF('Model inputs'!N13="","",'Model inputs'!N13=1))),IF('Model inputs'!B14="","",'Model inputs'!B14),IF('Model inputs'!M11="","",'Model inputs'!M11)) -> 90 | O17: =IF(IF(IF(ISERROR('Model inputs'!O13=1),'Model inputs'!O13=1,IF('Model inputs'!O13="","",'Model inputs'!O13=1))="",FALSE,IF(ISERROR('Model inputs'!O13=1),'Model inputs'!O13=1,IF('Model inputs'!O13="","",'Model inputs'!O13=1))),IF('Model inputs'!B14="","",'Model inputs'!B14),IF('Model inputs'!N11="","",'Model inputs'!N11)) -> 100 | P17: =IF(IF(IF(ISERROR('Model inputs'!P13=1),'Model inputs'!P13=1,IF('Model inputs'!P13="","",'Model inputs'!P13=1))="",FALSE,IF(ISERROR('Model inputs'!P13=1),'Model inputs'!P13=1,IF('Model inputs'!P13="","",'Model inputs'!P13=1))),IF('Model inputs'!B14="","",'Model inputs'!B14),IF('Model inputs'!O11="","",'Model inputs'!O11)) -> 110
A18: Token cost per attempt | B18: =0.005 -> 0.005
